Workbook

Sheet Orçam-Realiza
B1: AGROINVEST | C1: AGROINVEST | D1: AGROINVEST | E1: AGROINVEST | F1: AGROINVEST | G1: AGROINVEST | H1: AGROINVEST | I1: AGROINVEST | J1: AGROINVEST
B2: 2025-2026 (01 Outubro - 30 Setembro) | C2: 2025-2026 (01 Outubro - 30 Setembro) | D2: 2025-2026 (01 Outubro - 30 Setembro) | E2: 2025-2026 (01 Outubro - 30 Setembro) | F2: 2025-2026 (01 Outubro - 30 Setembro) | G2: 2025-2026 (01 Outubro - 30 Setembro) | H2: 2025-2026 (01 Outubro - 30 Setembro) | I2: 2025-2026 (01 Outubro - 30 Setembro) | J2: 2025-2026 (01 Outubro - 30 Setembro) | AB2: =$AB$16+(AD2*$AB$19) | AD2: 1.2
B3: Fatores Importantes : | AB3: =$AB$16+(AD3*$AB$19) | AD3: 1.15
D4: Algodão | F4: Soja | H4: Milho | J4: Caroço | L4: Total | AB4: =$AB$16+(AD4*$AB$19) | AD4: 1.1
C5: Hectares de Produção (todas fazendas) | D5: 0 | F5: 900 | H5: 1380 | J5: N/A | L5: =D5+F5+H5 | AB5: =$AB$16+(AD5*$AB$19) | AD5: 1.05
D6: =D5/$L5 | F6: =F5/$L5 | H6: =H5/$L5 | L6: =SUM(D6:K6) | AB6: =D80 | AD6: 1 | AE6: = 100% Metas / Bonus / 70% salario bruta
C7: Hectares de Produção (parte de CF) | D7: 0 | F7: =F5 | G7: 5750 | H7: =H5 | J7: N/A | L7: =D7+F7+H7 | M7: Produtividade reducao: | AB7: =$AB$16+(AD7*$AB$19) | AD7: 0.9
C8: (Carroll, mais de um terço das outras fazendas) | D8: =D7/$L7 | F8: =F7/$L7 | H8: =H7/$L7 | L8: =SUM(D8:K8) | AA8: 0 | AB8: =$AB$16+(AD8*$AB$19) | AD8: 0.75
AA9: =AB6-AA10 | AB9: =$AB$16+(AD9*$AB$19) | AD9: 0.65
C10: Pressupostos de Produção | D10: 0 | F10: 70 | H10: 180 | J10: N/A | M10: Resultado: (realizado orçamento) | AB10: =$AB$16+(AD10*$AB$19) | AD10: 0.5
D11: Arrobas/HA | F11: Sacas/HA | H11: Sacas/HA | M11: Receita algodao | AA11: =D43 | AB11: =$AB$16+(AD11*$AB$19) | AD11: 0.4
M12: Receita milho | AA12: =D45 | AB12: =$AB$16+(AD12*$AB$19) | AD12: 0.25
C13: Os Preços-Alvo - USD | D13: 0 | F13: 20 | H13: =60/D29 | M13: Receita soja | P13: Total Arrobas: | Q13: 465439.97 | AA13: =D44 | AB13: =$AB$16+(AD13*$AB$19) | AD13: 0.2
C14: (Vamos utilizar o preço médio de venda fixo para produção total) | D14: Por lb | F14: Por Saca | H14: Por Saca | J14: Por tonelada | P14: Total Kilos: | Q14: =Q13*15 | AB14: =$AB$16+(AD14*$AB$19) | AD14: 0.15
C15: (Vamos utilizar o preço médio de venda fixo para produção total) | P15: Total Pounds: | Q15: =Q14/0.45359237 | AB15: =$AB$16+(AD15*$AB$19) | AD15: 0.1
C16: Os Preços-Alvo - BRL | D16: =D13*2.2046*D29*15 | F16: =F13*D29 | H16: =H13*D29 | J16: =J13*D29 | P16: Total Reais: | Q16: =Q15*D13*D29 | AB16: 1813938 | AD16: 0
D17: Por Arroba | F17: Por Saca | H17: Por Saca | J17: Por tonelada | P17: Check: | Q17: =Q16-D43
C19: Custo do descaroçamento por arroba pluma | D19: 8.25 | AB19: =AB6-AB16
AB20: =1-(AA9/AB19) | AC20: =(AC21*AB20)/AB21 | AD20: Meta
C21: Percentual vendidos no Pessoa Juridica | D21: 1 | F21: =D19-F19 | AB21: 100 | AC21: 70
C22: Percentual da algodão exportado | D22: 1
C23: Percentual da soja e milho vendidos na Bahia | D23: 1
C24: Percentual da caroço vendidos para indústria | D24: 1
C26: Pluma Percentuais | D26: 0.4 | J26: 0.52
C28: Subsídios | D28: 0
C29: Taxa de câmbio (R$ por USD) | D29: 5.4 | F29: BRL/USD
C32: Em EUA dolares $$ por hectare | D32: =D35 | F32: =F35 | H32: =H35
C33: Custo defensivos, adubo, e semente - 24/25 | D33: 0 | F33: ='Quimi. Fert. Semente'!G27 | H33: ='Quimi. Fert. Semente'!G28
D34: 0 | F34: =(F33*D29)-F36 | H34: =(H33*D29)-H36
C35: Em BR reais R$ por hectare | D35: =D4 | F35: =F4 | H35: =H4
C36: Custo projetado de produção 25-26 | D36: 0 | F36: ='Quimi. Fert. Semente'!G22*'Orçam-Realiza'!D29 | H36: ='Quimi. Fert. Semente'!G23*'Orçam-Realiza'!D29
C37: Custo do ano anterior de produção - 2024 | D37: 0 | F37: =F33*D29 | H37: =H33*D29
O39: Algodão | Q39: Soja | S39: Milho
D40: 2025 - 2026 Safra | O40: 3801.3676 | P40: =O40/Q40 | Q40: 1154.5599 | S40: 1647.2279
F41: Percentual da | O41: =D5 | Q41: =F5 | S41: =H5
D42: BRL$ | F42: Receitas
C43: Vendas de algodão | D43: =D16*D10*D26*(D7+H43) | F43: =D43/$D$48
C44: Vendas de soja | D44: =F16*F10*F7 | F44: =D44/$D$48 | O44: 10327 | Q44: 392 | S44: 691
C45: Vendas de milho | D45: =H16*H10*H7 | F45: =D45/$D$48
B46: RECEITAS | C46: Vendas de caroço | D46: =(D10*D7*J26*15)/1000*J16 | F46: =D46/$D$48
C47: Subsídio | D47: =D28 | F47: =D47/$D$48
C48: Receita Operacional Bruta | D48: =SUM(D43:D47) | F48: =D48/$D$48 | J48: 0.0353
C49: (-) Deduções Vendas Tributos | D49: =((0.25+1.2+1.08+1)%*D48)*-1 | F49: =D49/$D$48
D50: 0 | F50: =D50/$D$48
D51: 0 | F51: Se tiver, estes serão removidos diretamente do Receita Liquida | G51: Se tiver, estes serão removidos diretamente do Receita Liquida | H51: Se tiver, estes serão removidos diretamente do Receita Liquida | I51: Se tiver, estes serão removidos diretamente do Receita Liquida | J51: Se tiver, estes serão removidos diretamente do Receita Liquida | K51: Se tiver, estes serão removidos diretamente do Receita Liquida | L51: Se tiver, estes serão removidos diretamente do Receita Liquida
D52: 0 | F52: Se tiver, estes serão removidos diretamente do Receita Liquida | G52: Se tiver, estes serão removidos diretamente do Receita Liquida | H52: Se tiver, estes serão removidos diretamente do Receita Liquida | I52: Se tiver, estes serão removidos diretamente do Receita Liquida | J52: Se tiver, estes serão removidos diretamente do Receita Liquida | K52: Se tiver, estes serão removidos diretamente do Receita Liquida | L52: Se tiver, estes serão removidos diretamente do Receita Liquida
C53: Receita Operacional Líquida | D53: =SUM(D48:D52) | F53: =D53/$D$48
H54: alvo | J54: actual | L54: Variencia
B55: (-) Indenização trabalhistas e ambientais | C55: (-) Milho Adubo (N,P,K,Calcario) | D55: =-'Quimi. Fert. Semente'!N6*'Orçam-Realiza'!D29 | F55: =D55/$D$79 | L55: =H55-J55 | Q55: Seed | S55: Chemical | U55: Fertilizer | V55: Total
B56: (-) Multas de Fiscalização | C56: (-) Milho Semente | D56: =-'Quimi. Fert. Semente'!D8*'Orçam-Realiza'!D29 | F56: =D56/$D$79 | L56: =H56-J56 | Q56: Seed | S56: Chemical | U56: Fertilizer | V56: Total
C57: (-) Milho Defensivos | D57: =-'Quimi. Fert. Semente'!I8*'Orçam-Realiza'!D29 | F57: =D57/$D$79 | L57: =H57-J57
C58: (-) Soja Adubo (N,P,K,Calcario) | D58: =-'Quimi. Fert. Semente'!N5*'Orçam-Realiza'!D29 | F58: =D58/$D$79 | L58: =H58-J58
C59: (-) Soja Semente | D59: =-'Quimi. Fert. Semente'!D5*'Orçam-Realiza'!D29 | F59: =D59/$D$79 | L59: =H59-J59
C60: (-) Soja Defensivos | D60: =-'Quimi. Fert. Semente'!I5*'Orçam-Realiza'!D29 | F60: =D60/$D$79 | L60: =H60-J60
C61: (-) Algodão Adubo (N,P,K,Calcario) | D61: =-('[1]Quimic. Fertil. Sement.'!N7)*4 | F61: =D61/$D$79 | L61: =H61-J61
C62: (-) Algodão Semente | D62: =-(SUM('[1]Quimic. Fertil. Sement.'!D10:D13))*4 | F62: =D62/$D$79 | L62: =H62-J62
C63: (-) Algdodão Defensivos | D63: =-(SUM('[1]Quimic. Fertil. Sement.'!I10:I13))*4 | F63: =D63/$D$79 | L63: =H63-J63
B64: (-) C.P.V (Custo do Produção Vendido) | C64: (-) arrendamento | F64: =D64/$D$79 | L64: 0 | Q64: Seed | S64: Chemical | U64: Fertilizer | V64: Total
C65: (-) Salários, Provisões e Encargos (fazenda) | D65: =-'Orçamento Resumo'!K15 | F65: =D65/$D$79 | L65: =H65-J65 | M65: =(D65/5750) | P65: 116.09252 | Q65: 982142.72 | R65: 489 | S65: 4136940 | T65: 355.90748 | U65: 3010977.3 | V65: =T65+R65+P65 | W65: =U65+S65+Q65
C66: (-) Combustível e óleo | D66: =-SUM('Orçamento Resumo'!B15:D15) | F66: =D66/$D$79 | L66: =H66-J66 | M66: =(D66/5750) | P66: 44 | Q66: 17600 | R66: 290.464 | S66: 116185.6 | T66: 152.93 | U66: 61172 | V66: =T66+R66+P66 | W66: =U66+S66+Q66
C67: (-) Avião | D67: =-'Orçamento Resumo'!L15 | F67: =D67/$D$79 | L67: =H67-J67 | M67: =(D67/5750)
C68: (-) Depreciação (fazenda) | D68: =-'Deprecisação '!Q174 | F68: =D68/$D$79 | L68: 0 | M68: =(D68/5750) | Q68: =SUM(Q65:Q66) | S68: =SUM(S65:S66) | U68: =SUM(U65:U66) | V68: =SUM(V65:V66) | W68: =SUM(W65:W66)
C69: (-) Manutenção, Concerto e Peças | D69: =-'Orçamento Resumo'!E15 | F69: =D69/$D$79 | L69: =H69-J69 | M69: =(D69/5750)
C70: (-) Alimentos | D70: =-'Orçamento Resumo'!P15 | F70: =D70/$D$79 | L70: =H70-J70 | M70: =(D70/5750)
C71: (-) Contratacao Serviços/Frete (terceiros) | D71: =-'Orçamento Resumo'!M15 | F71: =D71/$D$79 | L71: =H71-J71 | M71: =(D71/5750)
C72: (-) Silo Bag | D72: =-'Orçamento Resumo'!F15 | F72: =D72/$D$79 | L72: =H72-J72 | M72: =(D72/5750)
C73: (-) Veiculo | D73: =-'Orçamento Resumo'!G15 | F73: =D73/$D$79 | L73: =H73-J73 | M73: =(D73/5750)
C74: (-) Seguros | D74: =-'Orçamento Resumo'!N15 | F74: =D74/$D$79 | L74: =H74-J74 | M74: =(D74/5750)
C75: (-) Suprimentos | D75: =-'Orçamento Resumo'!I15 | F75: =D75/$D$79 | L75: =H75-J75 | M75: =(D75/5750)
C76: (-) Utilidades (fazenda) | D76: =-'Orçamento Resumo'!O15 | F76: =D76/$D$79 | L76: =H76-J76 | M76: =(D76/5750)
C77: (-) Aluguel de carro | D77: =-'Orçamento Resumo'!H15 | F77: =D77/$D$79 | L77: =H77-J77 | M77: =(D77/5750)
C78: (-) Serviços profissionais | D78: =-'Orçamento Resumo'!J15 | F78: =D78/$D$79 | L78: =H78-J78 | M78: =(D78/5750)
D79: =SUM(D55:D78) | F79: =SUM(F55:F78) | H79: =SUM(H55:H78) | J79: =SUM(J55:J78) | K79: =SUM(K55:K78) | L79: =SUM(L55:L78) | M79: =SUM(M66:M78)
C80: Lucro Bruto | D80: =D53+D79 | F80: =D80/$D$48
C82: (-) Despesas Administrativo | D82: -300000 | F82: =D82/$D$48 | U82: =V82/2.471 | V82: 961 | W82: 8130060
B83: (-) Total C.P.V | C83: (-) Despesas Frete e Trans | D83: 0 | F83: =D83/$D$48 | Q83: Seed | S83: Chemical | U83: Fertilizer | V83: Total
C84: (-) Despesas EUA | D84: 0 | F84: =D84/$D$48
B85: (-) Despesas Administrativo e Operacionais | C85: (-) Despesas Comerciais | D85: 0 | F85: =D85/$D$48 | Q85: Seed | S85: Chemical | U85: Fertilizer | V85: Total
D86: =SUM(D82:D85) | F86: =D86/$D$48 | U86: =V86/2.471 | V86: 709 | W86: 910356
C87: Lucro Operacional | D87: =D80+D86 | F87: =D87/$D$48 | W87: =SUM(W83:W86)
C89: (+/-) Ganho/Perda em activos | D89: 0 | F89: =D89/$D$48
B90: (-) Total Despesas Admin e Operacionais | C90: (+/-) Impostos | D90: =-(SUM((D43+D44)*2.28%)+SUM(D45*5.13%)) | F90: =D90/$D$48 | Q90: Seed | S90: Chemical | U90: Fertilizer | V90: Total
C91: (+/-) Renda de Juros | F91: =D91/$D$48
B92: (+/-) Outras Receitas e Despesas | C92: (+/-) Despesas de Juros | F92: =D92/$D$48 | Q92: Seed | S92: Chemical | U92: Fertilizer | V92: Total
C93: (+/-) Receitas diversas | F93: =D93/$D$48 | U93: =V93/2.471 | V93: 709 | W93: 910356
D94: =SUM(D89:D93) | F94: =D94/$D$48
W95: =SUM(W89:W93)
C96: Lucro Líquido | D96: =D87+D94 | F96: =D96/$D$48
B98: (+/-) Total Outras Receitas e Despesas | Q98: Seed | S98: Chemical | U98: Fertilizer | V98: Total
D101: Custo/há | E101: Custo/há | F101: Custo/há
D102: Custo Operaciona + Arrendametno | F102: Sem arrendamento
D103: =(SUM(D64:D78)/2300)*-1 | F103: =(SUM(D65:D78)/2300)*-1
D104: =D103/D29 | F104: =D103/D29

Sheet Orçamento Resumo
A1: ORÇAMENTO 22-23 | B1: ORÇAMENTO 22-23 | C1: ORÇAMENTO 22-23 | D1: ORÇAMENTO 22-23 | E1: ORÇAMENTO 22-23
B2: DIESEL | C2: Gasolina | D2: Lubrificantes | E2: Peças e concertos | F2: Silo bolsa | G2: Veiculos | H2: Aluguel de carro/trator | I2: Suprimentos | J2: Serviços Proficionais | K2: Salarios, Provisões e Encargos | L2: Avião | M2: Contratação Serviços | N2: Seguros | O2: Utilidades Fazenda | P2: Alimentos | Q2: Fertilizante | R2: Quimicos | S2: Semente
A3: Outubro | B3: ='Combust. Lubrif'!$D$27*0.09 | C3: ='Combust. Lubrif'!$K$3/12 | D3: ='Combust. Lubrif'!L23/12 | E3: ='peças '!C28 | I3: ='Supriment-Ser Profiss'!$C$96/12 | J3: ='Supriment-Ser Profiss'!$H$82/12 | K3: ='Folha pagamento '!N24/14 | N3: 96000 | O3: ='Utilidades e Veiculos'!P3 | P3: ='Alimentação '!E85 | T3: =SUM(B3:S3)
A4: Novembro | B4: ='Combust. Lubrif'!$D$27*0.09 | C4: ='Combust. Lubrif'!$K$3/12 | D4: ='Combust. Lubrif'!L23/12 | E4: ='peças '!D28 | I4: ='Supriment-Ser Profiss'!$C$96/12 | J4: ='Supriment-Ser Profiss'!$H$82/12 | K4: ='Folha pagamento '!N24/14+'Folha pagamento '!N29 | O4: ='Utilidades e Veiculos'!P4 | P4: ='Alimentação '!G85 | T4: =SUM(B4:S4)
A5: Dezembro | B5: ='Combust. Lubrif'!$D$27*0.09 | C5: ='Combust. Lubrif'!$K$3/12 | D5: ='Combust. Lubrif'!L23/12 | E5: ='peças '!E28 | I5: ='Supriment-Ser Profiss'!$C$96/12 | J5: ='Supriment-Ser Profiss'!$H$82/12 | K5: ='Folha pagamento '!N24/14+'Folha pagamento '!N29 | L5: =Avião!$Q$99/5 | O5: ='Utilidades e Veiculos'!P5 | P5: ='Alimentação '!I85 | T5: =SUM(B5:S5)
A6: Janeiro | B6: ='Combust. Lubrif'!D27*0.1 | C6: ='Combust. Lubrif'!$K$3/12 | D6: ='Combust. Lubrif'!L23/12 | E6: ='peças '!F28 | G6: ='Utilidades e Veiculos'!H63 | I6: ='Supriment-Ser Profiss'!$C$96/12 | J6: ='Supriment-Ser Profiss'!$H$82/12 | K6: ='Folha pagamento '!N24/14 | L6: =Avião!$Q$99/5 | O6: ='Utilidades e Veiculos'!P6 | P6: ='Alimentação '!K85 | T6: =SUM(B6:S6)
A7: Fevereiro | B7: ='Combust. Lubrif'!D27*0.1 | C7: ='Combust. Lubrif'!$K$3/12 | D7: ='Combust. Lubrif'!L23/12 | E7: ='peças '!G28 | F7: ='Contratação serviç.'!I17/3 | I7: ='Supriment-Ser Profiss'!$C$96/12 | J7: ='Supriment-Ser Profiss'!$H$82/12 | K7: ='Folha pagamento '!N24/14 | L7: =Avião!$Q$99/5 | O7: ='Utilidades e Veiculos'!P7 | P7: ='Alimentação '!M85 | T7: =SUM(B7:S7)
A8: Março | B8: ='Combust. Lubrif'!D27*0.11 | C8: ='Combust. Lubrif'!$K$3/12 | D8: ='Combust. Lubrif'!L23/12 | E8: ='peças '!H28 | F8: ='Contratação serviç.'!I17/3 | I8: ='Supriment-Ser Profiss'!$C$96/12 | J8: ='Supriment-Ser Profiss'!$H$82/12 | K8: ='Folha pagamento '!N24/14+'Folha pagamento '!N29 | L8: =Avião!$Q$99/5 | M8: ='Contratação serviç.'!$B$19/3 | O8: ='Utilidades e Veiculos'!P8 | P8: ='Alimentação '!O85 | T8: =SUM(B8:S8)
A9: Abril | B9: ='Combust. Lubrif'!D27*0.11 | C9: ='Combust. Lubrif'!$K$3/12 | D9: ='Combust. Lubrif'!L23/12 | E9: ='peças '!I28 | F9: ='Contratação serviç.'!I17/3 | I9: ='Supriment-Ser Profiss'!$C$96/12 | J9: ='Supriment-Ser Profiss'!$H$82/12 | K9: ='Folha pagamento '!N24/14 | L9: =Avião!$Q$99/5 | M9: ='Contratação serviç.'!$B$19/3 | O9: ='Utilidades e Veiculos'!P9 | P9: ='Alimentação '!Q85 | T9: =SUM(B9:S9)
A10: Maio | B10: ='Combust. Lubrif'!D27*0.11 | C10: ='Combust. Lubrif'!$K$3/12 | D10: ='Combust. Lubrif'!L23/12 | E10: ='peças '!J28 | I10: ='Supriment-Ser Profiss'!$C$96/12 | J10: ='Supriment-Ser Profiss'!$H$82/12 | K10: ='Folha pagamento '!N24/14 | M10: ='Contratação serviç.'!$B$19/3 | O10: ='Utilidades e Veiculos'!P10 | P10: ='Alimentação '!S85 | T10: =SUM(B10:S10)
A11: Junho | B11: ='Combust. Lubrif'!D27*0.07 | C11: ='Combust. Lubrif'!$K$3/12 | D11: ='Combust. Lubrif'!L23/12 | E11: ='peças '!K28 | I11: ='Supriment-Ser Profiss'!$C$96/12 | J11: ='Supriment-Ser Profiss'!$H$82/12 | K11: ='Folha pagamento '!N24/14 | O11: ='Utilidades e Veiculos'!P11 | P11: ='Alimentação '!U85 | T11: =SUM(B11:S11)
A12: Julho | B12: ='Combust. Lubrif'!D27*0.07 | C12: ='Combust. Lubrif'!$K$3/12 | D12: ='Combust. Lubrif'!L23/12 | E12: ='peças '!L28 | I12: ='Supriment-Ser Profiss'!$C$96/12 | J12: ='Supriment-Ser Profiss'!$H$82/12 | K12: ='Folha pagamento '!N24/14 | O12: ='Utilidades e Veiculos'!P12 | P12: ='Alimentação '!W85 | T12: =SUM(B12:S12)
A13: Agosto | B13: ='Combust. Lubrif'!D27*0.03 | C13: ='Combust. Lubrif'!$K$3/12 | D13: ='Combust. Lubrif'!L23/12 | E13: ='peças '!M28 | I13: ='Supriment-Ser Profiss'!$C$96/12 | J13: ='Supriment-Ser Profiss'!$H$82/12 | K13: ='Folha pagamento '!N24/14 | O13: ='Utilidades e Veiculos'!P13 | P13: ='Alimentação '!Y85 | T13: =SUM(B13:S13) | V13: U$$/há
A14: Setembro | B14: ='Combust. Lubrif'!D27*0.03 | C14: ='Combust. Lubrif'!$K$3/12 | D14: ='Combust. Lubrif'!L23/12 | E14: ='peças '!N28 | I14: ='Supriment-Ser Profiss'!$C$96/12 | J14: ='Supriment-Ser Profiss'!$H$82/12 | K14: ='Folha pagamento '!N24/14+'Folha pagamento '!N29 | O14: ='Utilidades e Veiculos'!P14 | P14: ='Alimentação '!AA85 | T14: =SUM(B14:S14) | U14: =U15/2300 | V14: =U14/5.6
A15: Total | B15: =SUM(B3:B14) | C15: =SUM(C3:C14) | D15: =SUM(D3:D14) | E15: =SUM(E3:E14) | F15: =SUM(F3:F14) | G15: =SUM(G3:G14) | H15: =SUM(H3:H14) | I15: =SUM(I3:I14) | ... P15: =SUM(P3:P14) | Q15: ='Quimi. Fert. Semente'!N10 | R15: ='Quimi. Fert. Semente'!I15 | S15: ='Quimi. Fert. Semente'!D15 | T15: =SUM(B15:S15) | U15: =SUM(B15:P15)+1282000
A17: 24-25 | B17: 873061 | C17: 873061 | D17: 873061 | E17: 767995 | F17: 16516 | G17: 8733 | H17: 4646 | I17: 142786 | J17: 812270 | K17: 995123 | L17: 410999 | M17: 871101 | N17: 94566 | O17: 83550 | P17: 196587 | Q17: 2758778.5 | R17: 2067511.2 | S17: 1511168.3 | T17: 10986279 | U17: 5930820.7
A18: Realizado 23-24 | B18: 700501.45 | C18: 700501.45 | D18: 700501.45 | E18: 687314.62 | F18: 17629.37 | G18: 7284.81 | H18: 0 | I18: 97114.28 | J18: 644446.82 | K18: 896802.99 | L18: -271514.77 | M18: 1022660.5 | N18: 69423.5 | O18: 104331.61 | P18: 165702.01 | Q18: 2424711 | R18: 2483600 | S18: 2042476 | T18: =SUM(B18:S18) | U18: =SUM(B18:P18) | V18: =(T15/T21)-1
A19: Realizado 23-24 | B19: 1007230 | C19: 1007230 | D19: 1007230 | E19: 442901.09 | F19: 11440 | G19: 7497.47 | H19: 0 | I19: 133422 | J19: 907493.23 | K19: 714449.57 | L19: 332262.36 | M19: 1063200 | N19: 33859.32 | O19: 137089.96 | P19: 152681.36 | Q19: 2122830 | R19: 1812595 | S19: 1829700 | T19: =SUM(B19:S19)
A20: Realizado 22-23 | B20: 1072358 | C20: 1072358 | D20: 1072358 | E20: 816622 | F20: 95121 | G20: 5660 | H20: 109000 | I20: 160587 | J20: 395630 | K20: 1065858 | L20: 335462 | M20: 2866224 | O20: 184570 | P20: 254116
A21: Realizado 21-22 | B21: 1717934 | C21: 1717934 | D21: 1717934 | E21: 960925 | F21: 188221 | G21: 9150 | H21: 43707 | I21: 71842 | J21: 298686 | K21: 1003922 | L21: 216259 | M21: 2667281 | O21: 153895 | P21: 225555 | Q21: 4537127 | R21: 5666912 | S21: 2825189 | T21: =SUM(B21:S21)
A22: Realizado 20-21 | B22: 578356.23 | C22: 578356.23 | D22: 578356.23 | E22: 162336.64 | F22: 53067.13 | G22: 5046.22 | H22: 0 | I22: 56679.488 | J22: 242050.96 | K22: 661110.68 | L22: 305977.24 | M22: 2178115 | N22: 0 | O22: 86875 | P22: 99000 | Q22: 0 | R22: 4849531 | S22: 2171360 | T22: =SUM(B22:S22)
A25: custo/há orçado | B25: =B15:D15/2300 | C25: =B15:D15/2300 | D25: =B15:D15/2300 | E25: =E15/2300 | F25: =F15/2300 | G25: =G15/2300 | H25: =H15/2300 | I25: =I15/2300 | J25: =J15/2300 | K25: =K15/2300 | L25: =L15/2300 | ... P25: =P15/2300
A27: Custo/há realizado | B27: =B17/2300 | C27: =B17/2300 | D27: =B17/2300 | E27: =E17/2300 | F27: =F17/2300 | G27: =G17/2300 | H27: =H17/2300 | I27: =I17/2300 | J27: =J17/2300 | K27: =K17/2300 | L27: =L17/2300 | ... P27: =P17/2300
G31: =SUM(C8,H8,M6) | H31: 888 | J31: =I31*5.2
I32: =SUM(I27:I31) | J32: =SUM(J27:J31)
G34: 347.57 | H34: 4127 | O34: =SUM(B15:P15)/2300
G35: 667.19 | H35: 1642 | O35: =O34/5.4

Sheet Combust. Lubrif
A1: Operação | B1: Media | C1: hectar/KM/hora | D1: total diesel | G1: Lubrificantes e Combustiveis
A2: Colheita Soja | B2: 13 | C2: 900 | D2: =C2*B2
A3: colheita milho | B3: 14 | C3: 1380 | D3: =C3*B3 | G3: Gasolina | H3: lts | I3: 6.4 | J3: 1300 | K3: =SUM(J3*I3)
A4: Colheita sementes cobertura | B4: 7 | C4: 200 | D4: =C4*B4
A5: Colheita de sorgo | B5: 8 | C5: 500 | D5: =C5*B5 | G5: Oleo 20w50 moto | H5: lts | I5: 26 | J5: 12 | K5: =SUM(J5*I5)
A6: Plantio Soja | B6: 4.57 | C6: 900 | D6: =B6*C6
A7: Plantio Milho | B7: 5 | C7: 1380 | D7: =C7*B7 | G7: graxa mineral | H7: Kgs | I7: 30 | J7: 60 | K7: =SUM(J7*I7)
A8: Plantio braquiaria | B8: 1.63 | C8: 1380 | D8: =C8*B8 | G8: Oleo plus 50 II | H8: lts | I8: 37 | J8: 60 | K8: =SUM(J8*I8)
A9: preparo de solo | B9: 20 | C9: 900 | D9: =C9*B9 | G9: Oleo 85w140 cubo | H9: lts | I9: 130 | J9: 24 | K9: =SUM(J9*I9)
A10: Semeadura milheto | B10: 0.84 | C10: 500 | D10: =C10*B10 | G10: Oleo cambio | H10: lts | I10: 70 | J10: 10 | K10: =SUM(J10*I10)
A11: Adubação a lanço KCl | B11: 0.75 | C11: 2350 | D11: =C11*B11 | G11: Oleo selenia 10w30 | H11: lts | I11: 40 | J11: 4 | K11: =SUM(J11*I11)
A12: Adubação a lanço SS | B12: 0.75 | C12: 1600 | D12: =C12*B12 | G12: Oleo plus 50 4 | H12: lts | I12: 35 | J12: 80 | K12: =SUM(J12*I12)
A13: Adubação plantio | B13: 4 | C13: 915 | D13: =C13*B13 | G13: Oleo 15w40 | H13: lts | I13: 25 | J13: 400 | K13: =SUM(J13*I13)
A14: Ureia | B14: 1.3 | C14: 2300 | D14: =C14*B14 | G14: OLEO 424 | H14: lts | I14: 30 | J14: 350 | K14: =SUM(J14*I14)
A15: Aplicação quimicos | B15: 0.7 | C15: 15000 | D15: =C15*B15 | G15: OLEO 68 | H15: lts | I15: 20 | J15: 60 | K15: =SUM(J15*I15)
A16: Manutençao de estrradas | C16: 677.9661 | D16: 4000
A17: F4000 melosa | C17: 508.47458 | D17: 3000
A18: S10 Schu | C18: 406.77966 | D18: 2400
A19: F4000 aplicaçao | C19: 508.47458 | D19: 3000
A20: S10 Romerio | C20: 932.20339 | D20: 5500 | G20: dulub ATF | H20: lts | I20: 24 | J20: 12 | K20: =SUM(J20*I20)
A21: Pa carregadeira | C21: 677.9661 | D21: 4000 | G21: oleo lub. Ciser 300ml/200GRS | H21: PC | I21: 12.2 | J21: 4 | K21: =SUM(J21*I21)
A22: JD5403 | C22: 169.49153 | D22: 1000 | G22: Oleo SAE 10 | H22: lts | I22: 32 | J22: 4 | K22: =SUM(J22*I22)
A23: Ford cargo | C23: 508.47458 | D23: 3000 | G23: Oleo Dot 4 | H23: lts | I23: 32 | J23: 8 | K23: =SUM(J23*I23) | L23: =SUM(K4:K23)
A24: Ts | C24: 16.949153 | D24: 100
A25: Compras | C25: 254.23729 | D25: 1500
D26: =SUM(D2:D25)
D27: =D26*5.9

Sheet peças 
A1: Máquinas N | B1: Numero | C1: Outubro | D1: Novembro | E1: Dezembro | F1: Janeiro | G1: Fevereiro | H1: Março | I1: Abril | J1: Maio | K1: Junho | L1: Julho | M1: Agosto | N1: Setembro | O1: Total P/ Maquina 20/21
A2: Pa | B2: 95 | C2: 2500 | H2: 2500 | K2: 1300 | L2: 500 | O2: =SUM(C2:N2)
A3: M4030 | B3: 87 | C3: 40000 | D3: 5000 | E3: 5300 | F3: 6200 | G3: 5200 | H3: 4000 | I3: 2500 | J3: 4200 | K3: 10000 | L3: 6500 | M3: 3500 | N3: 15000 | O3: =SUM(C3:N3)
A4: DN4040 | C4: 3000 | D4: 2500 | E4: 600 | F4: 300 | G4: 2400 | H4: 500 | I4: 300 | K4: 6000 | N4: 12000 | O4: =SUM(C4:N4)
A5: Plant Braquiaria | C5: 1200 | D5: 1200 | M5: 2500 | O5: =SUM(C5:N5)
A6: Plant 2134 | B6: 10 | D6: 1700 | J6: 12000 | K6: 600 | L6: 600 | N6: 2000 | O6: =SUM(C6:N6)
A7: DB | B7: 55 | C7: 5100 | D7: 3000 | E7: 6300 | F7: 2500 | G7: 3100 | M7: 8000 | O7: =SUM(C7:N7)
A8: 8370R | B8: 32 | C8: 12000 | D8: 6000 | E8: 2400 | F8: 1200 | G8: 30000 | H8: 15000 | I8: 1875 | J8: 3000 | K8: 12000 | O8: =SUM(C8:N8)
A9: 8335R | B9: 41 | C9: 8000 | D9: 6000 | E9: 3100 | F9: 10000 | H9: 19000 | K9: 30000 | O9: =SUM(C9:N9)
A10: 5403 | B10: 35 | C10: 2500 | D10: 3200 | E10: 450 | H10: 600 | I10: 600 | J10: 450 | N10: 3500 | O10: =SUM(C10:N10)
A11: Bross preta | B11: 24 | C11: 800 | D11: 200 | E11: 200 | I11: 200 | M11: 600 | O11: =SUM(C11:N11)
A12: Bros | B12: 97 | C12: 800 | D12: 350 | I12: 350 | N12: 800 | O12: =SUM(C12:N12)
A13: Tilleer GTS | B13: 107 | I13: 2000 | O13: =SUM(C13:N13)
A14: Terrus Gts 12 H | B14: 109 | C14: 8000 | H14: 3500 | O14: =SUM(C14:N14)
A15: Rolo faca | D15: 2000 | O15: =SUM(C15:N15)
A16: Extratora | B16: 105 | O16: =SUM(C16:N16)
A17: F4000 | B17: 74 | C17: 5300 | D17: 1200 | E17: 1200 | F17: 600 | G17: 910 | H17: 4600 | O17: =SUM(C17:N17)
A18: Ford Cargo | C18: 20000 | D18: 2000 | E18: 1000 | F18: 1000 | G18: 2500 | H18: 2400 | J18: 10000 | N18: 2200 | O18: =SUM(C18:N18)
A19: Romerio s10 | B19: 53 | C19: 3000 | D19: 650 | E19: 2500 | F19: 3000 | H19: 750 | J19: 2700 | K19: 750 | L19: 10000 | M19: 1300 | N19: 2500 | O19: =SUM(C19:N19)
A20: S10 compras e schu | G20: ='Compras '!E23/3 | I20: 5000 | O20: =SUM(C20:N20)
A21: Pipa da agua | C21: 3300 | D21: 2500 | E21: 370 | G21: 660 | I21: 1800 | O21: =SUM(C21:N21)
A22: Oficina | C22: 5300 | D22: 5300 | E22: 5300 | F22: 5300 | G22: 5300 | H22: 5300 | I22: 5300 | J22: 5300 | K22: 5300 | L22: 5300 | M22: 5300 | N22: 5300 | O22: =SUM(C22:N22)
A23: Sede | C23: 4000 | D23: 4000 | E23: 4000 | F23: 4000 | G23: 4000 | H23: 4000 | I23: 4000 | J23: 4000 | K23: 4000 | L23: 4000 | M23: 4000 | N23: 4000 | O23: =SUM(C23:N23)
A24: F-4000 nova | C24: 2300 | D24: 1500 | F24: 1000 | H24: 2400 | J24: 500 | L24: 800 | N24: 1500 | O24: =SUM(C24:N24)
A25: Silo | C25: 10000 | F25: 6400 | G25: 6400 | I25: 6000 | J25: 6000 | O25: =SUM(C25:N25)
A26: Gerador | G26: 1200 | L26: 1300 | M26: 1200 | O26: =SUM(C26:N26)
A27: Escritorio | C27: 150 | D27: 600 | E27: 300 | F27: 700 | G27: 700 | H27: 700 | I27: 700 | J27: 200 | K27: 130 | L27: 1500 | M27: 1400 | N27: 2500 | O27: =SUM(C27:N27)
C28: =SUM(C2:C27) | D28: =SUM(D2:D27) | E28: =SUM(E2:E27) | F28: =SUM(F2:F27) | G28: =SUM(G2:G27) | H28: =SUM(H2:H27) | I28: =SUM(I2:I27) | J28: =SUM(J2:J27) | ... O28: =SUM(O2:O27)

Sheet Alimentação 
A1: Cantina | C1: Preços medio | D1: Quan.Itens | E1: Outubro | G1: Novembro | I1: Dezembro | K1: Janeiro | M1: Fevereiro | O1: Março | Q1: Abril | S1: Maio | U1: Junho | W1: Julho | Y1: Agosto | AA1: Setembro
A2: GAS | B2: UNIDAD | C2: 160.65 | D2: 8 | E2: =C2*D2 | F2: 5 | G2: =F2*C2 | H2: 7 | I2: =H2*C2 | J2: 7 | K2: =J2*C2 | L2: 6 | M2: =L2*C2 | N2: 6 | O2: =N2*C2 | P2: 7 | Q2: =P2*C2 | R2: 6 | S2: =R2*C2 | T2: 6 | U2: =T2*C2 | V2: 5 | W2: =V2*C2 | X2: 8 | Y2: =X2*C2 | Z2: 8 | AA2: =Z2*C2
A3: AÇUCAR 5 kg | B3: UNIDADE | C3: 25.2 | D3: 6 | E3: =C3*D3 | F3: 5 | G3: =F3*C3 | H3: 12 | I3: =H3*C3 | J3: 4 | K3: =J3*C3 | L3: 5 | M3: =L3*C3 | N3: 5 | O3: =N3*C3 | P3: 5 | Q3: =P3*C3 | R3: 5 | S3: =R3*C3 | T3: 5 | U3: =T3*C3 | V3: 4 | W3: =V3*C3 | X3: 4 | Y3: =X3*C3 | Z3: 4 | AA3: =Z3*C3
A4: AGUA SANITARIA CANDEIAS 1L | B4: UND | C4: 2.478 | D4: 15 | E4: =C4*D4 | F4: 8 | G4: =F4*C4 | H4: 10 | I4: =H4*C4 | J4: 18 | K4: =J4*C4 | L4: 8 | M4: =L4*C4 | N4: 9 | O4: =N4*C4 | P4: 9 | Q4: =P4*C4 | R4: 8 | S4: =R4*C4 | T4: 8 | U4: =T4*C4 | V4: 18 | W4: =V4*C4 | X4: 18 | Y4: =X4*C4 | Z4: 12 | AA4: =Z4*C4
A5: ARROZ BRANCO 5KG | B5: UNIDADE | C5: 26.5335 | D5: 12 | E5: =C5*D5 | F5: 15 | G5: =F5*C5 | H5: 10 | I5: =H5*C5 | J5: 9 | K5: =J5*C5 | L5: 15 | M5: =L5*C5 | N5: 12 | O5: =N5*C5 | P5: 12 | Q5: =P5*C5 | R5: 15 | S5: =R5*C5 | T5: 15 | U5: =T5*C5 | V5: 9 | W5: =V5*C5 | X5: 9 | Y5: =X5*C5 | Z5: 10 | AA5: =Z5*C5
A6: AZEITE OLIVA ANDORINHA EXT VIRG | B6: UND | C6: 56.68782 | D6: 3 | E6: =C6*D6 | F6: 5 | G6: =F6*C6 | H6: 2 | I6: =H6*C6 | J6: 6 | K6: =J6*C6 | L6: 5 | M6: =L6*C6 | N6: 7 | O6: =N6*C6 | P6: 7 | Q6: =P6*C6 | R6: 5 | S6: =R6*C6 | T6: 5 | U6: =T6*C6 | V6: 6 | W6: =V6*C6 | X6: 6 | Y6: =X6*C6 | Z6: 3 | AA6: =Z6*C6
A7: BACON PERDIGÃO | B7: KG | C7: 30.3765 | D7: 3 | E7: =C7*D7 | F7: 6 | G7: =F7*C7 | H7: 3 | I7: =H7*C7 | J7: 5 | K7: =J7*C7 | L7: 6 | M7: =L7*C7 | N7: 8 | O7: =N7*C7 | P7: 8 | Q7: =P7*C7 | R7: 6 | S7: =R7*C7 | T7: 6 | U7: =T7*C7 | V7: 5 | W7: =V7*C7 | X7: 5 | Y7: =X7*C7 | Z7: 3 | AA7: =Z7*C7
A8: BOBINA PLAST. 35X50CM | B8: UND | C8: 36.3825 | D8: 2 | E8: =C8*D8 | F8: 6 | G8: =F8*C8 | H8: 2 | I8: =H8*C8 | J8: 5 | K8: =J8*C8 | L8: 6 | M8: =L8*C8 | N8: 8 | O8: =N8*C8 | P8: 8 | Q8: =P8*C8 | R8: 6 | S8: =R8*C8 | T8: 6 | U8: =T8*C8 | V8: 5 | W8: =V8*C8 | X8: 5 | Y8: =X8*C8 | Z8: 3 | AA8: =Z8*C8
A9: BOV 2S OSSO | B9: KG | C9: 26.9115 | D9: 20 | E9: =C9*D9 | F9: 10 | G9: =F9*C9 | H9: 10 | I9: =H9*C9 | J9: 11 | K9: =J9*C9 | L9: 10 | M9: =L9*C9 | N9: 17 | O9: =N9*C9 | P9: 17 | Q9: =P9*C9 | R9: 10 | S9: =R9*C9 | T9: 10 | U9: =T9*C9 | V9: 11 | W9: =V9*C9 | X9: 11 | Y9: =X9*C9 | Z9: 6 | AA9: =Z9*C9
A10: BOV CARNE MOIDA | B10: KG | C10: 29.064 | D10: 10 | E10: =C10*D10 | F10: 13 | G10: =F10*C10 | H10: 11 | I10: =H10*C10 | J10: 21 | K10: =J10*C10 | L10: 13 | M10: =L10*C10 | N10: 26 | O10: =N10*C10 | P10: 26 | Q10: =P10*C10 | R10: 13 | S10: =R10*C10 | T10: 13 | U10: =T10*C10 | V10: 21 | W10: =V10*C10 | X10: 21 | Y10: =X10*C10 | Z10: 11 | AA10: =Z10*C10
A11: BOV CHA FORA BIFE | B11: KG | C11: 35.826 | D11: 11 | E11: =C11*D11 | F11: 18 | G11: =F11*C11 | H11: 11 | I11: =H11*C11 | J11: 20 | K11: =J11*C11 | L11: 18 | M11: =L11*C11 | N11: 32 | O11: =N11*C11 | P11: 32 | Q11: =P11*C11 | R11: 18 | S11: =R11*C11 | T11: 18 | U11: =T11*C11 | V11: 20 | W11: =V11*C11 | X11: 20 | Y11: =X11*C11 | Z11: 11 | AA11: =Z11*C11
A12: BOV FILÉ AGULHA | B12: KG | C12: 27.993 | D12: 11 | E12: =C12*D12 | F12: 17 | G12: =F12*C12 | H12: 11 | I12: =H12*C12 | J12: 20 | K12: =J12*C12 | L12: 17 | M12: =L12*C12 | N12: 32 | O12: =N12*C12 | P12: 32 | Q12: =P12*C12 | R12: 17 | S12: =R12*C12 | T12: 17 | U12: =T12*C12 | V12: 20 | W12: =V12*C12 | X12: 20 | Y12: =X12*C12 | Z12: 11 | AA12: =Z12*C12
A13: BOV MIOLO PALETA BIFE | B13: KG | C13: 35.5215 | D13: 5 | E13: =C13*D13 | F13: 16 | G13: =F13*C13 | H13: 11 | I13: =H13*C13 | J13: 20 | K13: =J13*C13 | L13: 16 | M13: =L13*C13 | N13: 32 | O13: =N13*C13 | P13: 32 | Q13: =P13*C13 | R13: 16 | S13: =R13*C13 | T13: 16 | U13: =T13*C13 | V13: 20 | W13: =V13*C13 | X13: 20 | Y13: =X13*C13 | Z13: 11 | AA13: =Z13*C13
... A24: FARINHA DE TRIGO SANADUVA | B24: UND | C24: 6.111 | D24: 6 | E24: =C24*D24 | F24: 12 | G24: =F24*C24 | H24: 6 | I24: =H24*C24 | J24: 6 | K24: =J24*C24 | L24: 12 | M24: =L24*C24 | N24: 17 | O24: =N24*C24 | P24: 17 | Q24: =P24*C24 | R24: 12 | S24: =R24*C24 | T24: 12 | U24: =T24*C24 | V24: 6 | W24: =V24*C24 | X24: 6 | Y24: =X24*C24 | Z24: 6 | AA24: =Z24*C24
A25: FLOCÃO BONOMILHO 500 G | B25: UND | C25: 1.9215 | D25: 25 | E25: =C25*D25 | F25: 16 | G25: =F25*C25 | H25: 12 | I25: =H25*C25 | K25: =J25*C25 | L25: 16 | M25: =L25*C25 | N25: 10 | O25: =N25*C25 | P25: 10 | R25: 16 | T25: 16
A26: FEIJAO CAR PADIM TP-1 1kg | B26: UND | C26: 7.35 | D26: 31 | E26: =C26*D26 | F26: 42 | G26: =F26*C26 | H26: 31 | I26: =H26*C26 | J26: 42 | K26: =J26*C26 | L26: 42 | M26: =L26*C26 | N26: 60 | O26: =N26*C26 | P26: 60 | Q26: =P26*C26 | R26: 42 | S26: =R26*C26 | T26: 42 | U26: =T26*C26 | V26: 42 | W26: =V26*C26 | X26: 42 | Y26: =X26*C26 | Z26: 30 | AA26: =Z26*C26
A27: FERM. FERMIPAM 500G | B27: UND | C27: 21.63 | D27: 3 | E27: =C27*D27 | F27: 4 | G27: =F27*C27 | H27: 2 | I27: =H27*C27 | J27: 4 | K27: =J27*C27 | L27: 4 | M27: =L27*C27 | N27: 3 | O27: =N27*C27 | P27: 3 | Q27: =P27*C27 | R27: 4 | S27: =R27*C27 | T27: 4 | U27: =T27*C27 | V27: 4 | W27: =V27*C27 | X27: 4 | Y27: =X27*C27 | Z27: 2 | AA27: =Z27*C27
A28: FRIATO COXA SOBRE COXA | B28: KG | C28: 10.6365 | D28: 41 | E28: =C28*D28 | F28: 50 | G28: =F28*C28 | H28: 41 | I28: =H28*C28 | J28: 45 | K28: =J28*C28 | L28: 50 | M28: =L28*C28 | N28: 60 | O28: =N28*C28 | P28: 60 | Q28: =P28*C28 | R28: 50 | S28: =R28*C28 | T28: 50 | U28: =T28*C28 | V28: 45 | W28: =V28*C28 | X28: 45 | Y28: =X28*C28 | Z28: 39 | AA28: =Z28*C28
A29: FRUTA ABACAXI | B29: UND | C29: 9.786 | D29: 4 | E29: =C29*D29 | F29: 7 | G29: =F29*C29 | H29: 3 | I29: =H29*C29 | J29: 2 | K29: =J29*C29 | L29: 7 | M29: =L29*C29 | N29: 6 | O29: =N29*C29 | P29: 6 | Q29: =P29*C29 | R29: 7 | S29: =R29*C29 | T29: 7 | U29: =T29*C29 | V29: 2 | W29: =V29*C29 | X29: 2 | Y29: =X29*C29 | Z29: 3 | AA29: =Z29*C29
A30: FRUTA BANANA NANICA | B30: KG | C30: 3.3075 | D30: 20 | E30: =C30*D30 | F30: 35 | G30: =F30*C30 | H30: 21 | I30: =H30*C30 | J30: 20 | K30: =J30*C30 | L30: 35 | M30: =L30*C30 | N30: 35 | O30: =N30*C30 | P30: 35 | Q30: =P30*C30 | R30: 35 | S30: =R30*C30 | T30: 35 | U30: =T30*C30 | V30: 20 | W30: =V30*C30 | X30: 20 | Y30: =X30*C30 | Z30: 20 | AA30: =Z30*C30
A31: FRUTA LARANJA | B31: KG | C31: 3.7275 | D31: 21 | E31: =C31*D31 | F31: 35 | G31: =F31*C31 | H31: 21 | I31: =H31*C31 | J31: 21 | K31: =J31*C31 | L31: 35 | M31: =L31*C31 | N31: 25 | O31: =N31*C31 | P31: 25 | Q31: =P31*C31 | R31: 35 | S31: =R31*C31 | T31: 35 | U31: =T31*C31 | V31: 21 | W31: =V31*C31 | X31: 21 | Y31: =X31*C31 | Z31: 20 | AA31: =Z31*C31
A32: FRUTA MACA FUJI | B32: KG | C32: 11.7075 | D32: 17 | E32: =C32*D32 | F32: 25 | G32: =F32*C32 | H32: 17 | I32: =H32*C32 | J32: 25 | K32: =J32*C32 | L32: 25 | M32: =L32*C32 | N32: 25 | O32: =N32*C32 | P32: 25 | Q32: =P32*C32 | R32: 25 | S32: =R32*C32 | T32: 25 | U32: =T32*C32 | V32: 25 | W32: =V32*C32 | X32: 25 | Y32: =X32*C32 | Z32: 16 | AA32: =Z32*C32
A33: FRUTA MAMAO | B33: KG | C33: 2.709 | D33: 3 | E33: =C33*D33 | F33: 5 | G33: =F33*C33 | H33: 3 | I33: =H33*C33 | J33: 5 | K33: =J33*C33 | L33: 5 | M33: =L33*C33 | N33: 2 | O33: =N33*C33 | P33: 2 | Q33: =P33*C33 | R33: 5 | S33: =R33*C33 | T33: 5 | U33: =T33*C33 | V33: 5 | W33: =V33*C33 | X33: 5 | Y33: =X33*C33 | Z33: 3 | AA33: =Z33*C33
A34: FRUTA MELANCIA | B34: KG | C34: 2.709 | D34: 24 | E34: =C34*D34 | F34: 35 | G34: =F34*C34 | H34: 20 | I34: =H34*C34 | J34: 35 | K34: =J34*C34 | L34: 35 | M34: =L34*C34 | N34: 35 | O34: =N34*C34 | P34: 35 | Q34: =P34*C34 | R34: 35 | S34: =R34*C34 | T34: 35 | U34: =T34*C34 | V34: 35 | W34: =V34*C34 | X34: 35 | Y34: =X34*C34 | Z34: 22 | AA34: =Z34*C34
A35: ISQUEIRO BIC MAXI 1X1 | B35: UND | C35: 5.5125 | D35: 7 | E35: =C35*D35 | F35: 0 | G35: =F35*C35 | H35: 0 | I35: =H35*C35 | J35: 0 | K35: =J35*C35 | L35: 0 | M35: =L35*C35 | N35: 0 | O35: =N35*C35 | P35: 0 | Q35: =P35*C35 | R35: 0 | S35: =R35*C35 | T35: 0 | U35: =T35*C35 | V35: 0 | W35: =V35*C35 | X35: 0 | Y35: =X35*C35 | AA35: =Z35*C35
A36: LAVA LOUCAS MINUANO | B36: UND | C36: 2.2155 | D36: 24 | E36: =C36*D36 | F36: 35 | G36: =F36*C36 | H36: 19 | I36: =H36*C36 | J36: 21 | K36: =J36*C36 | L36: 35 | M36: =L36*C36 | N36: 35 | O36: =N36*C36 | P36: 35 | Q36: =P36*C36 | R36: 35 | S36: =R36*C36 | T36: 35 | U36: =T36*C36 | V36: 21 | W36: =V36*C36 | X36: 21 | Y36: =X36*C36 | Z36: 24 | AA36: =Z36*C36
A37: LIMP PESADA CANDEIAS GEL LAV 1 L | B37: UND | C37: 8.925 | D37: 12 | E37: =C37*D37 | F37: 25 | G37: =F37*C37 | H37: 10 | I37: =H37*C37 | J37: 10 | K37: =J37*C37 | L37: 25 | M37: =L37*C37 | N37: 10 | O37: =N37*C37 | P37: 10 | Q37: =P37*C37 | R37: 25 | S37: =R37*C37 | T37: 25 | U37: =T37*C37 | V37: 10 | W37: =V37*C37 | X37: 10 | Y37: =X37*C37 | Z37: 24 | AA37: =Z37*C37
A38: LIMPA ALUMINIO POLITRIZ LIMAO 500 ML | B38: UND | C38: 3.1395 | D38: 12 | E38: =C38*D38 | F38: 16 | G38: =F38*C38 | H38: 10 | I38: =H38*C38 | J38: 22 | K38: =J38*C38 | L38: 16 | M38: =L38*C38 | N38: 22 | O38: =N38*C38 | P38: 22 | Q38: =P38*C38 | R38: 16 | S38: =R38*C38 | T38: 16 | U38: =T38*C38 | V38: 22 | W38: =V38*C38 | X38: 22 | Y38: =X38*C38 | Z38: 24 | AA38: =Z38*C38
A39: LIMPA CANDEIAS CERAMICA 1 L | B39: UND | C39: 7.791 | D39: 12 | E39: =C39*D39 | F39: 30 | G39: =F39*C39 | H39: 10 | I39: =H39*C39 | J39: 6 | K39: =J39*C39 | L39: 30 | M39: =L39*C39 | N39: 16 | O39: =N39*C39 | P39: 16 | Q39: =P39*C39 | R39: 30 | S39: =R39*C39 | T39: 30 | U39: =T39*C39 | V39: 6 | W39: =V39*C39 | X39: 6 | Y39: =X39*C39 | Z39: 24 | AA39: =Z39*C39
A40: LIMPA VEJA MULTIUSO ORIG LV500 | B40: UND | C40: 5.985 | D40: 24 | E40: =C40*D40 | F40: 25 | G40: =F40*C40 | H40: 20 | I40: =H40*C40 | J40: 8 | K40: =J40*C40 | L40: 25 | M40: =L40*C40 | N40: 16 | O40: =N40*C40 | P40: 16 | Q40: =P40*C40 | R40: 25 | S40: =R40*C40 | T40: 25 | U40: =T40*C40 | V40: 8 | W40: =V40*C40 | X40: 8 | Y40: =X40*C40 | Z40: 24 | AA40: =Z40*C40
A41: LING. MISTA FRICO | B41: KG | C41: 21.21 | D41: 6 | E41: =C41*D41 | F41: 12 | G41: =F41*C41 | H41: 10 | I41: =H41*C41 | J41: 10 | K41: =J41*C41 | L41: 12 | M41: =L41*C41 | N41: 12 | O41: =N41*C41 | P41: 12 | Q41: =P41*C41 | R41: 12 | S41: =R41*C41 | T41: 12 | U41: =T41*C41 | V41: 10 | W41: =V41*C41 | X41: 10 | Y41: =X41*C41 | Z41: 6 | AA41: =Z41*C41
A42: LING. FRICO CALABRESA DEF | B42: KG | C42: 26.92746 | D42: 4 | E42: =C42*D42 | F42: 7 | G42: =F42*C42 | H42: 3 | I42: =H42*C42 | J42: 5 | K42: =J42*C42 | L42: 7 | M42: =L42*C42 | N42: 6 | O42: =N42*C42 | P42: 6 | Q42: =P42*C42 | R42: 7 | S42: =R42*C42 | T42: 7 | U42: =T42*C42 | V42: 5 | W42: =V42*C42 | X42: 5 | Y42: =X42*C42 | Z42: 3 | AA42: =Z42*C42
A43: LING. NOBRE MISTA | B43: KG | C43: 22.407 | D43: 10 | E43: =C43*D43 | F43: 7 | G43: =F43*C43 | H43: 8 | I43: =H43*C43 | J43: 4 | K43: =J43*C43 | L43: 7 | M43: =L43*C43 | N43: 5 | O43: =N43*C43 | P43: 5 | Q43: =P43*C43 | R43: 7 | S43: =R43*C43 | T43: 7 | U43: =T43*C43 | V43: 4 | W43: =V43*C43 | X43: 4 | Y43: =X43*C43 | Z43: 3 | AA43: =Z43*C43
A44: LINGUI AURORA FGO | B44: KG | C44: 22.47 | D44: 9 | E44: =C44*D44 | F44: 18 | G44: =F44*C44 | H44: 8 | I44: =H44*C44 | J44: 2 | K44: =J44*C44 | L44: 18 | M44: =L44*C44 | N44: 16 | O44: =N44*C44 | P44: 16 | Q44: =P44*C44 | R44: 18 | S44: =R44*C44 | T44: 18 | U44: =T44*C44 | V44: 2 | W44: =V44*C44 | X44: 2 | Y44: =X44*C44 | Z44: 8 | AA44: =Z44*C44
A45: LUVA NOBRE PLAST DESC 100x1 | B45: UND | C45: 19.005 | D45: 2 | E45: =C45*D45 | F45: 2 | G45: =F45*C45 | H45: 2 | I45: =H45*C45 | J45: 2 | K45: =J45*C45 | L45: 2 | M45: =L45*C45 | N45: 2 | O45: =N45*C45 | P45: 2 | Q45: =P45*C45 | R45: 2 | S45: =R45*C45 | T45: 2 | U45: =T45*C45 | V45: 2 | W45: =V45*C45 | X45: 2 | Y45: =X45*C45 | Z45: 1 | AA45: =Z45*C45
A46: MAC PAULISTA SEM ESPAGUETE 500G | B46: UND | C46: 3.003 | D46: 20 | E46: =C46*D46 | F46: 15 | G46: =F46*C46 | H46: 14 | I46: =H46*C46 | J46: 20 | K46: =J46*C46 | L46: 15 | M46: =L46*C46 | N46: 16 | O46: =N46*C46 | P46: 16 | Q46: =P46*C46 | R46: 15 | S46: =R46*C46 | T46: 15 | U46: =T46*C46 | V46: 20 | W46: =V46*C46 | X46: 20 | Y46: =X46*C46 | Z46: 11 | AA46: =Z46*C46
A47: MASSA LASANHA DONA BENTA | B47: UND | C47: 7.623 | D47: 4 | E47: =C47*D47 | F47: 6 | G47: =F47*C47 | H47: 4 | I47: =H47*C47 | J47: 5 | K47: =J47*C47 | L47: 6 | M47: =L47*C47 | N47: 5 | O47: =N47*C47 | P47: 5 | Q47: =P47*C47 | R47: 6 | S47: =R47*C47 | T47: 6 | U47: =T47*C47 | V47: 5 | W47: =V47*C47 | X47: 5 | Y47: =X47*C47 | Z47: 4 | AA47: =Z47*C47
... A62: SALSICHA FRIATO CONG. | B62: KG | C62: 9.849 | D62: 10 | E62: =C62*D62 | F62: 12 | G62: =F62*C62 | H62: 6 | I62: =H62*C62 | J62: 10 | K62: =J62*C62 | L62: 12 | M62: =L62*C62 | N62: 10 | O62: =N62*C62 | P62: 10 | Q62: =P62*C62 | R62: 12 | S62: =R62*C62 | T62: 12 | U62: =T62*C62 | V62: 10 | W62: =V62*C62 | X62: 10 | Y62: =X62*C62 | Z62: 6 | AA62: =Z62*C62
A63: Suino granja | B63: Kg | C63: 15 | D63: 300 | E63: =C63*D63
C64: 0
A65: TAPETE PARNASUL PORTA CASA 45X65 | B65: UND | C65: 20.79 | D65: 4 | E65: =C65*D65 | F65: 7 | G65: =F65*C65 | H65: 1 | I65: =H65*C65 | J65: 4 | K65: =J65*C65 | L65: 7 | M65: =L65*C65 | N65: 1 | O65: =N65*C65 | P65: 1 | Q65: =P65*C65 | R65: 7 | S65: =R65*C65 | T65: 7 | U65: =T65*C65 | V65: 4 | W65: =V65*C65 | X65: 4 | Y65: =X65*C65 | Z65: 3 | AA65: =Z65*C65
A66: TEMP. NERESCO AÇAFRAO 500G | B66: UND | C66: 16.317 | D66: 3 | E66: =C66*D66 | F66: 3 | G66: =F66*C66 | H66: 2 | I66: =H66*C66 | J66: 3 | K66: =J66*C66 | L66: 3 | M66: =L66*C66 | N66: 3 | O66: =N66*C66 | P66: 3 | Q66: =P66*C66 | R66: 3 | S66: =R66*C66 | T66: 3 | U66: =T66*C66 | V66: 3 | W66: =V66*C66 | X66: 3 | Y66: =X66*C66 | Z66: 2 | AA66: =Z66*C66
A67: TEMP. SAZON CARNE 60G | B67: UND | C67: 5.6805 | D67: 6 | E67: =C67*D67 | F67: 5 | G67: =F67*C67 | H67: 4 | I67: =H67*C67 | J67: 11 | K67: =J67*C67 | L67: 5 | M67: =L67*C67 | N67: 6 | O67: =N67*C67 | P67: 6 | Q67: =P67*C67 | R67: 5 | S67: =R67*C67 | T67: 5 | U67: =T67*C67 | V67: 11 | W67: =V67*C67 | X67: 11 | Y67: =X67*C67 | Z67: 6 | AA67: =Z67*C67
A68: TEMP. SAZON FRANGO 60G | B68: UND | C68: 5.6805 | D68: 4 | E68: =C68*D68 | F68: 7 | G68: =F68*C68 | H68: 4 | I68: =H68*C68 | J68: 6 | K68: =J68*C68 | L68: 7 | M68: =L68*C68 | N68: 6 | O68: =N68*C68 | P68: 6 | Q68: =P68*C68 | R68: 7 | S68: =R68*C68 | T68: 7 | U68: =T68*C68 | V68: 6 | W68: =V68*C68 | X68: 6 | Y68: =X68*C68 | Z68: 3 | AA68: =Z68*C68
A69: TEMP. SAZON LEGUMES 60G | B69: UND | C69: 5.6805 | D69: 6 | E69: =C69*D69 | F69: 12 | G69: =F69*C69 | H69: 3 | I69: =H69*C69 | J69: 6 | K69: =J69*C69 | L69: 12 | M69: =L69*C69 | N69: 10 | O69: =N69*C69 | P69: 10 | Q69: =P69*C69 | R69: 12 | S69: =R69*C69 | T69: 12 | U69: =T69*C69 | V69: 6 | W69: =V69*C69 | X69: 6 | Y69: =X69*C69 | Z69: 6 | AA69: =Z69*C69
A70: TEMP.SAZON MASSAS 60G | B70: UND | C70: 5.6805 | D70: 4 | E70: =C70*D70 | F70: 7 | G70: =F70*C70 | H70: 3 | I70: =H70*C70 | J70: 4 | K70: =J70*C70 | L70: 7 | M70: =L70*C70 | N70: 5 | O70: =N70*C70 | P70: 5 | Q70: =P70*C70 | R70: 7 | S70: =R70*C70 | T70: 7 | U70: =T70*C70 | V70: 4 | W70: =V70*C70 | X70: 3 | Y70: =X70*C70 | Z70: 3 | AA70: =Z70*C70
A71: TOUCA DESC. NOBRE TNT 50X1 | B71: UND | C71: 11.55 | D71: 2 | E71: =C71*D71 | F71: 3 | G71: =F71*C71 | H71: 2 | I71: =H71*C71 | J71: 2 | K71: =J71*C71 | L71: 3 | M71: =L71*C71 | N71: 2 | O71: =N71*C71 | P71: 2 | Q71: =P71*C71 | R71: 3 | S71: =R71*C71 | T71: 3 | U71: =T71*C71 | V71: 2 | W71: =V71*C71 | X71: 2 | Y71: =X71*C71 | Z71: 2 | AA71: =Z71*C71
A72: VERD. ALFACE | B72: UND | C72: 2.65398 | D72: 6 | E72: =C72*D72 | F72: 12 | G72: =F72*C72 | H72: 6 | I72: =H72*C72 | J72: 7 | K72: =J72*C72 | L72: 12 | M72: =L72*C72 | N72: 10 | O72: =N72*C72 | P72: 10 | Q72: =P72*C72 | R72: 12 | S72: =R72*C72 | T72: 12 | U72: =T72*C72 | V72: 7 | W72: =V72*C72 | X72: 6 | Y72: =X72*C72 | Z72: 6 | AA72: =Z72*C72
A73: VERD. BATATA DOCE | B73: KG | C73: 4.1895 | D73: 4 | E73: =C73*D73 | F73: 8 | G73: =F73*C73 | H73: 4 | I73: =H73*C73 | J73: 4 | K73: =J73*C73 | L73: 8 | M73: =L73*C73 | N73: 6 | O73: =N73*C73 | P73: 6 | Q73: =P73*C73 | R73: 8 | S73: =R73*C73 | T73: 8 | U73: =T73*C73 | V73: 4 | W73: =V73*C73 | X73: 4 | Y73: =X73*C73 | Z73: 4 | AA73: =Z73*C73
A74: VERD. BETERRABA | B74: KG | C74: 5.313 | D74: 4 | E74: =C74*D74 | F74: 7 | G74: =F74*C74 | H74: 4 | I74: =H74*C74 | J74: 4 | K74: =J74*C74 | L74: 7 | M74: =L74*C74 | N74: 6 | O74: =N74*C74 | P74: 6 | Q74: =P74*C74 | R74: 7 | S74: =R74*C74 | T74: 7 | U74: =T74*C74 | V74: 4 | W74: =V74*C74 | X74: 3 | Y74: =X74*C74 | Z74: 3 | AA74: =Z74*C74
A75: VERD. CEBOLINHA | B75: UB | C75: 3.69768 | D75: 7 | E75: =C75*D75 | F75: 6 | G75: =F75*C75 | H75: 7 | I75: =H75*C75 | J75: 8 | K75: =J75*C75 | L75: 6 | M75: =L75*C75 | N75: 6 | O75: =N75*C75 | P75: 6 | Q75: =P75*C75 | R75: 6 | S75: =R75*C75 | T75: 6 | U75: =T75*C75 | V75: 8 | W75: =V75*C75 | X75: 7 | Y75: =X75*C75 | Z75: 7 | AA75: =Z75*C75
A76: VERD. CENOURA | B76: UB | C76: 3.57 | D76: 4 | E76: =C76*D76 | F76: 7 | G76: =F76*C76 | H76: 4 | I76: =H76*C76 | J76: 4 | K76: =J76*C76 | L76: 7 | M76: =L76*C76 | N76: 3 | O76: =N76*C76 | P76: 3 | Q76: =P76*C76 | R76: 7 | S76: =R76*C76 | T76: 7 | U76: =T76*C76 | V76: 4 | W76: =V76*C76 | X76: 3 | Y76: =X76*C76 | Z76: 3 | AA76: =Z76*C76
... A84: VINAGRE CASTELO ALCOOL 750ML | B84: UND | C84: 5.48688 | D84: 4 | E84: =C84*D84 | F84: 7 | G84: =F84*C84 | H84: 3 | I84: =H84*C84 | J84: 4 | K84: =J84*C84 | L84: 7 | M84: =L84*C84 | N84: 2 | O84: =N84*C84 | P84: 2 | Q84: =P84*C84 | R84: 7 | S84: =R84*C84 | T84: 7 | U84: =T84*C84 | V84: 3 | W84: =V84*C84 | X84: 3 | Y84: =X84*C84 | Z84: 3 | AA84: =Z84*C84
E85: =SUM(E2:E84) | G85: =SUM(G2:G84) | I85: =SUM(I2:I84) | K85: =SUM(K2:K84) | M85: =SUM(M2:M84) | O85: =SUM(O2:O84) | Q85: =SUM(Q2:Q84) | S85: =SUM(S2:S84) | U85: =SUM(U2:U84) | W85: =SUM(W2:W84) | Y85: =SUM(Y2:Y84) | AA85: =SUM(AA2:AA84) | AB85: =SUM(E85:AA85)
AA86: R$/dia/func | AB86: =(AB85/365)/14

Sheet Utilidades e Veiculos
A2: Radoll/Silo | B2: Consumo kw/h/mês fora Ponta | C2: Consumo kw/h/mês na Ponta | D2: Demanda | E2: R$ | G2: Radoll/Sede | H2: Consumo kw/h/mês -TUSD | I2: Consumo kw/h/mês TE | J2: Bandeira vermelha | K2: R$ | M2: INTERNET | N2: TOTAL | P2: Total
A3: Outubro | B3: 1623 | C3: 108 | D3: 33 | E3: =(B3*0.45)+(C3*3.9)+(D3*49.68)+200 | G3: Outubro | K3: 100 | M3: Outurbro | N3: 240 | P3: =SUM(N3,K3,E3)
A4: Novembro | B4: 2200 | C4: 47 | D4: 34 | E4: =(B4*0.45)+(C4*3.9)+(D4*49.68)+200 | G4: Novembro | K4: 100 | M4: Novembro | N4: 240 | P4: =SUM(N4,K4,E4)
A5: Dezembro | B5: 2400 | C5: 60 | D5: 34 | E5: =(B5*0.45)+(C5*3.9)+(D5*49.68)+200 | G5: Dezembro | K5: 100 | M5: Dez | N5: 240 | P5: =SUM(N5,K5,E5)
A6: Janeiro | B6: 1000 | C6: 127 | D6: 40 | E6: =(B6*0.45)+(C6*3.9)+(D6*49.68)+200 | G6: Janeiro | K6: 100 | M6: Jan | N6: 240 | P6: =SUM(N6,K6,E6)
A7: Fevereiro | B7: 1720 | C7: 72 | D7: 70 | E7: =(B7*0.45)+(C7*3.9)+(D7*49.68)+200 | G7: Fevereiro | K7: 100 | M7: Fevereiro | N7: 240 | P7: =SUM(N7,K7,E7)
A8: Março | B8: 1620 | C8: 84 | D8: 7 | E8: =(B8*0.45)+(C8*3.9)+(D8*49.68)+200 | G8: Março | K8: 100 | M8: Março | N8: 240 | P8: =SUM(N8,K8,E8)
A9: Abril | B9: 10700 | C9: 240 | D9: 140 | E9: =(B9*0.45)+(C9*3.9)+(D9*49.68)+200 | G9: Abril | K9: 100 | M9: Abril | N9: 240 | P9: =SUM(N9,K9,E9)
A10: Maio | B10: 3350 | C10: 57 | D10: 70 | E10: =(B10*0.45)+(C10*3.9)+(D10*49.68)+200 | G10: Maio | K10: 100 | M10: Maio | N10: 240 | P10: =SUM(N10,K10,E10)
A11: Junho | B11: 1471 | C11: 50 | D11: 42 | E11: =(B11*0.45)+(C11*3.9)+(D11*49.68)+200 | G11: Junho | K11: 100 | M11: Junho | N11: 240 | P11: =SUM(N11,K11,E11)
A12: Julho | B12: 1300 | C12: 55 | D12: 42 | E12: =(B12*0.45)+(C12*3.9)+(D12*49.68)+200 | G12: Julho | K12: 100 | M12: Julho | N12: 240 | P12: =SUM(N12,K12,E12)
A13: Agosto | B13: 1200 | C13: 30 | D13: 41 | E13: =(B13*0.45)+(C13*3.9)+(D13*49.68)+200 | G13: Agosto | K13: 100 | M13: Agosto | N13: 240 | P13: =SUM(N13,K13,E13)
A14: Setembro | B14: 1100 | C14: 42 | D14: 45 | E14: =(B14*0.45)+(C14*3.9)+(D14*49.68)+200 | G14: Setembro | K14: 100 | M14: Setembro | N14: 240 | P14: =SUM(N14,K14,E14)
B15: 118200 | C15: Cambio 5,20 | D15: =D14*5.2 | E15: =SUM(E3:E14) | I15: =I14*5.2 | K15: =SUM(K3:K14) | N15: =SUM(N3:N14) | P15: =SUM(P3:P14)
B18: Planilha de Veiculos Agroservice - Exercício 2022 | C18: Planilha de Veiculos Agroservice - Exercício 2022 | D18: Planilha de Veiculos Agroservice - Exercício 2022 | E18: Planilha de Veiculos Agroservice - Exercício 2022 | F18: Planilha de Veiculos Agroservice - Exercício 2022 | G18: Planilha de Veiculos Agroservice - Exercício 2022 | H18: Planilha de Veiculos Agroservice - Exercício 2022 | I18: Planilha de Veiculos Agroservice - Exercício 2022
B19: veiculos | C19: Chassi: | D19: Renavam: | E19: Placa: | F19: Valor normal | G19: Valor c desconto | H19: CRLV -2021 | I19: Situação | J19: Proprietarios
A20: F4000 2019 | B20: F4000 a | C20: 9BFLF47P6KB017257 | D20: 1183397566 | E20: PRV3B48 | G20: 1132 | I20: ok | J20: AGROINVEST
B21: F4000 | C21: 9BFLF4799BB098143 | D21: 464016150 | E21: NZU-7394 | G21: 622.85 | I21: ok | J21: AGROSERVICE
B22: F4000 a | C22: 9BFLF47949B061110 | D22: 124118003 | E22: JSA-0223 | G22: 544.25 | I22: ok | J22: JOHN DANIEL CARROLL
B23: F4000 | C23: 9BFLF4798AB077721 | D23: 273513079 | E23: NYK-7967 | G23: 581.45 | I23: ok | J23: JOHN DANIEL CARROLL
B24: F4000 | C24: 9BFLF4791AB076751 | D24: 273494791 | E24: NYK-4040 | G24: 581.45 | I24: ok | J24: JOHN DANIEL CARROLL
B25: F4000 | C25: 9BFLF4799BB098370 | D25: 471104248 | E25: NZY-3157 | G25: 622.85 | I25: ok | J25: AGROSERVICE
B26: F4000 | C26: 9BFLF4797BB087433 | D26: 337348677 | E26: NYZ-2185 | G26: 622.85 | I26: ok | J26: AGROSERVICE
B27: VOLKSWAGEN 23230 NOVO | C27: 9536G8243LR003331 | D27: 1197330574 | E27: PLT-5I44 | G27: 1939.19 | I27: ok | J27: AGROSERVICE
B28: FORD 2422 E | C28: 9BFYCEHVX7BB99495 | D28: 954271483 | E28: JRC-6349 | G28: 840.8 | I28: ok | J28: JOHN DANIEL CARROLL
B29: FORD 2422 E a | C29: 9BFYCEHV47BB89394 | D29: 954273478 | E29: JRE-1214 | G29: 840.8 | I29: ok | J29: JOHN DANIEL CARROLL
B30: ONIBUS | C30: 9BM384088NB944904 | D30: 319418359 | E30: KOD-1895 | G30: 149.16 | I30: ok | J30: JHON DANIEL CARROLL
B31: F350 | C31: 9BFJF37939B062346 | D31: 124117074 | E31: JSA-9307 | G31: 589.9 | I31: ok/v | J31: JOHN DANIEL CARROLL
B32: STRADA BRANCA NOVO 2018 | C32: 9BD5781FFHY167654 | D32: 1129961807 | E32: PKQ-1249 | G32: 1049.6 | I32: ok | J32: AGROSERVICE | K32: office | L32: ok
B33: EVOQUE PURE | C33: SALVA2BG4DH724928 | D33: 505863987 | E33: OUD-7408 | G33: 2114.6 | I33: ok | J33: AGROSERVICE | K33: office | L33: ok
B34: ONIX NOVO 2018 | C34: 9BGKS48V0JG146937 | D34: 1124430986 | E34: PKO-5490 | G34: 1189.01 | I34: ok | J34: AGROSERVICE | K34: office | L34: ok
B35: FOX | C35: 9BWKA05Z664065844 | D35: 865893497 | E35: JGO-6738 | G35: 149.16 | I35: ok | J35: JOHN DANIEL CARROLL | K35: office | L35: ok
B36: QUANTUM | C36: 9BWZZZ33ZNP030722 | D36: 606002928 | E36: BLG-6647 | G36: 149.16 | I36: ok/v | J36: JOHN DANIEL CARROLL | K36: office | L36: ok
B37: S-10 Nova Prata - Schuh | C37: 9BG148FK0LC429210 | D37: 1226385033 | E37: QTZ3H12 | G37: 3822.27 | I37: ok | J37: AGROSERVICE
B38: S-10 - Dan | C38: 9BG148FK0FC409677 | D38: 1036472890 | E38: OZV-5618 | G38: 2624.66 | I38: ok | J38: AGROSERVICE | K38: office | L38: ok
B39: S-10 - nova Branca - Davi | C39: 9BG148DK0KC406908 | D39: 1154492491 | E39: QOK-8422 | G39: 2927.76 | I39: ok | J39: AGROSERVICE | K39: radoll
B40: S-10 - Dpt. Compras | C40: 9BG144DK0LC431427 | D40: 1218843494 | E40: QTW2B92 | G40: 3580.85 | I40: ok | J40: AGROSERVICE
B41: Moto bros 150 ano 2011 | C41: 9C2KD0580CR500290 | D41: 425829022 | E41: OGL-7521 | G41: 149.16 | I41: ok | J41: AGROSERVICE
B42: Moto xtz 125 ano 2011 | C42: 9C6KE1260C0026212 | D42: 459372858 | E42: OGZ-3372 | G42: 149.16 | I42: ok | J42: AGROSERVICE
B43: Moto bros 150 ano 2011 a | C43: 9C2KD0560CR500617 | D43: 394245792 | E43: OGW-7606 | G43: 149.16 | I43: ok | J43: AGROSERVICE
B44: HONDA BROZ | C44: 9C2KD03208R036469 | D44: 117032476 | E44: JRX-1383 | G44: 149.16 | I44: ok | J44: JOHN DANIEL CARROLL
B45: HONDA BROZ | C45: 9C2KD0530AR017279 | D45: 273661388 | E45: NYK7394 | G45: 149.16 | I45: ok | J45: JOHN DANIEL CARROLL
B46: honda bros 160cc a | C46: 9C2KD100HR002639 | D46: 1116589777 | E46: PKK1003 | G46: 264 | I46: ok | J46: Agroinvest
B47: HONDA BROZ PRETA | C47: 9C2KD0530AR017337 | D47: 273663143 | E47: NYK-3552 | G47: 149.16 | I47: ok | J47: JOHN DANIEL CARROLL
B48: HONDA BIZ | C48: 9C2HA07103R065270 | D48: 827421311 | E48: JQE-5117 | G48: 149.16 | I48: ok | J48: AGROSERVICE | K48: office | L48: ok
B49: YAMAHA XTZ-125 | C49: 9C6KE1260C0027940 | D49: 492843651 | E49: OMY-0515 | G49: 149.16 | I49: ok | J49: AGROSERVICE
B50: YAMAHA XTZ-125 | C50: 9C6KE1260C0027588 | D50: 492844577 | E50: OMY-0565 | G50: 149.16 | I50: ok | J50: AGROSERVICE
B51: REBOQUE | C51: C1C1546CIC | D51: 216160260 | E51: JOL- 1037 | G51: 149.16 | I51: ok | J51: AGROSERVICE
B52: REBOQUE | C52: 9A9V11530V2AD9142 | D52: 692229485 | E52: JLI-9419 | G52: 149.16 | I52: ok | J52: AGROSERVICE
B53: Moto bros 150 ano 2011 | C53: Carroll Farms | D53: 9C2KD0560CR506030 | E53: N emplacada | F53: N emplacada | G53: N emplacada | J53: CARROLL FARMS BRASIL
B54: Moto bros 150 ano 2010 | C54: JONH | D54: 9C2KD0530AR002069 | E54: N emplacada | F54: N emplacada | G54: N emplacada | J54: JHON DANIEL CARROLL
B55: Ford Ranger XLS LUIZ | D55: 1271767179 | E55: RDJ0C64 | G55: 3688.65 | I55: ok | J55: AGROSERVICE
B56: F4000 2020 | D56: 1053727647 | E56: PJI - 6B81 | G56: 952.12 | I56: ok | J56: AGROSERVICE
B57: VOLVO/VM 330 8X2R/Feed Truck | C57: 93KP0S1F6ME174489 | D57: 1272019966 | E57: RDJ0I77 | G57: 3181.69 | I57: ok | J57: AGROSERVICE
B58: IVECO/TECTOR 310E30CE Semi | C58: 93ZJ13BM0N8943307 | D58: 1272575389 | E58: RDJ2H81 | G58: 4962.11 | I58: ok | J58: AGROSERVICE
E60: Valor Total | G60: =SUM(G21:G58)
F61: Sem Desconto | G61: Desconto 10%
G63: Agroinvest | H63: =SUM(G39,G29,G22,G43,G46,G20)

Sheet Supriment-Ser Profiss
A1: Suprimentos | B1: Suprimentos | C1: Suprimentos | F1: Serviços Profissionais | G1: Serviços Profissionais | H1: Serviços Profissionais | I1: Serviços Profissionais
A2: Produto | B2: Quantidade | C2: R$ Total | F2: Serviço | G2: Referncia (mensal, anual, p/serviço) | H2: R$ Total
A3: Confraternização Final de ano | B3: 1 | C3: =RH!C22 | F3: Focu Consultoria 5X 9000 | G3: 75000 | H3: 75000
A4: Agroinvest | B4: Agroinvest | C4: Agroinvest | F4: Davi, mapas de fertilidade e prescrição | G4: R$0,28/há de mapas
A5: Confraternização Trimestral | C5: =RH!C38 | F5: Oeste Acessoria R$750,20x12meses | G5: 12 | H5: =((1212*0.682)*15000)/5750 | I5: Rateado com Agroservice
A6: Baners Prioridades | C6: ='Supriment-Ser Profiss'!H1 | F6: Cooperfarms comissão de compra de quimicos | G6: U$$ * 1% | H6: =(211666*1%)*'Orçam-Realiza'!D29 | M6: 606.98
A7: Datas comemorativas | C7: =RH!C34 | F7: Armazenagem de Quimicos ( n° pallet) | G7: 527 Pallet | H7: =SUM(G11:O11)
C8: =SUM(C5:C7) | G8: Out | H8: 248.24 | I8: Dez | J8: Jan | K8: Fev | L8: Mar | M8: Abr | N8: Mai | O8: Jun
A9: Materiasis Eletricos | B9: 1 | C9: 5000 | F9: Lts Quimic | G9: =40500/2 | H9: =50580/2 | I9: =48600/2 | J9: =49500/2 | K9: =43200/2 | L9: =34650/2 | M9: =27000/2 | N9: =24700/2 | O9: =25000/2
A10: Grafica, Papelaria, Higiene e Limpeza. | F10: N° Pallet | G10: 20 | H10: 20 | I10: 20 | J10: 2 | K10: 2 | L10: 2 | M10: 2 | N10: 2 | O10: 2
A11: Calculadora | B11: 1 | C11: =Angelo!D4 | F11: R$/Pallet | G11: =G10*80+810 | H11: =H10*80+810 | I11: =I10*80+810 | J11: =J10*80+720 | K11: =K10*80+720 | L11: =L10*80+720 | M11: =M10*80+720 | N11: =N10*80+720 | O11: =O10*80+720
A12: Comodato impressora 12xR$ 240 | B12: 12 | C12: =Angelo!D5 | F12: Lavanderia (reaproveitamento de Uniformes)
A13: Concerto noobrak | B13: 1 | C13: =Angelo!D6 | F13: Manutençao dos AC | G13: 4 | H13: 3000
A14: Concerto ar condicionado | B14: 1 | C14: =Angelo!D7 | F14: Manutenção dos Radios de comunicação | G14: 1 | H14: 1000
A15: Caneta cx | B15: 1 | C15: =Angelo!D8 | F15: FFGU (Coleta, transporte, tratamento e disposição final) | G15: Quant | H15: Total
A16: Cx com 5 mil Granpos 26/6 para grampeador | B16: 1 | C16: =Angelo!D9 | F16: Lampada | G16: 3 | H16: =Angelo!D97
A17: Cx com 48 unidades de prendedor de papel 25mm | B17: 1 | C17: =Angelo!D10 | F17: Baterias | G17: 6 | H17: =Angelo!D98
A18: Cx com 12 unidades de prendedor de papel 51mm | B18: 2 | C18: =Angelo!D11 | F18: Residuos oleosos | G18: 20 | H18: =Angelo!D99
A19: Grampeador | B19: 1 | C19: =Angelo!D12 | F19: Residuos misto | G19: 60 | H19: =Angelo!D100
A20: Lampadas para escritorio | B20: 2 | C20: =Angelo!D13 | F20: Rejeitos | G20: 50 | H20: =Angelo!D101
A21: Lixeira 15 lt com pedal | B21: 0 | C21: =Angelo!D14 | F21: Plastico | G21: 50 | H21: =Angelo!D102 | J21: =I20*5.2
A22: Marcador permanente | B22: 6 | C22: =Angelo!D15 | F22: Borracha | G22: 70 | H22: =Angelo!D103 | I22: =SUM(I20:I21) | J22: =I21*5.2
A23: Marca texto verde | B23: 2 | C23: =Angelo!D16 | H23: =SUM(H16:H22) | J23: =SUM(J21:J22)
A24: Ticket lavoura soja e milho | C24: =Angelo!D19 | F24: Transporte Estagiarios (passagens onibus) | G24: 1 | H24: 600
A25: bico microaspersor | B25: 10 | C25: 101.25 | F25: Pesquisa ( Kasuya)
A26: caixa de descarga | B26: 1 | C26: 146 | F26: Kasuya (n° Tratamentos )
A27: condor escova | B27: 4 | C27: 33 | F27: ABAPA
A28: desinf 2l | B28: 5 | C28: 85 | F28: HVI (1,58/amostra fardo de 240 kg) | G28: 0 | H28: 0
A29: Detergente liq 500ml neutro | B29: 48 | F29: Anuidade (R$ 6/há) | G29: 0 | H29: 0
A30: detergente neutro 5l | B30: 6 | C30: 520 | H30: =SUM(H28:H29)
A31: Escova | B31: 4 | C31: 102 | F31: Treinamentos, Coaching, Reuniões Trimestrais | H31: =RH!C34
A32: esponja multiuso | B32: 10 | C32: 23 | F32: SF2 (Sinal GPS tratores) | G32: 2 | H32: 16000
A33: facão | B33: 1 | C33: 140 | F33: CREA
A34: familiar sup. Papel | B34: 9 | C34: 95 | F34: ART SAFRA (n° Matric.) | G34: 15 | H34: =G34*90
A35: fita veda rosca censi 18x10m | B35: 2 | C35: 24 | F35: ART José Victor | G35: 1 | H35: 600
A36: inseticida aerosol multi | B36: 1 | C36: 26 | F36: Anuidade Angelo | G36: 1 | H36: 40
A37: inseticidada aerosol citronela | B37: 1 | C37: 26 | F37: Anuidade Agroinvest | G37: 1 | H37: 3275.01
A38: lampada bulbo led 9w 6500k | B38: 15 | C38: 400 | H38: =SUM(H34:H37)
A39: Pá de bico c/cabo 120cm | B39: 1 | C39: 210 | F39: Vigilancia Fazenda (mensalidade) | G39: 12 | H39: =11930*G39
A40: Pá plastica | F40: Laboratorio de analises | G40: N° amostras
A41: Pano de chão | B41: 10 | C41: 123 | F41: Analise de solo Macro e Micro | H41: =SUM(I42:J42) | I41: 345 | J41: 115
A42: papel toalha fl22x21 | B42: 14 | C42: 2750 | F42: Analise de solo Biologica | G42: 4 | H42: =Tecnico!D39 | I42: =I41*30 | J42: =J41*60
A43: Rastel | B43: 4 | C43: 61 | F43: Analise de solo e folhas | G43: 40 | H43: =Tecnico!D34
A44: resistencia para choveiro | B44: 2 | C44: 85 | H44: =SUM(H41:H43)
A45: resistencia para chuveiro 4600w | B45: 2 | C45: 96 | F45: Exames e consultas periodicas e admissionais
A46: sabaao em po 5kg | B46: 2 | C46: 210 | F46: Conusltas medicas e exames Admissionais | H46: =RH!M20
A47: sabao glicerinado 5x200g | B47: 3 | C47: 75
A48: sabonete 90g | B48: 12 | C48: 250 | F48: Consultas e Exames Periodicos | H48: =RH!P11
A49: sabonete liquido 5l | B49: 5 | C49: 610 | F49: Consultas medicas e exames Demissionais | H49: =RH!O20
A50: sifao ajustavel multiuso 66c | B50: 4 | C50: 50 | F50: Exame Toxicologio Motoristas | H50: =RH!S18
A51: starhig assepigel | B51: 2 | C51: 150
A52: Vassoura | B52: 2 | C52: 61
A53: torneira orbe lavar BA branc | B53: 4 | C53: 154 | H53: =SUM(H46:H51)
A54: PLACAS DE SEGURANÇA | B54: 1 | C54: =Angelo!D78 | F54: AMB
A55: Filtro dos bebedouros C3 IBBL | B55: 2 | C55: 123 | F55: ATUALIZAÇÃO PCMSO | H55: 0
A56: Filtro dos bebedouros 888 ACQUA GELADA | B56: 2 | C56: 197 | F56: ATUALIZAÇÃO PGSSMATR | H56: 0
F57: MENSALIDADE | G57: 1 | H57: =Angelo!D37 | I57: =Angelo!E35
C58: =SUM(C11:C56) | G58: -
A59: Uniformes | C59: 5000
A60: Extintores | H60: =SUM(H55:H59)
A61: Recarga de agua 10 Lt | B61: 6 | C61: =Angelo!D42 | F61: AIBA
A62: Recarga de agua 75 Lt | B62: 1 | C62: =Angelo!D43 | F62: Anuidade | G62: Cancelado | H62: 0
A63: Recarga de pó 4 kg | B63: 2 | C63: =Angelo!D44 | F63: Operação Safra (R$ 1,5/há) | G63: Cancelado | H63: 0
A64: Recarga de pó 6 kg | B64: 7 | C64: =Angelo!D45 | H64: =SUM(H62:H63)
A65: Recarga de pó 8 kg | B65: 1 | C65: =Angelo!D46 | F65: Taxa Fiscalização Funcionamento (LEM) | H65: 841.33
A66: Recarga de pó 12 kg | B66: 6 | C66: =Angelo!D47 | F66: Solfinftec
A67: Recarga de Co2 6 kg | B67: 1 | C67: =Angelo!D48 | F67: Comodato do sistema completo Solinftec | G67: 0 | H67: 74937
A68: Recarga de Co2 4 kg | B68: 1 | C68: =Angelo!D49 | F68: Plataforma Farmbox (R$/há) | G68: 2.55 | H68: =G68*2300
A69: Travas | B69: 4 | C69: =Angelo!D50 | F69: Inspeções /Aferições
A70: Pintura | B70: 5 | C70: =Angelo!D51 | F70: Inspeção Caldeira | G70: 1 | H70: =Angelo!D85
A71: Difusor | B71: 1 | C71: =Angelo!D52 | F71: Tratamanto agua caldeira | G71: 1 | H71: =Angelo!D86
A72: Teste Hidrostatico | B72: 1 | C72: =Angelo!D53 | F72: Inspeção Compressor | G72: 2 | H72: =Angelo!D87
A73: Mangueira | B73: 1 | C73: =Angelo!D54 | F73: Calibração Gasalert | G73: 2 | H73: =Angelo!D88
B74: 4 | C74: =Angelo!D55 | F74: Aferição balança Imetro | G74: 2 | H74: =Angelo!D89
F75: Manutençao balança | G75: 2 | H75: =Angelo!D90
C76: =SUM(C61:C74) | F76: Potabilidade agua | G76: 4 | H76: =Angelo!D91
A77: EPIs | C77: 11013 | H77: =SUM(H70:H76)
A78: CAIXA DE PRIMEIROS SOCORROS | B78: CAIXA DE PRIMEIROS SOCORROS | C78: CAIXA DE PRIMEIROS SOCORROS | F78: Eletrecista (Mão de obra+km) | G78: 5 | S78: VALDIMIR DA SILVA FLORES | T78: M | U78: 3
A79: Algodão 50gr | B79: 5 | C79: =Angelo!D61 | F79: Detetização Cantina e alojamentos | H79: 3600 | S79: VALMIRA FERREIRA DOS ANJOS | T79: GG | U79: 3
A80: Atadura de crepom | B80: 15 | C80: =Angelo!D62 | F80: Manutenção rede de intertne e telefone | S80: VICTOR JUAREZ HOFFMANN | T80: G | U80: 3
A81: Compressa de gaze 7,5x7,5cm | B81: 25 | C81: =Angelo!D63 | F81: Carroll Serviços (serviços administrativos) | H81: ='Orçam-Realiza'!D48*1.5% | S81: WAGNER DE OLIVEIRA | T81: G | U81: 8
A82: Cotonete | B82: 7 | C82: =Angelo!D64 | G82: TOTAL | H82: =SUM(H3,H4,H6,H7,H12:H14,H23,H24,H26,H30,H31,H32,H38,H39,H44,H53,H60,H64,H65,H67,H68,H77,H78,H79,H80:H81) | S82: CONTRATAÇOES | T82: M | U82: 8
A83: Band eid | B83: 7 | C83: =Angelo!D65 | S83: CONTRATAÇOES | T83: GG | U83: 8
A84: Esparadrapo 10x4,5 cm | B84: 7 | C84: =Angelo!D66 | S84: CONTRATAÇOES | T84: P | U84: 6
A85: Lanterna pequena | B85: 5 | C85: =Angelo!D67 | S85: CONTRATAÇOES | T85: G | U85: 3
A86: Luvas de procedimentos cirurgico cx | B86: 1 | C86: =Angelo!D68 | S86: ESTAGIARIO 1 | T86: G | U86: 3
A87: Sabão liquido bactericida | B87: 7 | C87: =Angelo!D69 | S87: ESTAGIARIO 2 | T87: G | U87: 3
A88: Polvidine 100 ml | B88: 7 | C88: =Angelo!D70
A89: Soro fisiologico 0,9% | B89: 8 | C89: =Angelo!D71 | S89: ESTAGIARIO 3 | T89: G | U89: 3
A90: Tesoura sem ponto | B90: 4 | C90: =Angelo!D72 | S90: ESTAGIARIO 4 | T90: G | U90: 3
A91: Caixa para colocar o material | B91: 1 | C91: =Angelo!D73 | S91: ESTAGIARIO 5 | T91: G | U91: 3
C92: =SUM(C79:C91) | S92: ESTAGIARIO 6 | U92: =SUM(U78:U91) | V92: 64.5 | X92: =(U92*V92)
A93: Secador de Grãos | S93: TOTAL
A94: Lenha para secador 3 cargas | C94: 75000 | T94: Jaleco | U94: Quant | V94: Tamanho | W94: Valor und | X94: Total
A95: Ti | C95: =Pedro!E30 | S95: Nome | T95: Eq tecnica | U95: 8 | V95: GG | W95: 92 | X95: =(U95*W95)
B96: Total | C96: =SUM(C95,C94,C92,C77,C76,C59,C58,C9,C8,C3) | S96: Marcio A | T96: Oficina | U96: 6 | V96: 4 G, 2 GG e 6 EX | W96: 92 | X96: =(U96*W96)
S97: Dalvan | W97: Total | X97: =SUM(X95,X96)

Sheet Folha pagamento 
B1: Salário | C1: Quiquenio | D1: Insalubridade | E1: Periculosidade | F1: HE 50% | G1: HE 100% | H1: DSR | I1: Adic. Férias | J1: 13º | K1: INSS Empre | L1: FGTS | M1: Total Mensal | N1: Total anual | T1: Out | U1: Nov | V1: Dez | W1: Jan | X1: Fev | Y1: Mar | Z1: Abr | AA1: Mai | AB1: Jun | AC1: Jul | AD1: Ago | AE1: Set
A2: Plantio e TS | S2: Romerio | AB2: férias
A3: Romerio | B3: 15000 | C3: =B3*10% | D3: 293 | E3: 0 | I3: =(B3+C3+D3)*33%/12 | J3: =SUM(A3:G3)/12 | K3: =SUM(B3:J3)*2.7% | L3: =SUM(B3:J3)*8% | M3: =SUM(B3:L3) | N3: =M3*12 | S3: Paulo Vitor | AB3: férias
A4: Paulo Vitor | B4: 3700 | D4: 293 | E4: 0 | F4: =(B4+D4)/220*1.5*24 | G4: =(B4+D4)/220*2*10 | H4: =(F4+G4)/26*4 | I4: =SUM(B4:H4)*33%/12 | J4: =SUM(A4:H4)*8% | K4: =SUM(B4:J4)*2.7% | L4: =SUM(F4:K4)*8% | M4: =SUM(B4:L4) | N4: =M4*12 | S4: Raimundo | AC4: férias
A5: Raimundo | B5: 2200 | E5: =B5*30% | F5: =(B5+E5)/220*1.5*20 | G5: =(B5+E5)/220*2*10 | H5: =(F5+G5)/26*4 | I5: =SUM(B5:H5)*33%/12 | J5: =SUM(A5:H5)*8% | K5: =SUM(B5:J5)*2.7% | L5: =SUM(F5:K5)*8% | M5: =SUM(B5:L5) | N5: =M5*12 | S5: Marcos Santana | AD5: férias
E6: =B6*30% | F6: =(B6+D6)/220*1.5*20 | G6: =(B6+D6)/220*2*15 | H6: =(F6+G6)/26*4 | I6: =SUM(B6:H6)*33%/12 | J6: =SUM(A6:H6)*8% | K6: =SUM(B6:J6)*2.7% | L6: =SUM(F6:K6)*8% | M6: =SUM(B6:L6) | N6: =M6*12 | S6: Wanderson | AC6: Férias
A7: Marcos Santana | B7: 4000 | D7: 293 | F7: =(B7+D7)/220*1.5*20 | G7: =(B7+D7)/220*2*10 | H7: =(F7+G7)/26*4 | I7: =SUM(B7:H7)*33%/12 | J7: =SUM(A7:H7)*8% | K7: =SUM(B7:J7)*2.7% | L7: =SUM(F7:K7)*8% | M7: =SUM(B7:L7) | N7: =M7*12 | S7: Wanderson | AC7: Férias
A8: Wanderson | B8: 6500 | D8: 293 | E8: 0 | I8: =(B8+C8+D8)*33%/12 | J8: =SUM(A8:G8)/12 | K8: =SUM(B8:J8)*2.7% | L8: =SUM(B8:J8)*8% | M8: =SUM(B8:L8) | N8: =M8*12 | S8: Bruno | AB8: Férias
A9: Bruno | B9: 3700 | D9: 293 | E9: 0 | F9: =(B9+D9)/220*1.5*20 | G9: =(B9+D9)/220*2*10 | H9: =(F9+G9)/26*4 | I9: =SUM(B9:H9)*33%/12 | J9: =SUM(A9:H9)*8% | K9: =SUM(B9:J9)*2.7% | L9: =SUM(F9:K9)*8% | M9: =SUM(B9:L9) | N9: =M9*12 | S9: Francidalva | AB9: Férias
A10: Motorista | B10: 3100 | D10: 293 | E10: 0 | F10: =(B10+D10)/220*1.5*20 | G10: =(B10+D10)/220*2*15 | H10: =(F10+G10)/26*4 | I10: =SUM(B10:H10)*33%/12 | J10: =SUM(A10:H10)*8% | K10: =SUM(B10:J10)*2.7% | L10: =SUM(F10:K10)*8% | M10: =SUM(B10:L10) | N10: =M10*6
A11: Nanci | B11: 2200 | F11: =(B11+D11)/220*1.5*5 | G11: =(B11+D11)/220*2*10 | H11: =(F11+G11)/26*4 | I11: =SUM(B11:H11)*33%/12 | J11: =SUM(A11:H11)*8% | K11: =SUM(B11:J11)*2.7% | L11: =SUM(F11:K11)*8% | M11: =SUM(B11:L11) | N11: =M11*12
A12: Francidalva | B12: 2500 | F12: =(B12+D12)/220*1.5*10 | G12: =(B12+D12)/220*2*7 | H12: =(F12+G12)/26*4 | I12: =SUM(B12:H12)*33%/12 | J12: =SUM(A12:H12)*8% | K12: =SUM(B12:J12)*2.7% | L12: =SUM(F12:K12)*8% | M12: =SUM(B12:L12) | N12: =M12*12 | S12: Fabio
A14: Wilton | B14: 2300 | D14: 293 | F14: =(B14+E14)/220*1.5*20 | G14: =(B14+E14)/220*2*10 | H14: =(F14+G14)/26*4 | I14: =SUM(B14:H14)*33%/12 | J14: =SUM(A14:H14)*8% | K14: =SUM(B14:J14)*2.7% | L14: =SUM(F14:K14)*8% | M14: =SUM(B14:L14) | N14: =M14*12
A15: Marcos magalhães | B15: 3300 | D15: 293 | E15: 0 | F15: =(B15+D15)/220*1.5*20 | G15: =(B15+D15)/220*2*8 | H15: =(F15+G15)/26*4 | I15: =SUM(B15:H15)*33%/12 | J15: =SUM(A15:H15)*8% | K15: =SUM(B15:J15)*2.7% | L15: =SUM(F15:K15)*8% | M15: =SUM(B15:L15) | N15: =M15*12
A16: Joelson | B16: 3500 | D16: 293 | E16: 0 | F16: =(B16+D16)/220*1.5*40 | G16: =(B16+D16)/220*2*15 | H16: =(F16+G16)/26*4 | I16: =SUM(B16:H16)*33%/12 | J16: =SUM(A16:H16)*8% | K16: =SUM(B16:J16)*2.7% | L16: =SUM(F16:K16)*8% | M16: =SUM(B16:L16) | N16: =M16*12
A17: Angelo | B17: 4254.95 | N17: =B17*12
A18: Rosivaldo | B18: =6300*0.3 | E18: 0 | I18: =(B18+C18+F17)*33%/12 | J18: =SUM(A18:G18)/12 | K18: =SUM(B18:J18)*2.7% | L18: =SUM(B18:J18)*8% | M18: =SUM(B18:L18) | N18: =M18*12
A19: Pedro | B19: 1321 | I19: =(B19+C19+G19)*33%/12 | J19: =SUM(A19:G19)/12 | K19: =SUM(B19:J19)*2.7% | L19: =SUM(B19:J19)*8% | M19: =SUM(B19:L19) | N19: =M19*12
A20: valdimir | B20: 2778.804 | E20: 0 | M20: =SUM(B20:L20) | N20: =M20*12
A21: Marcos schu | B21: 3000 | C21: =B21*5% | D21: 293 | E21: 0 | I21: =(B21+C21+F18)*33%/12 | J21: =SUM(A21:G21)/12 | K21: =SUM(B21:J21)*2.7% | L21: =SUM(B21:J21)*8% | M21: =SUM(B21:L21) | N21: =M21*3.6
A22: Estagiario | B22: 1500 | M22: =SUM(B22:L22)*2 | N22: =M22*12
A23: Cartâo vale transporte | B23: =RH!F1 | N23: =RH!I4
A24: Total | B24: =SUM(B3:B22) | D24: =SUM(D3:D22) | E24: =SUM(E3:E22) | F24: =SUM(F3:F22) | G24: =SUM(G3:G22) | H24: =SUM(H3:H22) | I24: =SUM(I3:I22) | J24: =SUM(J3:J22) | K24: =SUM(K3:K22) | ... M24: =SUM(M3:M22) | N24: =SUM(N3:N23)
N25: =N24-'Orçamento Resumo'!K8
N27: =N24/14
N28: =N27*2
N29: =N28/4
N40: =SUM(N27:N39)

Sheet Quimi. Fert. Semente
A3: Semente | B3: Semente | C3: Semente | D3: Semente | F3: Quimicos | G3: Quimicos | H3: Quimicos | I3: Quimicos | K3: Adubo | L3: Adubo | M3: Adubo | N3: Adubo
A4: Agroinvest | B4: Hectar | C4: U$/há | D4: Total | F4: Agroinvest | G4: Hectar | H4: U$/há | I4: Total | K4: Agroinvest | L4: Hectar | M4: U$/há | N4: Total
A5: Soja Intacta | B5: 900 | C5: 83.57 | D5: =B5*C5 | F5: Soja Intacta | G5: =B5 | H5: 154.15 | I5: =G5*H5 | K5: Soja | L5: =SUM(G5:G6) | M5: 105 | N5: =L5*M5
A6: Soja Convencional | B6: 0 | C6: 0 | D6: =B6*C6 | F6: Soja Convencional | G6: =B6 | H6: 0 | I6: =G6*H6 | K6: Milho | L6: =SUM(G7:G9) | M6: 406 | N6: =L6*M6
A7: Milho Refugio | B7: 0 | C7: 0 | D7: =B7*C7 | F7: Milho Refugio | G7: =B7 | H7: 0 | I7: =G7*H7 | K7: Algodão | L7: =SUM(G10:G13) | M7: 0 | N7: =L7*M7
A8: Milho Leptra | B8: 1380 | C8: 187 | D8: =B8*C8 | F8: Milho Leptra | G8: =B8 | H8: 138.61 | I8: =G8*H8
A9: Milho PRO/PW | B9: 0 | C9: 0 | D9: =B9*C9 | F9: Milho PRO/PW | G9: =B9 | H9: 0 | I9: =G9*H9 | N9: =SUM(N5:N7)
A10: Algodão WS | B10: 0 | C10: 0 | D10: =B10*C10 | F10: Algodão WS | G10: =B10 | H10: 0 | I10: =G10*H10 | N10: =N9*'Orçam-Realiza'!D29
A11: Algodão GLT | B11: 0 | C11: 0 | D11: =B11*C11 | F11: Algodão GLT | G11: =B11 | H11: 0 | I11: =G11*H11
A12: Algodão B2RRF | B12: 0 | C12: 0 | D12: =B12*C12 | F12: Algodão B2RRF | G12: =B12 | H12: 0 | I12: =G12*H12
A13: Algodão RR | B13: 0 | C13: 0 | D13: =B13*C13 | F13: Algodão RR | G13: =B13 | H13: 0 | I13: =G13*H13
D14: =SUM(D5:D13) | I14: =SUM(I5:I13)
D15: =D14*'Orçam-Realiza'!D29 | I15: =I14*'Orçam-Realiza'!D29
F21: SAFRA 25-26 | G21: SAFRA 25-26 | H21: SAFRA 25-26 | I21: SAFRA 25-26 | J21: SAFRA 25-26
F22: Soja | G22: =C5+H5+M5 | H22: 900 | I22: =H22*G22 | J22: =I22*'Orçam-Realiza'!$D$29
F23: Milho | G23: =C8+H8+M6 | H23: 1380 | I23: =H23*G23 | J23: =I23*'Orçam-Realiza'!$D$29
I24: =SUM(I22:I23) | J24: =I24*'Orçam-Realiza'!$D$29
F26: SAFRA 24-25 | G26: SAFRA 24-25 | H26: SAFRA 24-25 | I26: SAFRA 24-25 | J26: SAFRA 24-25
F27: Soja | G27: 358.68977 | H27: 1380 | I27: 494991.88 | J27: 2771954.5
F28: Milho | G28: 694.25046 | H28: 900 | I28: 624825.41 | J28: 3499022.3
I29: 1119817.3 | J29: 6270976.8
F31: SAFRA 23-24 | G31: SAFRA 23-24 | H31: SAFRA 23-24 | I31: SAFRA 23-24 | J31: SAFRA 23-24
F32: Soja | G32: 360.39 | H32: 1600 | I32: =H32*G32 | J32: =I32*'Orçam-Realiza'!$D$29
F33: Milho | G33: 823.43 | H33: 700 | I33: =H33*G33 | J33: =I33*'Orçam-Realiza'!$D$29
I34: =SUM(I32:I33) | J34: =I34*'Orçam-Realiza'!$D$29
F36: SAFRA 22-23 | G36: SAFRA 22-23 | H36: SAFRA 22-23 | I36: SAFRA 22-23 | J36: SAFRA 22-23
F37: Soja | G37: 360.69 | H37: 1600 | I37: =H37*G37 | J37: =I37*'Orçam-Realiza'!$D$29
F38: Milho | G38: =SUM(C8,H8,M6) | H38: 700 | I38: =H38*G38 | J38: =I38*'Orçam-Realiza'!$D$29
I39: =SUM(I37:I38) | J39: =I39*'Orçam-Realiza'!$D$29
F40: SAFRA 21-22 | G40: SAFRA 21-22 | H40: SAFRA 21-22 | I40: SAFRA 21-22 | J40: SAFRA 21-22
F41: Soja | G41: 347.57 | H41: 4127 | I41: =H41*G41 | J41: =I41*5.15
F42: Milho | G42: 667.19 | H42: 1642 | I42: =H42*G42 | J42: =I42*5.15
I43: =SUM(I41:I42) | J43: =SUM(J41:J42)
F44: SAFRA 20-21 | G44: SAFRA 20-21 | H44: SAFRA 20-21 | I44: SAFRA 20-21 | J44: SAFRA 20-21
F45: Soja | G45: =1221.02/5.4 | H45: 5750 | I45: =H45*G45 | J45: =I45*5.15
F46: Milho | G46: 0 | H46: =H9 | I46: =H46*G46 | J46: =I46*5.15
I47: =SUM(I45:I46) | J47: =SUM(J45:J46)

Sheet Contratação serviç.
A2: Operação | B2: Hectares | C2: SC/HÁ e R$/ha
A3: Colheita Soja e Milho | B3: 2300 | C3: 2.2 | D3: =(C3*2300)*120
A4: Safrinha | B4: 300 | C4: 1.8 | D4: =(C4*B4)*55
D5: =SUM(D3:D4)
A6: FRETE SOJA p TRADE | B6: FRETE SOJA p TRADE | C6: FRETE SOJA p TRADE | D6: FRETE SOJA p TRADE
B7: T produção | C7: T FOB | D7: Frete
A8: Agroinvest X BV | B8: 1290 | D8: =B8*15
A9: Agroinvest x Cargil | B9: 1020 | D9: =B9*50
A10: Agroinvest x Placas | B10: 1212 | D10: =B10*38
A11: FRETE p Secador e Silos | B11: FRETE p Secador e Silos | C11: FRETE p Secador e Silos | D11: FRETE p Secador e Silos
A12: Produto | B12: T | C12: R$/T | D12: Total Frete
D13: =C13*B13
A14: Soja | B14: 1200 | C14: 16 | D14: =C14*B14
A15: Milho | B15: 7000 | C15: 14 | D15: =C15*B15
D16: =C16*B16 | H16: Silo beg | I16: 4
C17: Cambio 5,20 | H17: Custo | I17: =(I16*2600)*1.1
C18: Total FRETE | D18: =SUM(D13:D17,D10) | F18: Silo bolsa | G18: =I17+I8
A19: TOTAL Seviçõs | B19: =D5+D8+D9+D10+D18
A23: Prancha para logistica de maquinas e equipamentos | B23: Prancha para logistica de maquinas e equipamentos | C23: Prancha para logistica de maquinas e equipamentos
A24: Equipamento | B24: KM
A25: Rolo faca | B25: 800 | C25: =B25*8.5
A26: Niveladora | B26: 800 | C26: =B26*8.5
A27: Fiat strada ou s10 | C27: =B27*15
A28: Trator alugado | C28: =B28*15
C29: =SUM(C25:C28)
A31: Fretes | B31: KM
A32: Quimicos | B32: 1260 | C32: =B32*4
A33: Embalagens | B33: 2 viagens | C33: 3000
A34: Cascalhos | B34: 4 viagens | C34: 5000
C35: =SUM(C32:C34)

Sheet Avião
A1: Orçamento 2025/2026 | B1: Orçamento 2025/2026 | C1: Orçamento 2025/2026 | D1: Orçamento 2025/2026 | E1: Orçamento 2025/2026 | F1: Orçamento 2025/2026 | G1: Orçamento 2025/2026 | H1: Orçamento 2025/2026 | I1: Orçamento 2025/2026 | J1: Orçamento 2025/2026 | K1: Orçamento 2025/2026 | L1: Orçamento 2025/2026 | M1: Orçamento 2025/2026 | N1: Orçamento 2025/2026 | O1: Orçamento 2025/2026 | P1: Orçamento 2025/2026 | Q1: Orçamento 2025/2026 | R1: Obs
A2: Orçamento 2025/2026 | B2: Orçamento 2025/2026 | C2: Orçamento 2025/2026 | D2: Orçamento 2025/2026 | E2: Orçamento 2025/2026 | F2: Orçamento 2025/2026 | G2: Orçamento 2025/2026 | H2: Orçamento 2025/2026 | I2: Orçamento 2025/2026 | J2: Orçamento 2025/2026 | K2: Orçamento 2025/2026 | L2: Orçamento 2025/2026 | M2: Orçamento 2025/2026 | N2: Orçamento 2025/2026 | O2: Orçamento 2025/2026 | P2: Orçamento 2025/2026 | Q2: Orçamento 2025/2026 | X2: ORÇAMENTO BASE ZERO ACFT SENECA V (PR-PME) /Meridian500 | Y2: ORÇAMENTO BASE ZERO ACFT SENECA V (PR-PME) /Meridian500 | Z2: ORÇAMENTO BASE ZERO ACFT SENECA V (PR-PME) /Meridian500 | AA2: ORÇAMENTO BASE ZERO ACFT SENECA V (PR-PME) /Meridian500 | AB2: ORÇAMENTO BASE ZERO ACFT SENECA V (PR-PME) /Meridian500 | AC2: ORÇAMENTO BASE ZERO ACFT SENECA V (PR-PME) /Meridian500 | AD2: ORÇAMENTO BASE ZERO ACFT SENECA V (PR-PME) /Meridian500 | AE2: ORÇAMENTO BASE ZERO ACFT SENECA V (PR-PME) /Meridian500
A3: Orçamento 2025/2026 | B3: Orçamento 2025/2026 | C3: Orçamento 2025/2026 | D3: Orçamento 2025/2026 | E3: Orçamento 2025/2026 | F3: Orçamento 2025/2026 | G3: Orçamento 2025/2026 | H3: Orçamento 2025/2026 | I3: Orçamento 2025/2026 | J3: Orçamento 2025/2026 | K3: Orçamento 2025/2026 | L3: Orçamento 2025/2026 | M3: Orçamento 2025/2026 | N3: Orçamento 2025/2026 | O3: Orçamento 2025/2026 | P3: Orçamento 2025/2026 | Q3: Orçamento 2025/2026 | X3: ITEM | Y3: QUANTIDADE | AA3: VALOR
D4: out | E4: Nov | F4: Dez | G4: jan | H4: Fev | I4: Mar | J4: Abr | K4: Mai | M4: Horas | O4: Total | P4: Valor unid | Q4: Total R$ | X4: Seguro reta | Y4: 1 | Z4: 767.88 | AA4: =Z4*Y4
A5: Aplicação Aerea | B5: Descrição | D5: Agroservice 1º fung soja 5.637 2º fung soja 5.637 3º fung soja 5.637 4º Fung soja 5.637 5°micro/ins 1º ins milho 3.678 2º ins milho 3.678 3º ins milho 3.678 4º fun milho 3.678 5º fun milho 3.678 6º ins milho 3.678 7° ins milho 8°ins milho Agroinvest= 5000 ha | E5: Agroservice 1º fung soja 5.637 2º fung soja 5.637 3º fung soja 5.637 4º Fung soja 5.637 5°micro/ins 1º ins milho 3.678 2º ins milho 3.678 3º ins milho 3.678 4º fun milho 3.678 5º fun milho 3.678 6º ins milho 3.678 7° ins milho 8°ins milho Agroinvest= 5000 ha | F5: Agroservice 1º fung soja 5.637 2º fung soja 5.637 3º fung soja 5.637 4º Fung soja 5.637 5°micro/ins 1º ins milho 3.678 2º ins milho 3.678 3º ins milho 3.678 4º fun milho 3.678 5º fun milho 3.678 6º ins milho 3.678 7° ins milho 8°ins milho Agroinvest= 5000 ha | G5: Agroservice algodão 22 aplicação inseticida total 5280 Há fugincida 6 aplicação total 1440Ha Agroinvest = 6000 há | H5: 3500 mix de cobertura pivõ 10 aplicações =1600 | I5: 3 aplicações inseticida Safrinha 1500 | L5: AGROSERVICE milho = 29424 soja=28.185 algodão=6.720 sorgo=1.500 pivô milho=1.600 AGROINVEST=11.000 TOTAL=78.429 | O5: 78429 | X5: Atendiemnto Angar Icaro (BSB) | Y5: 12 | Z5: 1500 | AA5: =Z5*Y5
A6: Air tractor B502 | B6: Area trabalhada | C6: Há liquido 20 | D6: 9600 | E6: 22548 | F6: 29933 | G6: 12608 | H6: 2240 | I6: 1500 | O6: =SUM(D6:N6) | X6: jeepson -Renovação assinatura garmim | Y6: 1 | Z6: 6400 | AA6: =Z6*Y6 | AD6: Valor aquisição Meridian | AE6: 3175000
A7: Air tractor B502 | B7: Area trabalhada | X7: Revisoes/manutençoes | Y7: 1 | Z7: 40000 | AA7: =Z7*Y7 | AD7: Agroservice 50% | AE7: =AE6/2
A8: Air tractor B502 | B8: Area trabalhada | C8: há solido | H8: 3500 | M8: 40/h | O8: =SUM(F8:J8) | P8: 500 | Q8: 20000 | X8: Angarage | Y8: 12 | Z8: 850 | AA8: =Z8*Y8
A9: Air tractor B502 | B9: Horas trabalhada | C9: Hora | D9: =SUM(D6:D7)/185 | E9: =SUM(E6:E7)/185 | F9: =SUM(F6:F7)/185 | G9: =SUM(G6:G7)/185 | H9: =SUM(H6:H7)/185 | I9: =SUM(I6:I7)/185 | J9: =J6/175 | O9: =SUM(D9:J9) | X9: Piloto | Y9: 13 | Z9: 9000 | AA9: =Z9*Y9
A10: Air tractor B502 | B10: Querosene | C10: Lt | D10: =220*D9 | E10: =220*E9 | F10: =220*F9 | G10: =220*G9 | H10: =220*H9 | I10: =220*I9 | O10: =SUM(D10:J10) | P10: 6 | Q10: =P10*O10 | X10: Combustivel (querosene) | Y10: 12 | Z10: 5625 | AA10: =Z10*Y10
A11: Air tractor B502 | B11: Oleo Motor/turbina | C11: Lt | D11: =D9/20 | E11: =E9/20 | F11: =F9/20 | G11: =G9/20 | H11: =H9/20 | I11: 0 | O11: =SUM(D11:J11) | P11: 60 | Q11: =P11*O11 | X11: Taxas Inframerica (pousos) + Decea (tarifa uso EP) | Y11: 12 | Z11: 920.84 | AA11: =Z11*Y11
A12: Air tractor B502 | B12: REVISÃO 100/Hr | O12: 1 | P12: 6380 | Q12: 6380 | Y12: Total | AA12: =SUM(AA4:AA11)
A13: Air tractor B502 | B13: REVISÃO 200/Hr | O13: 1 | P13: 1540 | Q13: 1540
A14: Air tractor B502 | B14: REVISÃO 300/Hr | O14: 1 | P14: 9350 | Q14: 9350
A15: Air tractor B502 | B15: TBO turbina | C15: Und | J15: 1 | O15: 1 | P15: 1070000 | Q15: =P15*O15/10
A16: Air tractor B502 | B16: IAM | C16: R$ | J16: 1 | O16: =SUM(D16:J16) | P16: 25000 | Q16: =P16*O16 | R16: Custo de peças durante as revisões de 100,200,300 horas
A17: Air tractor B502 | B17: Seguro reta | C17: R$ | J17: 1 | O17: =SUM(D17:J17) | P17: 600 | Q17: =P17*O17
A18: Air tractor B502 | B18: Mão de obra manutenção | C18: R$ | J18: 1 | O18: =SUM(D18:J18) | P18: 80000 | Q18: =P18*O18
A19: Air tractor B502 | B19: Peças revisão | C19: R$ | O19: 1 | P19: 50000 | Q19: =P19*O19
A20: Air tractor B502 | B20: Pneus dianteiro | C20: Und | D20: 2 | O20: =SUM(D20:J20) | P20: 7000 | Q20: =P20*O20
A21: Air tractor B502 | B21: Camara ar | C21: Und | D21: 2 | O21: =SUM(D21:J21) | P21: 1600 | Q21: =P21*O21 | R21: revisão efetuada safra 23-24 | S21: revisão efetuada safra 23-24 | T21: revisão efetuada safra 23-24
A22: Air tractor B502 | B22: Pneu bequilha | C22: Und | D22: 1 | O22: =SUM(D22:J22) | P22: 1200 | Q22: =P22*O22
A23: Air tractor B502 | B23: Camara bequilha | C23: Und | D23: 1 | O23: =SUM(D23:J23) | P23: 550 | Q23: =P23*O23
A24: Air tractor B502 | B24: Revisao pós safra | O24: 1 | P24: 150000 | Q24: =O24*P24
A25: Air tractor B502 | B25: Pastilha freio | C25: Und | F25: 12 | J25: 24 | O25: =SUM(D25:J25) | P25: 75 | Q25: =P25*O25
A26: Air tractor B502 | B26: Escova limpa sensor | C26: Und | E26: 1 | G26: 1 | O26: 3 | P26: 30 | Q26: 90
A27: Air tractor B502 | B27: Filtro ar o par | C27: Und | E27: 2 | F27: 2 | G27: 2 | O27: 6 | P27: 380 | Q27: =P27*O27
A28: Air tractor B502 | B28: Filtro combustivel | C28: Und | D28: 1 | F28: 1 | I28: 1 | O28: =SUM(D28:J28) | P28: 65 | Q28: =P28*O28
A29: Air tractor B502 | B29: Saco de estoupa | C29: Und | D29: 1 | O29: =SUM(D29:J29) | P29: 120 | Q29: =P29*O29
A30: Air tractor B502 | B30: Cera para brisa | C30: Und | D30: 1 | O30: =SUM(D30:J30) | P30: 230 | Q30: =P30*O30
A31: Air tractor B502 | B31: Reparos bomba solução | C31: und | D31: 2 | O31: 2 | P31: 375 | Q31: =P31*O31
A32: Air tractor B502 | B32: conjunto de bicos cp 11tt | C32: und | D32: 42 | O32: 42 | P32: 521.38 | Q32: =P32*O32
A33: Air tractor B502 | B33: bomba eólica | C33: und | D33: 1 | O33: 1 | P33: 7156.59 | Q33: =P33*O33
A34: Air tractor B502 | B34: funil inox duas curvas | C34: und | D34: 1 | O34: =SUM(D34:N34) | P34: 65 | Q34: =P34*O34
A35: Air tractor B502 | B35: Detergente neutro | C35: Und | D35: 36 | O35: =SUM(D35:J35) | P35: 4 | Q35: =P35*O35
A36: Acessorios de aplicação | B36: Mangueira 3 pol | C36: mt | D36: 20 | O36: =SUM(D36:J36) | P36: 75 | Q36: =P36*O36
A37: Acessorios de aplicação | B37: Engate rapido 3 Pol | C37: Und | D37: 4 | O37: =SUM(D37:J37) | P37: 160 | Q37: =P37*O37
A38: Acessorios de aplicação | B38: CADEADO | C38: Und | D38: 1 | O38: 1 | P38: 45 | Q38: 45
A39: Acessorios de aplicação | B39: Registro 3 pol | C39: Und | D39: 2 | O39: =SUM(D39:J39) | P39: 600 | Q39: =P39*O39
A40: Acessorios de aplicação | B40: Mangueira 3 pol flexivel | C40: Mt | D40: 30 | O40: =SUM(D40:J40) | P40: 60 | Q40: =P40*O40
A41: Acessorios de aplicação | B41: Garrafa termica 3 lt | C41: Und | D41: 2 | O41: =SUM(D41:J41) | P41: 60 | Q41: =P41*O41
A42: Acessorios de aplicação | B42: Balde dosador 20 lt | C42: Und | D42: 4 | O42: =SUM(D42:J42) | P42: 175 | Q42: =P42*O42
A43: Acessorios de aplicação | B43: Balde dosador 10 lt | C43: Und | D43: 2 | O43: =SUM(D43:J43) | P43: 75 | Q43: =P43*O43
A44: Acessorios de aplicação | B44: Registro 2pol | C44: Und | D44: 4 | O44: =SUM(D44:J44) | P44: 230 | Q44: =P44*O44
A45: Acessorios de aplicação | B45: Mangueira 2 pol | C45: Mt | D45: 10 | O45: =SUM(D45:J45) | P45: 25 | Q45: =P45*O45
A46: Acessorios de aplicação | B46: Magueira 1Pol | C46: Mt | D46: 15 | O46: =SUM(D46:J46) | P46: 25 | Q46: =P46*O46
A47: Acessorios de aplicação | B47: Registro 1 pol | C47: Und | D47: 4 | O47: =SUM(D47:J47) | P47: 120 | Q47: =P47*O47
A48: Acessorios de aplicação | B48: Pincel para quadro branco | C48: uind | D48: 8 | O48: =SUM(D48:J48) | P48: 8.9 | Q48: =P48*O48
A49: Acessorios de aplicação | B49: Caixa caneta bic | C49: uind | D49: 1 | O49: =SUM(D49:J49) | P49: 32 | Q49: =P49*O49
A50: Acessorios de aplicação | B50: Canivete | C50: Und | D50: 3 | O50: =SUM(D50:J50) | P50: 20 | Q50: =P50*O50
A51: Acessorios de aplicação | B51: Bateria 150 amperes | C51: Und | D51: 2 | O51: 2 | P51: 1000 | Q51: =P51*O51
A52: Acessorios de aplicação | B52: Pre mistura 800L | C52: UND | D52: 1 | O52: =SUM(D52:J52) | P52: 12000 | Q52: =P52*O52
A53: Acessorios de aplicação | B53: Moto bomba 2 tempo | C53: UND | D53: 1 | O53: 1 | P53: 1400 | Q53: =O53*P53
A54: Acessorios de aplicação | B54: 1 moto bomba | C54: Und | D54: 1 | O54: 1 | P54: 4000 | Q54: 4000
A55: F4000 simples | B55: Area trabalhada | C55: Km | D55: 5000 | E55: 6000 | F55: 6000 | G55: 6000 | H55: 6000 | I55: 4000 | O55: =SUM(D55:J55)
A56: F4000 simples | B56: Dissell | C56: Lt | D56: =D55/8 | E56: =E55/8 | F56: =F55/8 | G56: =G55/8 | H56: =H55/8 | I56: =I55/8 | J56: =J55/8 | O56: =SUM(D56:J56) | P56: 5.8 | Q56: =P56*O56
A57: F4000 simples | B57: Oleo 15w40 Motor | C57: Lt | D57: 10 | E57: 3 | F57: 10 | G57: 3 | H57: 10 | O57: =SUM(D57:J57) | P57: 25 | Q57: =P57*O57
A58: F4000 simples | B58: Oleo 15w40 Transmisão | C58: Lt | Q58: =P58*O58
A59: F4000 simples | B59: Graxa | C59: Kg | D59: 5 | E59: 5 | F59: 5 | G59: 5 | H59: 5 | I59: 5 | O59: =SUM(D59:J59) | P59: 40 | Q59: =P59*O59
A60: F4000 simples | B60: Manguiera 1 pol gasolina | C60: Mt | D60: 10 | O60: =SUM(D60:J60) | P60: 70 | Q60: =P60*O60
A61: F4000 simples | B61: Bomba abastecimento | C61: Und | D61: 1 | O61: =SUM(D61:J61) | P61: 1500 | Q61: =P61*O61
A62: F4000 simples | B62: Pistola de Abastecimento | C62: Und | D62: 1 | O62: =SUM(D62:J62) | P62: 160 | Q62: =P62*O62
A63: F4000 simples | B63: Bateria 150 amperes | C63: Und | D63: 2 | O63: =SUM(D63:J63) | P63: 1500 | Q63: =P63*O63
A64: F4000 simples | B64: filtro de querosene | C64: unid | D64: 2 | E64: 2 | F64: 2 | G64: 2 | O64: =SUM(D64:J64) | P64: 25 | Q64: =P64*O64
A65: F4000 simples | B65: bomba para graxa manual 7kg | C65: R$ | D65: 1 | O65: 1 | P65: 499 | Q65: 499
A66: Enpilhadeira | B66: Gas | C66: Und | D66: 1 | E66: 2 | F66: 1 | G66: 1 | O66: =SUM(D66:N66) | P66: 250 | Q66: =P66*O66
A67: Equipe | B67: Papel sensível | C67: Pac | D67: 1 | O67: =SUM(D67:N67) | P67: 280 | Q67: =P67*O67
A68: Equipe | B68: Facao | C68: und | D68: 2 | O68: 2 | P68: 45 | Q68: =P68*O68
A69: Equipe | B69: Papel medir ph | C69: Pac | D69: 2 | O69: =SUM(D69:N69) | P69: 100 | Q69: =P69*O69
A70: Funcionarios Salarios | B70: Vagner vazao 20 | C70: R$ | O70: 87736 | P70: 4.2 | Q70: =O70*P70
A71: Funcionarios Salarios | B71: Vagner vazao 30 | C71: R$ | F71: =3.75*F7 | G71: =3.75*G7 | Q71: =SUM(F71:P71)
A72: Funcionarios Salarios | B72: Vagner solidos | C72: R$ | O72: 40/H | P72: 500 | Q72: 20000
A73: Funcionarios Salarios | B73: TECNICO dosador | C73: R$ | D73: 1 | E73: 1 | F73: 1 | G73: 1 | H73: 1 | I73: 1 | J73: 1 | K73: 1 | O73: =SUM(D73:N73) | P73: 3000 | Q73: =(P73*O73)
A74: Funcionarios Salarios | B74: dosador | C74: R$ | D74: 1 | E74: 1 | F74: 1 | G74: 1 | H74: 1 | I74: 1 | J74: 1 | O74: =SUM(D74:N74) | P74: 2500 | Q74: =(P74*O74)
A75: Salarios horas extras 50% | B75: dosador 1 | C75: R$ | D75: 0 | E75: 48 | F75: 48 | G75: 48 | H75: 30 | I75: 20 | J75: 10 | O75: =SUM(D75:J75) | P75: 20.45 | Q75: =(P75*O75)
A76: Salarios horas extras 50% | B76: Ivanilson | C76: R$ | E76: 48 | F76: 48 | G76: 48 | H76: 30 | I76: 20 | J76: 10 | O76: =SUM(D76:J76) | P76: 17 | Q76: =(P76*O76)
A77: Hora extra 100% | B77: dosador 1 | E77: 40 | F77: 40 | G77: 20 | O77: =SUM(C77:N77) | P77: 27.27 | Q77: =(P77*O77)
A78: Hora extra 100% | B78: Ivanilson | E78: 40 | F78: 40 | G78: 20 | O78: =SUM(D78:N78) | P78: 22.72 | Q78: =(P78*O78)
A79: Periculosidade | B79: dosador 1 | D79: 1 | E79: 1 | F79: 1 | G79: 1 | H79: 1 | I79: 1 | J79: 1 | K79: 1 | O79: =SUM(D79:N79) | P79: 900 | Q79: =(P79*O79)
A80: Periculosidade | B80: Ivanilson | D80: 1 | E80: 1 | F80: 1 | G80: 1 | H80: 1 | I80: 1 | J80: 1 | O80: =SUM(D80:N80) | P80: 720 | Q80: =O80*P80
A81: Uniforme Aplicação | B81: AVIÃO | C81: Desc. | D81: Conj Aplic | E81: Luva Cano C | F81: Luva Cano L | G81: Mascarra 3m | H81: Filtro | I81: Oculos Escuro | J81: Bota Borr | K81: kit 2ª pele | L81: toalha | M81: Avental | N81: sabonete | O81: meia
A82: Uniforme Aplicação | B82: Vagner | C82: Und | D82: 3 | E82: 0 | F82: 0 | G82: 1 | H82: 2 | I82: 0 | J82: 0 | K82: 3 | L82: 1 | N82: 5
A83: Uniforme Aplicação | B83: A contratar | C83: Und | D83: 10 | E83: 5 | F83: 15 | G83: 1 | H83: 5 | I83: 2 | J83: 1 | K83: 3 | L83: 1 | M83: 2 | N83: 5 | O83: 3
A84: Uniforme Aplicação | B84: A contratar | C84: Und | D84: 10 | E84: 5 | F84: 15 | G84: 2 | H84: 5 | I84: 2 | J84: 1 | K84: 3 | L84: 1 | M84: 2 | N84: 5 | O84: 3
A85: Uniforme Aplicação | B85: Total | C85: Und | D85: =SUM(D82:D84) | E85: =SUM(E82:E84) | F85: =SUM(F82:F84) | G85: =SUM(G82:G84) | H85: =SUM(H82:H84) | I85: =SUM(I82:I84) | J85: =SUM(J82:J84) | K85: =SUM(K82:K84) | ... O85: =SUM(O82:O84)
A86: Uniforme Aplicação | B86: Total R$ | C86: R$ | D86: =80*D85 | E86: =10*E85 | F86: =50*F85 | G86: =140*G85 | H86: =95*H85 | I86: =8*I85 | J86: =55*J85 | K86: =60*K85 | L86: =15*L85 | M86: =15*M85 | N86: =2*N85 | O86: =12*O85 | Q86: =SUM(D86:P86)
A87: Uniforme | B87: AVIÃO | C87: Desc. | D87: Conj. Calça/camisa | E87: Luva Pano | F87: Luva vaqueta | G87: Prot. Auricula plug | H87: Prot auricular concha | I87: Mascara PFS1 | J87: Botina | K87: toca arrabe | L87: Garrafa
A88: Uniforme | B88: VAGNER | C88: Unid | D88: 3 | E88: 0 | F88: 0 | G88: 4 | H88: 1 | I88: 20 | J88: 2 | K88: 1 | L88: 1 | N88: 5
A89: Uniforme | B89: a contratar | C89: Unid | D89: 3 | E89: 3 | F89: 1 | G89: 2 | H89: 1 | I89: 10 | J89: 2 | K89: 2 | L89: 1
A90: Uniforme | B90: A contratar | C90: Unid | D90: 3 | E90: 3 | F90: 1 | G90: 2 | H90: 1 | I90: 10 | J90: 2 | K90: 2 | L90: 1
A91: Uniforme | B91: Total | C91: Unid | D91: =SUM(D88:D90) | E91: =SUM(E88:E90) | F91: =SUM(F88:F90) | G91: =SUM(G88:G90) | H91: =SUM(H88:H90) | I91: =SUM(I88:I90) | J91: =SUM(J88:J90) | K91: =SUM(K88:K90) | L91: =SUM(L88:L90) | N91: 5
A92: Uniforme | B92: Total R$ | C92: R$ | D92: =85*D91 | E92: =5*E91 | F92: =5*F91 | G92: =2*G91 | H92: =35*H91 | I92: =5*I91 | J92: =70*J91 | K92: =10*K91 | L92: =45*L91 | N92: 10 | Q92: =SUM(D92:P92)
A94: Total | P94: Total AIR TRACTOR | Q94: =SUM(Q10:Q35)
P96: TOTAL | Q96: =SUM(Q94:Q95)+Q70
P97: Ceneca (8 h de voo) | Q97: =8*2500
P98: Agroservice | Q98: =(Q96*0.85)+Q97
P99: Agroinvest | Q99: =(Q96*0.15)

Sheet Deprecisação 
A1: 10/17/2025 | B1: 10/17/2025 | C1: 10/17/2025 | D1: 10/17/2025 | E1: Agroinvest Ltda | F1: Agroinvest Ltda | G1: Agroinvest Ltda | H1: Agroinvest Ltda | I1: Agroinvest Ltda | J1: Agroinvest Ltda | K1: Agroinvest Ltda
A2: 2:04 PM | B2: 2:04 PM | C2: 2:04 PM | D2: 2:04 PM | E2: Agroinvest Ltda | F2: Agroinvest Ltda | G2: Agroinvest Ltda | H2: Agroinvest Ltda | I2: Agroinvest Ltda | J2: Agroinvest Ltda | K2: Agroinvest Ltda
A3: 2:04 PM | B3: 2:04 PM | C3: 2:04 PM | D3: 2:04 PM
A4: 2:04 PM | B4: 2:04 PM | C4: 2:04 PM | D4: 2:04 PM | E4: Fixed Asset Activity | F4: Fixed Asset Activity | G4: Fixed Asset Activity | H4: Fixed Asset Activity | I4: Fixed Asset Activity | J4: Fixed Asset Activity | K4: Fixed Asset Activity
E5: Fixed Asset Activity | F5: Fixed Asset Activity | G5: Fixed Asset Activity | H5: Fixed Asset Activity | I5: Fixed Asset Activity | J5: Fixed Asset Activity | K5: Fixed Asset Activity
E7: 1/1/2025 to 12/31/2025 | F7: 1/1/2025 to 12/31/2025 | G7: 1/1/2025 to 12/31/2025 | H7: 1/1/2025 to 12/31/2025 | I7: 1/1/2025 to 12/31/2025 | J7: 1/1/2025 to 12/31/2025 | K7: 1/1/2025 to 12/31/2025
D9: Transaction Date | E9: Transaction Date | F9: Transaction Number | G9: Entry Screen | H9: Offset Account | I9: Book Value | J9: Accumulated Depreciation | K9: Depreciable Basis | L9: Depreciable Basis | P9: Valor Mercado 01/10/2024 | Q9: Valor Mercado 01/10/2025 | R9: Depreciação Orçamento | S9: Depreciação Centerpoint 2025
A10: Buildings & Improvements | B10: Buildings & Improvements | C10: Buildings & Improvements | D10: Buildings & Improvements | E10: Buildings & Improvements | F10: Buildings & Improvements | G10: Buildings & Improvements | H10: Buildings & Improvements | I10: Buildings & Improvements | J10: Buildings & Improvements | K10: Buildings & Improvements | L10: Buildings & Improvements | M10: Buildings & Improvements
B11: Buildings and Structures - | C11: Buildings and Structures - | D11: Buildings and Structures - | E11: Buildings and Structures - | F11: Buildings and Structures - | G11: Buildings and Structures - | H11: Buildings and Structures - | I11: Buildings and Structures - | J11: Buildings and Structures - | K11: Buildings and Structures - | L11: Buildings and Structures - | M11: Buildings and Structures -
C12: Irrigation Well | D12: Irrigation Well | E12: Irrigation Well | F12: Irrigation Well | G12: Irrigation Well | H12: Irrigation Well | I12: Irrigation Well | J12: Irrigation Well | K12: Irrigation Well | L12: Irrigation Well | M12: Irrigation Well
D13: 45657 | E13: 45657 | F13: Beg Bal | I13: 172800 | J13: 0 | K13: 172800 | L13: 172800
A14: Irrigation Well Totals | B14: Irrigation Well Totals | C14: Irrigation Well Totals | D14: Irrigation Well Totals | E14: Irrigation Well Totals | F14: Irrigation Well Totals | G14: Irrigation Well Totals | H14: Irrigation Well Totals | I14: 172800 | J14: 0 | K14: 172800 | L14: 172800 | R14: 7200 | S14: 7200
C15: Shed 1 | D15: Shed 1 | E15: Shed 1 | F15: Shed 1 | G15: Shed 1 | H15: Shed 1 | I15: Shed 1 | J15: Shed 1 | K15: Shed 1 | L15: Shed 1 | M15: Shed 1
D16: 45657 | E16: 45657 | F16: Beg Bal | I16: 1238400 | J16: 0 | K16: 1238400 | L16: 1238400
A17: Shed 1 Totals | B17: Shed 1 Totals | C17: Shed 1 Totals | D17: Shed 1 Totals | E17: Shed 1 Totals | F17: Shed 1 Totals | G17: Shed 1 Totals | H17: Shed 1 Totals | I17: 1238400 | J17: 0 | K17: 1238400 | L17: 1238400 | R17: 51600 | S17: 51600
C18: Shed 2 | D18: Shed 2 | E18: Shed 2 | F18: Shed 2 | G18: Shed 2 | H18: Shed 2 | I18: Shed 2 | J18: Shed 2 | K18: Shed 2 | L18: Shed 2 | M18: Shed 2
D19: 45657 | E19: 45657 | F19: Beg Bal | I19: 960000 | J19: 0 | K19: 960000 | L19: 960000
A20: Shed 2 Totals | B20: Shed 2 Totals | C20: Shed 2 Totals | D20: Shed 2 Totals | E20: Shed 2 Totals | F20: Shed 2 Totals | G20: Shed 2 Totals | H20: Shed 2 Totals | I20: 960000 | J20: 0 | K20: 960000 | L20: 960000 | R20: 40000 | S20: 40000
C21: Shed 3 | D21: Shed 3 | E21: Shed 3 | F21: Shed 3 | G21: Shed 3 | H21: Shed 3 | I21: Shed 3 | J21: Shed 3 | K21: Shed 3 | L21: Shed 3 | M21: Shed 3
D22: 45657 | E22: 45657 | F22: Beg Bal | I22: 1152000 | J22: 0 | K22: 1152000 | L22: 1152000
A23: Shed 3 Totals | B23: Shed 3 Totals | C23: Shed 3 Totals | D23: Shed 3 Totals | E23: Shed 3 Totals | F23: Shed 3 Totals | G23: Shed 3 Totals | H23: Shed 3 Totals | I23: 1152000 | J23: 0 | K23: 1152000 | L23: 1152000 | R23: 48000 | S23: 48000
C24: Solar Project | D24: Solar Project | E24: Solar Project | F24: Solar Project | G24: Solar Project | H24: Solar Project | I24: Solar Project | J24: Solar Project | K24: Solar Project | L24: Solar Project | M24: Solar Project
D25: 45657 | E25: 45657 | F25: Beg Bal | I25: 60960 | J25: 0 | K25: 60960 | L25: 60960
A26: Solar Project Totals | B26: Solar Project Totals | C26: Solar Project Totals | D26: Solar Project Totals | E26: Solar Project Totals | F26: Solar Project Totals | G26: Solar Project Totals | H26: Solar Project Totals | I26: 60960 | J26: 0 | K26: 60960 | L26: 60960 | R26: 2540 | S26: 2540
C27: Structures from Land Purchase | D27: Structures from Land Purchase | E27: Structures from Land Purchase | F27: Structures from Land Purchase | G27: Structures from Land Purchase | H27: Structures from Land Purchase | I27: Structures from Land Purchase | J27: Structures from Land Purchase | K27: Structures from Land Purchase | L27: Structures from Land Purchase | M27: Structures from Land Purchase
D28: 45657 | E28: 45657 | F28: Beg Bal | I28: 8768621.7 | J28: 0 | K28: 8768621.7 | L28: 8768621.7
A29: Structures from Land Purchase Totals | B29: Structures from Land Purchase Totals | C29: Structures from Land Purchase Totals | D29: Structures from Land Purchase Totals | E29: Structures from Land Purchase Totals | F29: Structures from Land Purchase Totals | G29: Structures from Land Purchase Totals | H29: Structures from Land Purchase Totals | I29: 8768621.7 | J29: 0 | K29: 8768621.7 | L29: 8768621.7 | R29: 365359.23 | S29: 365359.23
C30: Water Tank 1 | D30: Water Tank 1 | E30: Water Tank 1 | F30: Water Tank 1 | G30: Water Tank 1 | H30: Water Tank 1 | I30: Water Tank 1 | J30: Water Tank 1 | K30: Water Tank 1 | L30: Water Tank 1 | M30: Water Tank 1
D31: 45657 | E31: 45657 | F31: Beg Bal | I31: 9984 | J31: 0 | K31: 9984 | L31: 9984
A32: Water Tank 1 Totals | B32: Water Tank 1 Totals | C32: Water Tank 1 Totals | D32: Water Tank 1 Totals | E32: Water Tank 1 Totals | F32: Water Tank 1 Totals | G32: Water Tank 1 Totals | H32: Water Tank 1 Totals | I32: 9984 | J32: 0 | K32: 9984 | L32: 9984 | R32: 416 | S32: 416
C33: Water Tank 2 | D33: Water Tank 2 | E33: Water Tank 2 | F33: Water Tank 2 | G33: Water Tank 2 | H33: Water Tank 2 | I33: Water Tank 2 | J33: Water Tank 2 | K33: Water Tank 2 | L33: Water Tank 2 | M33: Water Tank 2
D34: 45657 | E34: 45657 | F34: Beg Bal | I34: 21216 | J34: 0 | K34: 21216 | L34: 21216
A35: Water Tank 2 Totals | B35: Water Tank 2 Totals | C35: Water Tank 2 Totals | D35: Water Tank 2 Totals | E35: Water Tank 2 Totals | F35: Water Tank 2 Totals | G35: Water Tank 2 Totals | H35: Water Tank 2 Totals | I35: 21216 | J35: 0 | K35: 21216 | L35: 21216 | R35: 884 | S35: 884
C36: Water Tank 3 | D36: Water Tank 3 | E36: Water Tank 3 | F36: Water Tank 3 | G36: Water Tank 3 | H36: Water Tank 3 | I36: Water Tank 3 | J36: Water Tank 3 | K36: Water Tank 3 | L36: Water Tank 3 | M36: Water Tank 3
D37: 45657 | E37: 45657 | F37: Beg Bal | I37: 31200 | J37: 0 | K37: 31200 | L37: 31200
A38: Water Tank 3 Totals | B38: Water Tank 3 Totals | C38: Water Tank 3 Totals | D38: Water Tank 3 Totals | E38: Water Tank 3 Totals | F38: Water Tank 3 Totals | G38: Water Tank 3 Totals | H38: Water Tank 3 Totals | I38: 31200 | J38: 0 | K38: 31200 | L38: 31200 | R38: 1300 | S38: 1300
A40: Machinery & Equipment | B40: Machinery & Equipment | C40: Machinery & Equipment | D40: Machinery & Equipment | E40: Machinery & Equipment | F40: Machinery & Equipment | G40: Machinery & Equipment | H40: Machinery & Equipment | I40: Machinery & Equipment | J40: Machinery & Equipment | K40: Machinery & Equipment | L40: Machinery & Equipment | M40: Machinery & Equipment
B41: Machinery and Equipment - | C41: Machinery and Equipment - | D41: Machinery and Equipment - | E41: Machinery and Equipment - | F41: Machinery and Equipment - | G41: Machinery and Equipment - | H41: Machinery and Equipment - | I41: Machinery and Equipment - | J41: Machinery and Equipment - | K41: Machinery and Equipment - | L41: Machinery and Equipment - | M41: Machinery and Equipment -
C42: 2011 Honda NXR 150 KS OGW7606 | D42: 2011 Honda NXR 150 KS OGW7606 | E42: 2011 Honda NXR 150 KS OGW7606 | F42: 2011 Honda NXR 150 KS OGW7606 | G42: 2011 Honda NXR 150 KS OGW7606 | H42: 2011 Honda NXR 150 KS OGW7606 | I42: 2011 Honda NXR 150 KS OGW7606 | J42: 2011 Honda NXR 150 KS OGW7606 | K42: 2011 Honda NXR 150 KS OGW7606 | L42: 2011 Honda NXR 150 KS OGW7606 | M42: 2011 Honda NXR 150 KS OGW7606
D43: 45657 | E43: 45657 | F43: Beg Bal | I43: 800 | J43: 0 | K43: 800 | L43: 800
A44: 2011 Honda NXR 150 KS OGW7606 Totals | B44: 2011 Honda NXR 150 KS OGW7606 Totals | C44: 2011 Honda NXR 150 KS OGW7606 Totals | D44: 2011 Honda NXR 150 KS OGW7606 Totals | E44: 2011 Honda NXR 150 KS OGW7606 Totals | F44: 2011 Honda NXR 150 KS OGW7606 Totals | G44: 2011 Honda NXR 150 KS OGW7606 Totals | H44: 2011 Honda NXR 150 KS OGW7606 Totals | I44: 800 | J44: 0 | K44: 800 | L44: 800 | P44: 800 | Q44: 800 | R44: =P44-Q44 | S44: =K44-Q44
C45: 2016/2017 Honda Moto PKK 1003 | D45: 2016/2017 Honda Moto PKK 1003 | E45: 2016/2017 Honda Moto PKK 1003 | F45: 2016/2017 Honda Moto PKK 1003 | G45: 2016/2017 Honda Moto PKK 1003 | H45: 2016/2017 Honda Moto PKK 1003 | I45: 2016/2017 Honda Moto PKK 1003 | J45: 2016/2017 Honda Moto PKK 1003 | K45: 2016/2017 Honda Moto PKK 1003 | L45: 2016/2017 Honda Moto PKK 1003 | M45: 2016/2017 Honda Moto PKK 1003
D46: 45657 | E46: 45657 | F46: Beg Bal | I46: 12000 | J46: 0 | K46: 12000 | L46: 12000
A47: 2016/2017 Honda Moto PKK 1003 Totals | B47: 2016/2017 Honda Moto PKK 1003 Totals | C47: 2016/2017 Honda Moto PKK 1003 Totals | D47: 2016/2017 Honda Moto PKK 1003 Totals | E47: 2016/2017 Honda Moto PKK 1003 Totals | F47: 2016/2017 Honda Moto PKK 1003 Totals | G47: 2016/2017 Honda Moto PKK 1003 Totals | H47: 2016/2017 Honda Moto PKK 1003 Totals | I47: 12000 | J47: 0 | K47: 12000 | L47: 12000 | P47: 12000 | Q47: 9000 | R47: =P47-Q47 | S47: =K47-Q47
C48: 2018 Descompactador Terrus | D48: 2018 Descompactador Terrus | E48: 2018 Descompactador Terrus | F48: 2018 Descompactador Terrus | G48: 2018 Descompactador Terrus | H48: 2018 Descompactador Terrus | I48: 2018 Descompactador Terrus | J48: 2018 Descompactador Terrus | K48: 2018 Descompactador Terrus | L48: 2018 Descompactador Terrus | M48: 2018 Descompactador Terrus
D49: 45657 | E49: 45657 | F49: Beg Bal | I49: 114000 | J49: 0 | K49: 114000 | L49: 114000
A50: 2018 Descompactador Terrus Totals | B50: 2018 Descompactador Terrus Totals | C50: 2018 Descompactador Terrus Totals | D50: 2018 Descompactador Terrus Totals | E50: 2018 Descompactador Terrus Totals | F50: 2018 Descompactador Terrus Totals | G50: 2018 Descompactador Terrus Totals | H50: 2018 Descompactador Terrus Totals | I50: 114000 | J50: 0 | K50: 114000 | L50: 114000 | P50: 114000 | Q50: 100000 | R50: =P50-Q50 | S50: =K50-Q50
C51: 2019 F4000 | D51: 2019 F4000 | E51: 2019 F4000 | F51: 2019 F4000 | G51: 2019 F4000 | H51: 2019 F4000 | I51: 2019 F4000 | J51: 2019 F4000 | K51: 2019 F4000 | L51: 2019 F4000 | M51: 2019 F4000
D52: 45657 | E52: 45657 | F52: Beg Bal | I52: 195000 | J52: 0 | K52: 195000 | L52: 195000
A53: 2019 F4000 Totals | B53: 2019 F4000 Totals | C53: 2019 F4000 Totals | D53: 2019 F4000 Totals | E53: 2019 F4000 Totals | F53: 2019 F4000 Totals | G53: 2019 F4000 Totals | H53: 2019 F4000 Totals | I53: 195000 | J53: 0 | K53: 195000 | L53: 195000 | P53: 195000 | Q53: 170000 | R53: =P53-Q53 | S53: =K53-Q53
C54: 2021 Drybox 4040 DN Sprayer | D54: 2021 Drybox 4040 DN Sprayer | E54: 2021 Drybox 4040 DN Sprayer | F54: 2021 Drybox 4040 DN Sprayer | G54: 2021 Drybox 4040 DN Sprayer | H54: 2021 Drybox 4040 DN Sprayer | I54: 2021 Drybox 4040 DN Sprayer | J54: 2021 Drybox 4040 DN Sprayer | K54: 2021 Drybox 4040 DN Sprayer | L54: 2021 Drybox 4040 DN Sprayer | M54: 2021 Drybox 4040 DN Sprayer
D55: 45657 | E55: 45657 | F55: Beg Bal | I55: 1150000 | J55: 0 | K55: 1150000 | L55: 1150000
A56: 2021 Drybox 4040 DN Sprayer Totals | B56: 2021 Drybox 4040 DN Sprayer Totals | C56: 2021 Drybox 4040 DN Sprayer Totals | D56: 2021 Drybox 4040 DN Sprayer Totals | E56: 2021 Drybox 4040 DN Sprayer Totals | F56: 2021 Drybox 4040 DN Sprayer Totals | G56: 2021 Drybox 4040 DN Sprayer Totals | H56: 2021 Drybox 4040 DN Sprayer Totals | I56: 1150000 | J56: 0 | K56: 1150000 | L56: 1150000 | P56: 1150000 | Q56: 1000000 | R56: =P56-Q56 | S56: =K56-Q56
C57: 2021 Leveling Disk Starplan | D57: 2021 Leveling Disk Starplan | E57: 2021 Leveling Disk Starplan | F57: 2021 Leveling Disk Starplan | G57: 2021 Leveling Disk Starplan | H57: 2021 Leveling Disk Starplan | I57: 2021 Leveling Disk Starplan | J57: 2021 Leveling Disk Starplan | K57: 2021 Leveling Disk Starplan | L57: 2021 Leveling Disk Starplan | M57: 2021 Leveling Disk Starplan
D58: 45657 | E58: 45657 | F58: Beg Bal | I58: 20000 | J58: 0 | K58: 20000 | L58: 20000
A59: 2021 Leveling Disk Starplan Totals | B59: 2021 Leveling Disk Starplan Totals | C59: 2021 Leveling Disk Starplan Totals | D59: 2021 Leveling Disk Starplan Totals | E59: 2021 Leveling Disk Starplan Totals | F59: 2021 Leveling Disk Starplan Totals | G59: 2021 Leveling Disk Starplan Totals | H59: 2021 Leveling Disk Starplan Totals | I59: 20000 | J59: 0 | K59: 20000 | L59: 20000 | P59: 20000 | Q59: 18000 | R59: =P59-Q59 | S59: =K59-Q59
C60: 2023 Niveladora Tiller A30 | D60: 2023 Niveladora Tiller A30 | E60: 2023 Niveladora Tiller A30 | F60: 2023 Niveladora Tiller A30 | G60: 2023 Niveladora Tiller A30 | H60: 2023 Niveladora Tiller A30 | I60: 2023 Niveladora Tiller A30 | J60: 2023 Niveladora Tiller A30 | K60: 2023 Niveladora Tiller A30 | L60: 2023 Niveladora Tiller A30 | M60: 2023 Niveladora Tiller A30
D61: 45657 | E61: 45657 | F61: Beg Bal | I61: 400000 | J61: 0 | K61: 400000 | L61: 400000
A62: 2023 Niveladora Tiller A30 Totals | B62: 2023 Niveladora Tiller A30 Totals | C62: 2023 Niveladora Tiller A30 Totals | D62: 2023 Niveladora Tiller A30 Totals | E62: 2023 Niveladora Tiller A30 Totals | F62: 2023 Niveladora Tiller A30 Totals | G62: 2023 Niveladora Tiller A30 Totals | H62: 2023 Niveladora Tiller A30 Totals | I62: 400000 | J62: 0 | K62: 400000 | L62: 400000 | P62: 400000 | Q62: 380000 | R62: =P62-Q62 | S62: =K62-Q62
C63: Boiler | D63: Boiler | E63: Boiler | F63: Boiler | G63: Boiler | H63: Boiler | I63: Boiler | J63: Boiler | K63: Boiler | L63: Boiler | M63: Boiler
D64: 45657 | E64: 45657 | F64: Beg Bal | I64: 654077 | J64: 0 | K64: 654077 | L64: 654077
A65: Boiler Totals | B65: Boiler Totals | C65: Boiler Totals | D65: Boiler Totals | E65: Boiler Totals | F65: Boiler Totals | G65: Boiler Totals | H65: Boiler Totals | I65: 654077 | J65: 0 | K65: 654077 | L65: 654077 | R65: 27253 | S65: 27253
C66: Chevrolet S10 18/19 QOK8422 | D66: Chevrolet S10 18/19 QOK8422 | E66: Chevrolet S10 18/19 QOK8422 | F66: Chevrolet S10 18/19 QOK8422 | G66: Chevrolet S10 18/19 QOK8422 | H66: Chevrolet S10 18/19 QOK8422 | I66: Chevrolet S10 18/19 QOK8422 | J66: Chevrolet S10 18/19 QOK8422 | K66: Chevrolet S10 18/19 QOK8422 | L66: Chevrolet S10 18/19 QOK8422 | M66: Chevrolet S10 18/19 QOK8422
D67: 45657 | E67: 45657 | F67: Beg Bal | I67: 98000 | J67: 0 | K67: 98000 | L67: 98000
A68: Chevrolet S10 18/19 QOK8422 Totals | B68: Chevrolet S10 18/19 QOK8422 Totals | C68: Chevrolet S10 18/19 QOK8422 Totals | D68: Chevrolet S10 18/19 QOK8422 Totals | E68: Chevrolet S10 18/19 QOK8422 Totals | F68: Chevrolet S10 18/19 QOK8422 Totals | G68: Chevrolet S10 18/19 QOK8422 Totals | H68: Chevrolet S10 18/19 QOK8422 Totals | I68: 98000 | J68: 0 | K68: 98000 | L68: 98000 | P68: 100000 | Q68: 90000 | R68: =P68-Q68 | S68: =K68-Q68
C69: DB Planter Com Taxa Variavel | D69: DB Planter Com Taxa Variavel | E69: DB Planter Com Taxa Variavel | F69: DB Planter Com Taxa Variavel | G69: DB Planter Com Taxa Variavel | H69: DB Planter Com Taxa Variavel | I69: DB Planter Com Taxa Variavel | J69: DB Planter Com Taxa Variavel | K69: DB Planter Com Taxa Variavel | L69: DB Planter Com Taxa Variavel | M69: DB Planter Com Taxa Variavel
D70: 45657 | E70: 45657 | F70: Beg Bal | I70: 240000 | J70: 0 | K70: 240000 | L70: 240000
A71: DB Planter Com Taxa Variavel Totals | B71: DB Planter Com Taxa Variavel Totals | C71: DB Planter Com Taxa Variavel Totals | D71: DB Planter Com Taxa Variavel Totals | E71: DB Planter Com Taxa Variavel Totals | F71: DB Planter Com Taxa Variavel Totals | G71: DB Planter Com Taxa Variavel Totals | H71: DB Planter Com Taxa Variavel Totals | I71: 240000 | J71: 0 | K71: 240000 | L71: 240000 | P71: 240000 | Q71: 216000 | R71: =P71-Q71 | S71: =K71-Q71
C72: Diesel Tank | D72: Diesel Tank | E72: Diesel Tank | F72: Diesel Tank | G72: Diesel Tank | H72: Diesel Tank | I72: Diesel Tank | J72: Diesel Tank | K72: Diesel Tank | L72: Diesel Tank | M72: Diesel Tank
D73: 45657 | E73: 45657 | F73: Beg Bal | I73: 50425.94 | J73: 0 | K73: 50425.94 | L73: 50425.94
A74: Diesel Tank Totals | B74: Diesel Tank Totals | C74: Diesel Tank Totals | D74: Diesel Tank Totals | E74: Diesel Tank Totals | F74: Diesel Tank Totals | G74: Diesel Tank Totals | H74: Diesel Tank Totals | I74: 50425.94 | J74: 0 | K74: 50425.94 | L74: 50425.94 | R74: 2101 | S74: 2101
C75: Elevator Leg 1 | D75: Elevator Leg 1 | E75: Elevator Leg 1 | F75: Elevator Leg 1 | G75: Elevator Leg 1 | H75: Elevator Leg 1 | I75: Elevator Leg 1 | J75: Elevator Leg 1 | K75: Elevator Leg 1 | L75: Elevator Leg 1 | M75: Elevator Leg 1
D76: 45657 | E76: 45657 | F76: Beg Bal | I76: 60045.28 | J76: 0 | K76: 60045.28 | L76: 60045.28
A77: Elevator Leg 1 Totals | B77: Elevator Leg 1 Totals | C77: Elevator Leg 1 Totals | D77: Elevator Leg 1 Totals | E77: Elevator Leg 1 Totals | F77: Elevator Leg 1 Totals | G77: Elevator Leg 1 Totals | H77: Elevator Leg 1 Totals | I77: 60045.28 | J77: 0 | K77: 60045.28 | L77: 60045.28 | R77: 2502 | S77: 2502
C78: Elevator Leg 2 | D78: Elevator Leg 2 | E78: Elevator Leg 2 | F78: Elevator Leg 2 | G78: Elevator Leg 2 | H78: Elevator Leg 2 | I78: Elevator Leg 2 | J78: Elevator Leg 2 | K78: Elevator Leg 2 | L78: Elevator Leg 2 | M78: Elevator Leg 2
D79: 45657 | E79: 45657 | F79: Beg Bal | I79: 78436.1 | J79: 0 | K79: 78436.1 | L79: 78436.1
A80: Elevator Leg 2 Totals | B80: Elevator Leg 2 Totals | C80: Elevator Leg 2 Totals | D80: Elevator Leg 2 Totals | E80: Elevator Leg 2 Totals | F80: Elevator Leg 2 Totals | G80: Elevator Leg 2 Totals | H80: Elevator Leg 2 Totals | I80: 78436.1 | J80: 0 | K80: 78436.1 | L80: 78436.1 | R80: 3268 | S80: 3268
C81: Elevator Leg 3 | D81: Elevator Leg 3 | E81: Elevator Leg 3 | F81: Elevator Leg 3 | G81: Elevator Leg 3 | H81: Elevator Leg 3 | I81: Elevator Leg 3 | J81: Elevator Leg 3 | K81: Elevator Leg 3 | L81: Elevator Leg 3 | M81: Elevator Leg 3
D82: 45657 | E82: 45657 | F82: Beg Bal | I82: 91049.6 | J82: 0 | K82: 91049.6 | L82: 91049.6
A83: Elevator Leg 3 Totals | B83: Elevator Leg 3 Totals | C83: Elevator Leg 3 Totals | D83: Elevator Leg 3 Totals | E83: Elevator Leg 3 Totals | F83: Elevator Leg 3 Totals | G83: Elevator Leg 3 Totals | H83: Elevator Leg 3 Totals | I83: 91049.6 | J83: 0 | K83: 91049.6 | L83: 91049.6 | R83: 3794 | S83: 3794
C84: Elevator Leg 4 | D84: Elevator Leg 4 | E84: Elevator Leg 4 | F84: Elevator Leg 4 | G84: Elevator Leg 4 | H84: Elevator Leg 4 | I84: Elevator Leg 4 | J84: Elevator Leg 4 | K84: Elevator Leg 4 | L84: Elevator Leg 4 | M84: Elevator Leg 4
D85: 45657 | E85: 45657 | F85: Beg Bal | I85: 84090.58 | J85: 0 | K85: 84090.58 | L85: 84090.58
A86: Elevator Leg 4 Totals | B86: Elevator Leg 4 Totals | C86: Elevator Leg 4 Totals | D86: Elevator Leg 4 Totals | E86: Elevator Leg 4 Totals | F86: Elevator Leg 4 Totals | G86: Elevator Leg 4 Totals | H86: Elevator Leg 4 Totals | I86: 84090.58 | J86: 0 | K86: 84090.58 | L86: 84090.58 | R86: 3504 | S86: 3504
C87: Embutidora de Graos | D87: Embutidora de Graos | E87: Embutidora de Graos | F87: Embutidora de Graos | G87: Embutidora de Graos | H87: Embutidora de Graos | I87: Embutidora de Graos | J87: Embutidora de Graos | K87: Embutidora de Graos | L87: Embutidora de Graos | M87: Embutidora de Graos
D88: 45657 | E88: 45657 | F88: Beg Bal | I88: 60000 | J88: 0 | K88: 60000 | L88: 60000
A89: Embutidora de Graos Totals | B89: Embutidora de Graos Totals | C89: Embutidora de Graos Totals | D89: Embutidora de Graos Totals | E89: Embutidora de Graos Totals | F89: Embutidora de Graos Totals | G89: Embutidora de Graos Totals | H89: Embutidora de Graos Totals | I89: 60000 | J89: 0 | K89: 60000 | L89: 60000 | P89: 60000 | Q89: 54000 | R89: =P89-Q89 | S89: =K89-Q89
C90: Esteira 1 | D90: Esteira 1 | E90: Esteira 1 | F90: Esteira 1 | G90: Esteira 1 | H90: Esteira 1 | I90: Esteira 1 | J90: Esteira 1 | K90: Esteira 1 | L90: Esteira 1 | M90: Esteira 1
D91: 45657 | E91: 45657 | F91: Beg Bal | I91: 27565.34 | J91: 0 | K91: 27565.34 | L91: 27565.34
A92: Esteira 1 Totals | B92: Esteira 1 Totals | C92: Esteira 1 Totals | D92: Esteira 1 Totals | E92: Esteira 1 Totals | F92: Esteira 1 Totals | G92: Esteira 1 Totals | H92: Esteira 1 Totals | I92: 27565.34 | J92: 0 | K92: 27565.34 | L92: 27565.34 | R92: 1149 | S92: 1149
C93: Esteira 2 | D93: Esteira 2 | E93: Esteira 2 | F93: Esteira 2 | G93: Esteira 2 | H93: Esteira 2 | I93: Esteira 2 | J93: Esteira 2 | K93: Esteira 2 | L93: Esteira 2 | M93: Esteira 2
D94: 45657 | E94: 45657 | F94: Beg Bal | I94: 45076.94 | J94: 0 | K94: 45076.94 | L94: 45076.94
A95: Esteira 2 Totals | B95: Esteira 2 Totals | C95: Esteira 2 Totals | D95: Esteira 2 Totals | E95: Esteira 2 Totals | F95: Esteira 2 Totals | G95: Esteira 2 Totals | H95: Esteira 2 Totals | I95: 45076.94 | J95: 0 | K95: 45076.94 | L95: 45076.94 | R95: 1878 | S95: 1878
C96: Esteira 3 | D96: Esteira 3 | E96: Esteira 3 | F96: Esteira 3 | G96: Esteira 3 | H96: Esteira 3 | I96: Esteira 3 | J96: Esteira 3 | K96: Esteira 3 | L96: Esteira 3 | M96: Esteira 3
D97: 45657 | E97: 45657 | F97: Beg Bal | I97: 3010.97 | J97: 0 | K97: 3010.97 | L97: 3010.97
A98: Esteira 3 Totals | B98: Esteira 3 Totals | C98: Esteira 3 Totals | D98: Esteira 3 Totals | E98: Esteira 3 Totals | F98: Esteira 3 Totals | G98: Esteira 3 Totals | H98: Esteira 3 Totals | I98: 3010.97 | J98: 0 | K98: 3010.97 | L98: 3010.97 | R98: 125 | S98: 125
C99: Extratora Silobolsa Outgrain22 | D99: Extratora Silobolsa Outgrain22 | E99: Extratora Silobolsa Outgrain22 | F99: Extratora Silobolsa Outgrain22 | G99: Extratora Silobolsa Outgrain22 | H99: Extratora Silobolsa Outgrain22 | I99: Extratora Silobolsa Outgrain22 | J99: Extratora Silobolsa Outgrain22 | K99: Extratora Silobolsa Outgrain22 | L99: Extratora Silobolsa Outgrain22 | M99: Extratora Silobolsa Outgrain22
D100: 45657 | E100: 45657 | F100: Beg Bal | I100: 100000 | J100: 0 | K100: 100000 | L100: 100000
A101: Extratora Silobolsa Outgrain22 Totals | B101: Extratora Silobolsa Outgrain22 Totals | C101: Extratora Silobolsa Outgrain22 Totals | D101: Extratora Silobolsa Outgrain22 Totals | E101: Extratora Silobolsa Outgrain22 Totals | F101: Extratora Silobolsa Outgrain22 Totals | G101: Extratora Silobolsa Outgrain22 Totals | H101: Extratora Silobolsa Outgrain22 Totals | I101: 100000 | J101: 0 | K101: 100000 | L101: 100000 | P101: 100000 | Q101: 90000 | R101: =P101-Q101 | S101: =K101-Q101
C102: F4000 2009 Branca JSA 0223 | D102: F4000 2009 Branca JSA 0223 | E102: F4000 2009 Branca JSA 0223 | F102: F4000 2009 Branca JSA 0223 | G102: F4000 2009 Branca JSA 0223 | H102: F4000 2009 Branca JSA 0223 | I102: F4000 2009 Branca JSA 0223 | J102: F4000 2009 Branca JSA 0223 | K102: F4000 2009 Branca JSA 0223 | L102: F4000 2009 Branca JSA 0223 | M102: F4000 2009 Branca JSA 0223
D103: 45657 | E103: 45657 | F103: Beg Bal | I103: 30000 | J103: 0 | K103: 30000 | L103: 30000
...

Sheet Compras 
A1: Material de Escritório | B1: Unidade | C1: Quantidade | D1: Valor unitário | E1: Valor Subtotal
A2: Papeis A4 - resma c/ 500 folhas | B2: Resma | C2: 10 | D2: 25 | E2: 250
A3: canetas Bic | B3: Und | C3: 6 | D3: 1.5 | E3: 9
A4: Marca Texto | B4: Und | C4: 2 | D4: 5.5 | E4: 11
A5: calculadora | B5: Und | C5: 1 | D5: 37 | E5: 37
A6: Fita Durex - Para embalar | B6: Und | C6: 12 | D6: 14 | E6: 168
A7: Plástico Bolha - embalar p/ transporte | B7: Rolo | C7: 2 | D7: 80 | E7: 160
A8: Pincel Permanente - p/ identificação de Mercadorias | B8: Und | C8: 4 | D8: 6.5 | E8: 26
E9: =SUM(E2:E8) | F9: valor total podemos dividir p/ as 3 Empresas ( Matriz, Filial e Agroinvest )
A10: Manutenção S10 DPT Compras | B10: Manutenção S10 DPT Compras | C10: Manutenção S10 DPT Compras | D10: Manutenção S10 DPT Compras | E10: Manutenção S10 DPT Compras
A11: Peças e Serviços | B11: Unidade | C11: Quantidade | D11: Valor Unitário | E11: Valor Subtotal
A12: Revisão Preventiva | B12: Serviço | C12: 6 | D12: 450 | E12: 4200
A13: Troca de Grade Dianteira (Acessório do para-choque) | B13: Und | C13: 1 | D13: 1000 | E13: 1000
A14: Amortecedor Traseiro | B14: pá | C14: 1 | D14: 700 | E14: 700
A15: Palheita do Parabrisa | B15: Pá | C15: 1 | D15: 144 | E15: 144
A16: pastilhas de freio ( Jogo ) | B16: pá | C16: 1 | D16: 220 | E16: 220
A17: Reparos - Lonas de Freio ( Jogo ) | B17: jogo | C17: 1 | D17: 280 | E17: 265
A18: alinhamento / balanceamento | B18: Serviço | C18: 1 | D18: 150 | E18: 150
A19: Óleo do motor Todos os Filtros | B19: KIT | C19: 6 | D19: 600 | E19: 3600
A20: Bieletas | B20: pá | C20: 1 | D20: 100 | E20: 100
A21: Pivô inferior | B21: pá | C21: 1 | D21: 300 | E21: 300
A22: Pivô Superior | B22: pá | C22: 1 | D22: 360 | E22: 360
E23: =SUM(E12:E22) | F23: valor total podemos dividir p/ as 3 Empresas ( Matriz, Filial e Agroinvest ) 2 REVISÕES PARA CADA EMPRESA.
A24: Combustível | B24: Combustível | C24: Combustível | D24: Combustível | E24: Combustível
A25: Agroservice - Matriz | B25: LT | C25: 2000 | D25: 6 | E25: 12000
A26: Agroservice - Filial ( Granja ) | B26: LT | C26: 2000 | D26: 6 | E26: 12000
A27: Agroinvest Ltda | B27: LT | C27: 1500 | D27: 6 | E27: 9000
E29: =SUM(E25:E27)
D31: Total Geral | E31: 44700

Sheet Pedro
A1: Orçamento câmeras agroinvest | B1: Orçamento câmeras agroinvest | C1: Orçamento câmeras agroinvest | D1: Orçamento câmeras agroinvest | E1: Orçamento câmeras agroinvest | F1: Orçamento câmeras agroinvest
A2: Descrição | B2: Descrição | C2: Descrição | D2: Qtd | E2: Valor Unitario | F2: Valor Final
B3: CPE intelbras wom5a mimo | D3: 4 | E3: 500 | F3: =D3*E3
B4: Caixa organizadora | D4: 4 | E4: 80 | F4: =D4*E4
B5: 300 metros cabo de rede | D5: 1 | E5: 300 | F5: =D5*E5
B6: Fita dupla Face | D6: 1 | E6: 50 | F6: =D6*E6
B7: Switch SF 800 Q+ | D7: 3 | E7: 90 | F7: =D7*E7
B8: Roteador tp link | D8: 3 | E8: 200 | F8: =D8*E8
B9: Cartão de memora Sandisk | D9: 8 | E9: 80 | F9: =D9*E9
B10: Câmera Yoosee IP | D10: 8 | E10: 180 | F10: =D10*E10
F11: =D11*E11
E12: Total | F12: =SUM(F3:F11)
A14: Solinftec | B14: Solinftec | C14: Solinftec | D14: Solinftec | E14: Solinftec
A15: Agroinvest | B15: Agroinvest | C15: Agroinvest | D15: Agroinvest | E15: Agroinvest
A16: Itens | B16: Descrição | C16: Qtd | D16: Valor unit | E16: Valor
A17: 1 | B17: RK330 01A Atmospheric Temperature e Humidity Sensor | C17: 1 | D17: 800 | E17: =D17*C17
A18: =SUM(A17+1) | B18: Ch Power Plug Jd | C18: 1 | D18: 200 | E18: =D18*C18
A19: =SUM(A18+1) | B19: Bateria Selada 12v 7ah ELGIN | C19: 1 | D19: 120 | E19: =D19*C19
A20: =SUM(A19+1) | B20: Can Reader Cable | C20: 1 | D20: 320 | E20: =D20*C20
A21: =SUM(A20+1) | B21: Radio 433 V2 Weather Station | C21: 1 | D21: 100 | E21: =D21*C21
A22: =SUM(A21+1) | B22: Antena Zgbe Mu 35Di 900 960 Mhz Sma 1Fc | C22: 1 | D22: 230 | E22: =D22*C22
A23: =SUM(A22+1) | B23: Chicote Mag X Colheita Can Ver D | C23: 1 | D23: 305 | E23: =D23*C23
A24: =SUM(A23+1) | B24: Rain Colector Davis 6463M | C24: 3 | D24: 1200 | E24: =D24*C24
A25: =SUM(A24+1) | B25: Conjunto de Fixação com Base Adesiva | C25: 1 | D25: 390 | E25: =D25*C25
A26: =SUM(A25+1) | B26: Antena Gps At 65 V2 Sma 5M C Cabo 5 Mts | C26: 1 | D26: 120 | E26: =D26*C26
A27: =SUM(A26+1) | B27: RK120 01 Wind Speed e Direction Sensor | C27: 1 | D27: 2600 | E27: =D27*C27
A28: =SUM(A27+1) | B28: Placa Nws Pcb Smt Nwts Enig Vrd 4L 1 6MM 1P R2 | C28: 1 | D28: 1000 | E28: =D28*C28
A29: =SUM(A28+1) | B29: Caixa Weather Station 2 0 PBL280 | C29: 2 | D29: 160 | E29: =D29*C29
E30: =SUM(E17:E29)*0.3

Sheet RH
A1: Lembrancinhas e Cestas | B1: Lembrancinhas e Cestas | C1: Lembrancinhas e Cestas | E1: Variados | F1: Quantidade | G1: Valor | H1: Total Mensal | I1: Total Anual | K1: Quantidade | L1: Função | M1: exame admissional | N1: exame periodico | O1: demissional | P1: Total
A2: Cesta de natal | B2: 130 | C2: =B2*13 | D2: OK | K2: 1 | L2: AUX. ADM | N2: =25 | P2: =M2+N2+O2 | R2: EXAMES - TABELA 2 | S2: VALOR
A3: Lembrança Páscoa | B3: 15 | C3: =B3*17 | D3: OK | E3: AMB (segurança) Consultoria e treinamento | G3: 2150 | H3: =G3 | I3: =H3*12 | J3: ok | K3: 1 | L3: COZINHEIRA | N3: 60 | P3: =M3+N3+O3 | R3: ASO | S3: 25
A4: Lembrança dia das mães | B4: 50 | C4: =B4*2 | D4: OK | E4: SWILE | F4: 11 | G4: 250 | H4: =F4*G4 | I4: =H4*12 | J4: ok | K4: 1 | L4: AJUDANTE | N4: 75 | P4: =M4+N4+O4 | R4: ESPIROMETRIA | S4: 25
A5: Lembrança dia dos pais | B5: 45 | C5: =B5*5 | D5: OK | E5: SWILE TEMPORÁRIOS | F5: 2 | G5: 250 | H5: =G5*F5 | I5: =H5*3 | J5: ok | K5: 1 | L5: OPERADOR DE MAQUINAS | N5: 110 | P5: =M5+N5+O5 | R5: AUDIO (audiometria) | S5: 25
A6: Brinde dia da mulher | B6: 30 | C6: =B6*2 | D6: OK | K6: 1 | L6: OPERADOR DE SILO | N6: 190 | P6: =M6+N6+O6 | R6: ACUIDADE VISUAL | S6: 25
A7: Brinde anos de empresa | B7: 50 | C7: =B7*12 | D7: OK | E7: TOTAIS | F7: TOTAIS | G7: TOTAIS | H7: =SUM(H2:H6) | I7: =SUM(I2:I6) | K7: 1 | L7: AJUDANTE | N7: 75 | P7: =M7+N7+O7 | R7: ECG - Eletrocardiograma | S7: 50
A8: Lembrança colaborador novo | B8: 10 | C8: =B8*6 | D8: ok | K8: 1 | L8: GERENTE DE FAZENDA | N8: 75 | P8: =M8+N8+O8 | R8: EEG - Eletroencefalografia | S8: 100
A9: Brinde colaborador destaque | B9: 30 | C9: =B9*4 | K9: 1 | L9: COORDENADOR DE CAMPO | N9: 68 | P9: =M9+N9+O9
A10: Boné personalizado | B10: 25 | C10: =B10*22 | K10: 1 | L10: AJUDANTE | N10: 75 | P10: =M10+N10+O10 | R10: Glicemia : 5.00 | S10: 5
A11: TOTAL | B11: TOTAL | C11: =SUM(C2:C10) | K11: TOTAL | L11: TOTAL | M11: TOTAL | N11: TOTAL | O11: TOTAL | P11: =SUM(P2:P10) | R11: Parasitologico de fezes: 8.00 | S11: 8
A12: Confraternização Final do ano | B12: Confraternização Final do ano | C12: Confraternização Final do ano | K12: CONTRATAÇÕES | L12: CONTRATAÇÕES | M12: CONTRATAÇÕES | N12: CONTRATAÇÕES | O12: CONTRATAÇÕES | P12: CONTRATAÇÕES | R12: Sumário de urina : 6.00 | S12: 6
A13: Carnes + comida + sobremesa | C13: =85*24 | D13: ok | K13: 1 | L13: TÉCNICO AGRÍCOLA | M13: 68 | O13: 68 | P13: =M13+N13+O13 | R13: Vdrl: 10.00 | S13: 10
A14: Bebidas | C14: 1000 | D14: ok | K14: 1 | L14: OPERADOR DE MÁQUINAS | M14: 108 | O14: 108 | P14: =M14+N14+O14 | R14: Hemograma : 8.00 | S14: 8
A15: Garçom | C15: 200 | D15: OK | K15: 1 | L15: MOTORISTA | M15: 262 | O15: 262 | P15: =M15+N15+O15 | R15: Colinesterase: 10 | S15: 10
A16: Prêmios | C16: 4000 | K16: 1 | L16: AJUDANTE | M16: 75 | O16: 75 | P16: =M16+N16+O16 | R16: TGO | S16: 7.5
A17: Aluguel (pesque pague) | C17: 1666.66 | K17: 1 | L17: AUX. ADM | M17: 25 | O17: 25 | P17: =M17+N17+O17 | R17: TGP | S17: 7.5
A18: Banda | C18: 700 | K18: 1 | L18: GERENTE DE PRODUÇÃO E OPERAÇÕES AGROPECUÁR | M18: 75 | O18: 75 | P18: =M18+N18+O18 | R18: TOXICOLOGICO | S18: 187
A19: Caneca personalizada | C19: 189.75 | D19: ok | K19: TOTAL | L19: TOTAL | M19: TOTAL | N19: TOTAL | O19: TOTAL | P19: =SUM(P13:P18) | R19: Cultura da fezes | S19: 20
A20: Van transporte | C20: 1800 | D20: ok | M20: =SUM(M13:M18) | O20: =SUM(O13:O18)
A21: Salgados | C21: 180
A22: TOTAL | B22: TOTAL | C22: =SUM(C13:C21) | K22: TOTAL GERAL | L22: TOTAL GERAL | M22: TOTAL GERAL | N22: TOTAL GERAL | O22: TOTAL GERAL | P22: =P11+P19 | R22: Pesquisa de fungos nas unhas | S22: 7
A23: Palestras/treinamentos/consultoria | B23: Palestras/treinamentos/consultoria | C23: Palestras/treinamentos/consultoria | R23: AVALIAÇÃO PSICOSSOCIAL | S23: 110
A24: Transporte confraternização | C24: 1800 | D24: OK
A25: Palestra/treinamento avulsos | C25: 10000 | D25: OK
A26: Nutri + Treinamento | C26: =600*5 | D26: iremos manter?
A27: Consultoria Nick | C27: =1975.29*12+1975.29*3 | D27: NICK
A28: Instituição de ensino Jovem Aprendiz (curso) | B28: 157 | C28: =B28*1 | D28: OK
A29: Metronome Nick | B29: =646.92*2 | C29: =B29*2
A30: TOTAL | C30: =SUM(C24:C29)
A31: Confraternização trimestre | B31: Confraternização trimestre | C31: Confraternização trimestre
A32: Carnes | B32: 400 | C32: =B32*3 | D32: ok
A33: Bebidas | B33: 400 | C33: =B33*3 | D33: ok
A34: TOTAL | B34: TOTAL | C34: =SUM(C32:C33)
B36: Total Geral | C36: =C11+C22+C30+C34 | H36: Total Geral | I36: =I7

Sheet Tecnico
A1: PESSOAS PARA EQUIPE TÉCNICA AGROINVEST | B1: PESSOAS PARA EQUIPE TÉCNICA AGROINVEST | C1: PESSOAS PARA EQUIPE TÉCNICA AGROINVEST | D1: PESSOAS PARA EQUIPE TÉCNICA AGROINVEST | E1: PESSOAS PARA EQUIPE TÉCNICA AGROINVEST | F1: Salario Base | G1: Insalubridade | H1: Quinquenio | I1: Reajuste Sindicato Marçõ | J1: Aumento por Merito/Empresa | K1: Horas Extras 50% | L1: Hora Extra 100% | M1: Epis QUANTIDADE SAFRA | N1: Epis QUANTIDADE SAFRA | O1: Roupa 2 pele | P1: Luva Nitrilica | Q1: Mas.Quimica facial 3M | R1: Filtro mascara quimica | S1: Meias | T1: Toalhas de Banho | U1: Botinas/safra | V1: Uniformes (Calças e camisas) | W1: Uniformes (Calças e camisas) | X1: Botas | Y1: Mascaras de Pó PFF1 | Z1: Mascaras de Pó PFF1 | AA1: Luvas de pano Multitato | AB1: Oculos Escuro ou claro | AC1: Perneiras | AD1: Protetor Auricular | AE1: Protetor Solar | AF1: Jalecos | AG1: Capa de Chuva | AH1: Canivetes | AI1: Trenas | AJ1: Cantil | AK1: Garrafas termicas | AL1: Kit forro de cama
A2: 1 * Márcio (Gerente Técnico) | B2: 1 * Márcio (Gerente Técnico) | C2: 1 * Márcio (Gerente Técnico) | D2: 1 * Márcio (Gerente Técnico) | E2: 1 * Márcio (Gerente Técnico) | F2: Incluso na Agoservice | G2: Incluso Agroservice | H2: Incluso na lista da Agroservice | I2: Incluso na lista da Agroservice | J2: Comissão | K2: 0 | L2: 0 | M2: Marcio nada | N2: Marcio nada | O2: 0 | P2: 0 | Q2: 0 | R2: 0 | S2: 0 | T2: 0 | U2: 0 | V2: 0 | W2: 0 | X2: 0 | AA2: 0 | AB2: 0 | AC2: 0 safra | AD2: 0 | AF2: 0 | AG2: 0 | AH2: 0 | AI2: 0 | AJ2: 0 | AK2: já tem | AL2: 0
A3: 2* Contratar ( Monitoramento) | B3: 2* Contratar ( Monitoramento) | C3: 2* Contratar ( Monitoramento) | D3: 2* Contratar ( Monitoramento) | E3: 2* Contratar ( Monitoramento) | F3: 2700 | G3: 8 meses | H3: não | I3: não | J3: 5 a 10% | K3: 66 horas | L3: 20 | M3: (davi cotar) | N3: (davi cotar) | O3: 2 | P3: 2 | Q3: 1 | R3: 2 | S3: Davi cotou | T3: 2 | U3: 2 pares | V3: 3 pares cada de camisas e calças | W3: 3 pares cada de camisas e calças | X3: 1 | Y3: 5 | Z3: 5 | AA3: 2 pares/safra | AB3: 1 escuro | AC3: 1 safra | AD3: 0 | AE3: 10 | AF3: 1 G | AG3: 1 | AH3: 1 | AI3: 1 | AJ3: 1 | AK3: já tem | AL3: 0
A4: 3 * Extagiario (Monitoramento) Out, Nov, Dez, Jan, fev, Mar, Abril. | B4: 3 * Extagiario (Monitoramento) Out, Nov, Dez, Jan, fev, Mar, Abril. | C4: 3 * Extagiario (Monitoramento) Out, Nov, Dez, Jan, fev, Mar, Abril. | D4: 3 * Extagiario (Monitoramento) Out, Nov, Dez, Jan, fev, Mar, Abril. | E4: 3 * Extagiario (Monitoramento) Out, Nov, Dez, Jan, fev, Mar, Abril. | F4: 1500 | G4: 6 meses | H4: Não | I4: Não | J4: Não | K4: 0 | L4: 0 | M4: Extagiario (Davi cotar) | N4: Extagiario (Davi cotar) | O4: 2 | P4: 2 | Q4: 1 | R4: 2 | S4: Davi define | T4: 2 | U4: 2 pares | V4: 3 pares cada camisas e calças | W4: 3 pares cada camisas e calças | X4: 1 | Y4: 5 | Z4: 5 | AA4: 2 pares/ safra | AB4: 1 escuro | AC4: 1/safra | AD4: 0 | AE4: 10 | AF4: 0 | AG4: 1 | AH4: 1 | AI4: 1 | AJ4: 1 | AK4: 1 | AL4: 1
A5: Charles possivelmente fora da equipe técnica | B5: Charles possivelmente fora da equipe técnica | C5: Charles possivelmente fora da equipe técnica | D5: Charles possivelmente fora da equipe técnica | E5: Charles possivelmente fora da equipe técnica | F5: 3482 | G5: 11 meses | H5: sim 5 % do base | I5: 3 a 5 % | J5: 8200 | U5: 4 pares | V5: 6 pares de calças e camisas | W5: 6 pares de calças e camisas | X5: 2 | Y5: 10 | Z5: 10 | AA5: 4 pares safra | AB5: 2 escuro | AC5: 2 safra | AE5: 10 | AF5: 1 G | AG5: 2 | AH5: 2 | AI5: 2 | AJ5: 2 | AK5: 1 | AL5: 1
A6: Motos Agroinvest | B6: Motos Agroinvest | C6: Motos Agroinvest | D6: Motos Agroinvest | E6: Motos Agroinvest | F6: Motos Agroinvest | G6: Motos Agroinvest
A7: Periodo | B7: Periodo | C7: Periodo | D7: Km total | E7: Componentes | F7: Quantidade | G7: Gasolina necessaria
A8: Moto Charles (Novembro a Março) | B8: Moto Charles (Novembro a Março) | C8: Moto Charles (Novembro a Março) | D8: 5000 | E8: Oleo do motor Quantidade | F8: 10 | G8: 300
A9: Moto Extagiario (Dezembro a Março) | B9: Moto Extagiario (Dezembro a Março) | C9: Moto Extagiario (Dezembro a Março) | D9: 3000 | E9: Oleo do motor Quantidade | F9: 10 | G9: 176
A10: Utilizar 2 motos para monitoramento | B10: Utilizar 2 motos para monitoramento | C10: Utilizar 2 motos para monitoramento | E10: Filtro de Ar | F10: 2 | G10: Total 480 lts
A12: * Quantidade de relação para moto periodo do monitoramento= 2 relação para Bros + 2 relação para Xtz
A13: * Cameras necessarias para o periodo do monitoramento= 2 cameras para Bros + 2 cameras para Xtz
A16: * Ranger Equipe Técnica = Combustivel | B16: * Ranger Equipe Técnica = Combustivel | C16: * Ranger Equipe Técnica = Combustivel
A17: Idas para Radol= 14 vistorias X 480 KM= 6720 KM | B17: Idas para Radol= 14 vistorias X 480 KM= 6720 KM | C17: Idas para Radol= 14 vistorias X 480 KM= 6720 KM
A18: Total km rodados ranger safra 21/22 | B18: Total km rodados ranger safra 21/22 | C18: 6720 KM
A19: Diesel necessário= | B19: Diesel necessário= | C19: 610 LITROS
A21: * Para Jonatan | B21: * Para Jonatan
A22: * 1 lata de tinta pequena amarela para pintura das placas | B22: * 1 lata de tinta pequena amarela para pintura das placas
A23: * Meia lata de tinta preta | B23: * Meia lata de tinta preta
A24: * 1 pincel pequeno | B24: * 1 pincel pequeno
A26: PARA SCHUH | B26: PARA SCHUH | C26: PARA SCHUH | D26: PARA SCHUH | E26: PARA SCHUH
A27: Valores aplicativo Farm Box (Agroinvest) | B27: Valores aplicativo Farm Box (Agroinvest) | C27: Valores aplicativo Farm Box (Agroinvest) | D27: Valores aplicativo Farm Box (Agroinvest) | E27: Valores aplicativo Farm Box (Agroinvest)
A28: 13558 | B28: 13558 | C28: 13558 | D28: 13558 | E28: 13558 | F28: Total
A29: Entrada R$ 2500 no mês de Agosto de 2022 | B29: Entrada R$ 2500 no mês de Agosto de 2022 | C29: Entrada R$ 2500 no mês de Agosto de 2022 | D29: Entrada R$ 2500 no mês de Agosto de 2022 | E29: Entrada R$ 2500 no mês de Agosto de 2022 | F29: Restante pagar no próxima safra 2023 | G29: Restante pagar no próxima safra 2023 | H29: =(A28-2500)
A31: Analises de Folhas | B31: Analises de Folhas | C31: Analises de Folhas | D31: Analises de Folhas | E31: Analises de Folhas
A32: Quantidade de amostras | B32: Quantidade de amostras | C32: Quantidade de amostras | D32: 15
A33: Custo atual por amostra | B33: Custo atual por amostra | C33: Custo atual por amostra | D33: 86
A34: Total | B34: Total | C34: Total | D34: =(D33*D32)
A36: Analise para identificar raça de Cisto | B36: Analise para identificar raça de Cisto | C36: Analise para identificar raça de Cisto | D36: Analise para identificar raça de Cisto | E36: Analise para identificar raça de Cisto
A37: Quantidade de amostras | B37: Quantidade de amostras | C37: Quantidade de amostras | D37: 2 | F37: Radol 3 lote 5 e radol 1 e 2
A38: Custo atual por amostra | B38: Custo atual por amostra | C38: Custo atual por amostra | D38: 700
A39: Total | B39: Total | C39: Total | D39: =(D38*D37)
A41: Safra 22-23 tem analise de solo nas areas da bela vista | B41: Safra 22-23 tem analise de solo nas areas da bela vista | C41: Safra 22-23 tem analise de solo nas areas da bela vista | D41: Preço macro e micro atual | E41: 27.5 | F41: 384 | G41: =F41*E41
A42: Safra 22-23 tem analise de solo nas areas da bela vista | B42: Safra 22-23 tem analise de solo nas areas da bela vista | C42: Safra 22-23 tem analise de solo nas areas da bela vista | D42: Preço macro atual | E42: 16 | F42: 768 | G42: =F42*E42
A44: Comprar um Quadro branco para planejamento equipe técnica preço de internet 120 cm X 90 cm | B44: Comprar um Quadro branco para planejamento equipe técnica preço de internet 120 cm X 90 cm | C44: Comprar um Quadro branco para planejamento equipe técnica preço de internet 120 cm X 90 cm | D44: 130

Sheet Oficina
B1: OFICINA | C1: OFICINA
B2: Valor | C2: Descrição
B3: 143.41 | C3: parafusos e buchas de parede
B4: 145.8 | C4: Assente sanitario, lampada led, fita crepe
B5: 2800 | C5: Cilindro oxigenio
B6: 231.53 | C6: Mangueira e conexões
B7: 50.46 | C7: parafusos e porca travante
B8: 770 | C8: Graxa blue
B9: 165 | C9: veneno para rato
B10: 129.42 | C10: oculos incorlar, antirrespingo
B11: 211.85 | C11: Lamina e serra circular para cortar grama
B12: 38.8 | C12: Plug femea
B13: 353 | C13: bandeirinha marca teste
B14: 344.92 | C14: papel toalha
... B95: 1870 | C95: Rolamentos para rolo faca

Sheet Angelo
A1: ORÇAMENTO BAZE ZERO SAFRA 2022/2023 - Esccritorio Balança Agroinvest. | B1: ORÇAMENTO BAZE ZERO SAFRA 2022/2023 - Esccritorio Balança Agroinvest. | C1: ORÇAMENTO BAZE ZERO SAFRA 2022/2023 - Esccritorio Balança Agroinvest. | D1: ORÇAMENTO BAZE ZERO SAFRA 2022/2023 - Esccritorio Balança Agroinvest.
A2: ORÇAMENTO BAZE ZERO SAFRA 2022/2023 - Esccritorio Balança Agroinvest. | B2: ORÇAMENTO BAZE ZERO SAFRA 2022/2023 - Esccritorio Balança Agroinvest. | C2: ORÇAMENTO BAZE ZERO SAFRA 2022/2023 - Esccritorio Balança Agroinvest. | D2: ORÇAMENTO BAZE ZERO SAFRA 2022/2023 - Esccritorio Balança Agroinvest.
A3: Itens | B3: Quantidade | C3: Valor | D3: Valor total
A4: Calculadora | B4: 1 | C4: 35 | D4: =B4*C4
A5: Comodato impressora 12xR$ 240 | B5: 12 | C5: 150 | D5: =B5*C5
A6: Concerto noobrak | B6: 1 | C6: 250 | D6: =B6*C6
A7: Concerto ar condicionado | B7: 1 | C7: 650 | D7: =B7*C7
A8: Caneta cx | B8: 1 | C8: 46 | D8: =B8*C8
A9: Cx com 5 mil Granpos 26/6 para grampeador | B9: 1 | C9: 25 | D9: =B9*C9
A10: Cx com 48 unidades de prendedor de papel 25mm | B10: 1 | C10: 17.5 | D10: =B10*C10
A11: Cx com 12 unidades de prendedor de papel 51mm | B11: 2 | C11: 33 | D11: =B11*C11
A12: Grampeador | B12: 1 | C12: 60 | D12: =B12*C12
A13: Lampadas para escritorio | B13: 2 | C13: 37 | D13: =B13*C13
A14: Lixeira 15 lt com pedal | B14: 0 | C14: 270 | D14: =B14*C14
A15: Marcador permanente | B15: 6 | C15: 8 | D15: =B15*C15
A16: Marca texto verde | B16: 2 | C16: 5 | D16: =B16*C16 | G16: TOTAL | H16: =D21+D29
A17: Papel A4 cx | B17: 2 | C17: 200 | D17: =B17*C17
A18: Pilhas AAA pares | B18: 2 | C18: 13 | D18: =B18*C18
A19: Ticket lavoura soja e milho | B19: 8 | C19: 40 | D19: =B19*C19
A20: Ar condicionado (manutenção) | B20: 1 | C20: 250 | D20: =B20*C20
C21: Total | D21: =SUM(D4:D20)
A24: Horas extras colaboradores | B24: horas | C24: Quantidade | D24: Valor total
A25: AUXILIAR 1: SALARIO 2.200,00 R$ | B25: HE 50% | C25: 90
A26: AUXILIAR 1: SALARIO 2.200,00 R$ | B26: HE 100% | C26: 60 | E26: Se tiver estagiario conseguimos reduzir estas.
A28: AUXILIAR 1: Estagiario Salario 1.500,00 R$ | B28: HE 50%
A29: AUXILIAR 1: Estagiario Salario 1.500,00 R$ | B29: HE 100%
A32: CUSTOS SEG COMPAY E LCI | B32: CUSTOS SEG COMPAY E LCI | C32: CUSTOS SEG COMPAY E LCI | D32: CUSTOS SEG COMPAY E LCI
A33: TRABALHO | B33: EMPRESA | C33: VALOR UNIT. | D33: VALOR TOTAL
A34: ATUALIZAÇÃO PCMSO | B34: AMB | C34: 2000 | D34: =C34*12 | G34: TOTAL | H34: =D37+D56+D74+D81+D92+D104
A35: ATUALIZAÇÃO PGRTR | B35: AMB | C35: 0 | D35: =C35*1 | E35: Com alteração da NR31 passou ser bianual renovação
A36: MENSALIDADE/e-social | B36: AMB | C36: 0
C37: Total | D37: =SUM(D34:D36)
A40: Recarga de extintores | B40: Recarga de extintores | C40: Recarga de extintores | D40: Recarga de extintores
A41: ITEM | B41: Quantidade | C41: Valor Unit. | D41: Valor total.
A42: Recarga de agua 10 Lt | B42: 6 | C42: 40 | D42: =B42*C42
A43: Recarga de agua 75 Lt | B43: 1 | C43: 140 | D43: =B43*C43
A44: Recarga de pó 4 kg | B44: 2 | C44: 60 | D44: =B44*C44
A45: Recarga de pó 6 kg | B45: 7 | C45: 80 | D45: =B45*C45
A46: Recarga de pó 8 kg | B46: 1 | C46: 85 | D46: =B46*C46
A47: Recarga de pó 12 kg | B47: 6 | C47: 100 | D47: =B47*C47
A48: Recarga de Co2 6 kg | B48: 1 | C48: 145 | D48: =B48*C48
A49: Recarga de Co2 4 kg | B49: 1 | C49: 95 | D49: =B49*C49
A50: Travas | B50: 4 | C50: 3.5 | D50: =B50*C50
A51: Pintura | B51: 5 | C51: 20 | D51: =B51*C51
A52: Difusor | B52: 1 | C52: 17 | D52: =B52*C52
A53: Teste Hidrostatico | B53: 1 | C53: 20 | D53: =B53*C53
... A55: Manometro | B55: 4 | C55: 10 | D55: =B55*C55
C56: Total | D56: =SUM(D42:D55)
A59: PRIMEIROS SOCORROS | B59: PRIMEIROS SOCORROS | C59: PRIMEIROS SOCORROS | D59: PRIMEIROS SOCORROS
A60: ITEM | B60: Quantidade | C60: Valor Unit. | D60: Valor total
A61: Algodão 50gr | B61: 5 | C61: 5 | D61: =B61*C61
A62: Atadura de crepom | B62: 13 | C62: 5 | D62: =B62*C62
A63: Compressa de gaze 7,5x7,5cm | B63: 25 | C63: 2.25 | D63: =B63*C63
A64: Cotonete | B64: 7 | C64: 3.9 | D64: =B64*C64
A65: Band eid | B65: 7 | C65: 8 | D65: =B65*C65
A66: Esparadrapo 10x4,5 cm | B66: 7 | C66: 15 | D66: =B66*C66
A67: Lanterna pequena | B67: 5 | C67: 25 | D67: =B67*C67
A68: Luvas de procedimentos cirurgico cx | B68: 1 | C68: 22 | D68: =B68*C68
A69: Sabão liquido bactericida | B69: 7 | C69: 13.84 | D69: =B69*C69
A70: Polvidine 100 ml | B70: 7 | C70: 17.76 | D70: =B70*C70
A71: Soro fisiologico 0,9% | B71: 5 | C71: 4 | D71: =B71*C71
A72: Tesoura sem ponto | B72: 4 | C72: 7 | D72: =B72*C72
A73: Caixa para colocar o material | B73: 1 | C73: 55 | D73: =B73*C73
C74: Total | D74: =SUM(D61:D73)
A76: PLACAS DE SEGURANÇA/FILTRO BEBEDOUROS | B76: PLACAS DE SEGURANÇA/FILTRO BEBEDOUROS | C76: PLACAS DE SEGURANÇA/FILTRO BEBEDOUROS | D76: PLACAS DE SEGURANÇA/FILTRO BEBEDOUROS
A77: ITEM | B77: Quantidade | C77: Valor Unit. | D77: Valor total
A78: PLACAS DE SEGURANÇA | B78: 1 | C78: 1200 | D78: 1200
A79: Filtro dos bebedouros C3 IBBL | B79: 2 | C79: 120 | D79: =B79*C79
A80: Filtro dos bebedouros 888 ACQUA GELADA | B80: 2 | C80: 80 | D80: =B80*C80
C81: Total | D81: =SUM(D78:D80)
A83: AFERIÇÕES/CALIBRAÇÕES/ INSPEÇÕES / POTABILIDADE | B83: AFERIÇÕES/CALIBRAÇÕES/ INSPEÇÕES / POTABILIDADE | C83: AFERIÇÕES/CALIBRAÇÕES/ INSPEÇÕES / POTABILIDADE | D83: AFERIÇÕES/CALIBRAÇÕES/ INSPEÇÕES / POTABILIDADE
A84: ITEM | B84: Quantidade | C84: Valor Unit. | D84: Valor total
A85: Inspeção Caldeira | B85: 1 | C85: 7875 | D85: =B85*C85
A86: Tratamanto agua caldeira | B86: 1 | C86: 7000 | D86: =B86*C86
A87: Inspeção Compressor | B87: 2 | C87: 700 | D87: =B87*C87
A88: Calibração Gasalert | B88: 2 | C88: 950 | D88: =B88*C88
A89: Aferição balança Imetro | B89: 1 | C89: 2500 | D89: =B89*C89
A90: Manutençao balança | B90: 1 | C90: 3500 | D90: =B90*C90
A91: Potabilidade agua | B91: 4 | C91: 225 | D91: =B91*C91
C92: Total | D92: =SUM(D85:D91)
A95: AMBIENTALIX ( coleta, transporte, tratamento e disposição final ) | B95: AMBIENTALIX ( coleta, transporte, tratamento e disposição final ) | C95: AMBIENTALIX ( coleta, transporte, tratamento e disposição final ) | D95: AMBIENTALIX ( coleta, transporte, tratamento e disposição final )
A96: ITEM | B96: Quantidade | C96: Valor Unit. | D96: Valor Total
A97: Lampada | B97: 5 | C97: 15 | D97: =B97*C97
A98: Baterias | B98: 20 | C98: 4.5 | D98: =B98*C98
A99: Residuos oleosos | B99: 80 | C99: 4.5 | D99: =B99*C99
A100: Residuos misto | B100: 80 | C100: 4.5 | D100: =B100*C100
A101: Rejeitos | B101: 90 | C101: 4.5 | D101: =B101*C101
A102: Plastico | B102: 60 | C102: 4.5 | D102: =B102*C102
A103: Borracha | B103: 90 | C103: 4.5 | D103: =B103*C103
C104: Total | D104: =SUM(D97:D103)
